{
  "date": "2024-12-17",
  "count": 418,
  "data": [
    {
      "rank": 1,
      "title": "南大碎尸案逝者家属喊话张译",
      "category": "社会",
      "heat": 344.41,
      "reads": 28000.0,
      "discussions": 3.8,
      "originals": 0.6,
      "date": "2024-12-17"
    },
    {
      "rank": 2,
      "title": "南大碎尸案",
      "category": "教育",
      "heat": 329.65,
      "reads": 14000.0,
      "discussions": 5.5,
      "originals": 0.8,
      "date": "2024-12-17"
    },
    {
      "rank": 3,
      "title": "王鹤棣 内涵",
      "category": "",
      "heat": 306.66,
      "reads": 12000.0,
      "discussions": 11.3,
      "originals": 1.5,
      "date": "2024-12-17"
    },
    {
      "rank": 4,
      "title": "优酷回应南大碎尸案被害人家属发文",
      "category": "社会",
      "heat": 185.32,
      "reads": 9477.8,
      "discussions": 1.0,
      "originals": 0.25,
      "date": "2024-12-17"
    },
    {
      "rank": 5,
      "title": "我走出永夜星河了 他还没走出东方青苍",
      "category": "",
      "heat": 184.06,
      "reads": 5817.6,
      "discussions": 4.4,
      "originals": 1.2,
      "date": "2024-12-17"
    },
    {
      "rank": 6,
      "title": "李建平被执行死刑",
      "category": "社会",
      "heat": 153.92,
      "reads": 5867.2,
      "discussions": 0.62,
      "originals": 0.11,
      "date": "2024-12-17"
    },
    {
      "rank": 7,
      "title": "虞书欣换头像",
      "category": "明星",
      "heat": 149.35,
      "reads": 1090.1,
      "discussions": 0.84,
      "originals": 0.24,
      "date": "2024-12-17"
    },
    {
      "rank": 8,
      "title": "贾玲回应瘦身后观众缘松动",
      "category": "明星",
      "heat": 148.25,
      "reads": 4886.9,
      "discussions": 0.54,
      "originals": 0.18,
      "date": "2024-12-17"
    },
    {
      "rank": 9,
      "title": "特朗普说美中联手可解决世界上所有问题",
      "category": "社会",
      "heat": 146.38,
      "reads": 6800.2,
      "discussions": 1.6,
      "originals": 0.23,
      "date": "2024-12-17"
    },
    {
      "rank": 10,
      "title": "程潇评论区",
      "category": "",
      "heat": 144.15,
      "reads": 3176.5,
      "discussions": 1.3,
      "originals": 0.31,
      "date": "2024-12-17"
    },
    {
      "rank": 11,
      "title": "曝iPhone17ProMax渲染图",
      "category": "财经",
      "heat": 127.7,
      "reads": 7358.4,
      "discussions": 2.7,
      "originals": 0.33,
      "date": "2024-12-17"
    },
    {
      "rank": 12,
      "title": "悉尼碎尸案发现疑似死者丈夫尸体",
      "category": "社会",
      "heat": 120.46,
      "reads": 3677.2,
      "discussions": 0.19,
      "originals": 0.04,
      "date": "2024-12-17"
    },
    {
      "rank": 13,
      "title": "王鹤棣 如果哪天我不帅了",
      "category": "",
      "heat": 115.33,
      "reads": 4063.0,
      "discussions": 5.1,
      "originals": 0.86,
      "date": "2024-12-17"
    },
    {
      "rank": 14,
      "title": "15个字概括我国当前经济形势",
      "category": "社会",
      "heat": 112.67,
      "reads": 1605.3,
      "discussions": 0.29,
      "originals": 0.06,
      "date": "2024-12-17"
    },
    {
      "rank": 15,
      "title": "殡葬单位面试要先在遗体冷藏室10分钟",
      "category": "社会",
      "heat": 111.67,
      "reads": 2910.6,
      "discussions": 0.24,
      "originals": 0.05,
      "date": "2024-12-17"
    },
    {
      "rank": 16,
      "title": "王鹤棣演唱会 打折",
      "category": "",
      "heat": 109.2,
      "reads": 2037.7,
      "discussions": 1.9,
      "originals": 0.4,
      "date": "2024-12-17"
    },
    {
      "rank": 17,
      "title": "女子去银行存370元竟全是假币",
      "category": "社会",
      "heat": 100.89,
      "reads": 3592.8,
      "discussions": 0.44,
      "originals": 0.08,
      "date": "2024-12-17"
    },
    {
      "rank": 18,
      "title": "医院拒绝回应免费为多名老人做手术",
      "category": "社会",
      "heat": 95.04,
      "reads": 6716.5,
      "discussions": 0.45,
      "originals": 0.09,
      "date": "2024-12-17"
    },
    {
      "rank": 19,
      "title": "鹿晗背头",
      "category": "明星",
      "heat": 93.28,
      "reads": 2609.3,
      "discussions": 2.1,
      "originals": 0.33,
      "date": "2024-12-17"
    },
    {
      "rank": 20,
      "title": "百草味发霉致孕妇住院事件反转",
      "category": "社会",
      "heat": 92.82,
      "reads": 4102.0,
      "discussions": 0.54,
      "originals": 0.08,
      "date": "2024-12-17"
    },
    {
      "rank": 21,
      "title": "中国经济有望持续回升有力有进",
      "category": "",
      "heat": 92.61,
      "reads": 1237.0,
      "discussions": 0.17,
      "originals": 0.03,
      "date": "2024-12-17"
    },
    {
      "rank": 22,
      "title": "万千气象看吉林",
      "category": "社会",
      "heat": 91.95,
      "reads": 3870.1,
      "discussions": 3.4,
      "originals": 0.06,
      "date": "2024-12-17"
    },
    {
      "rank": 23,
      "title": "孙俪都不敢说甄嬛只能找她",
      "category": "",
      "heat": 91.63,
      "reads": 4471.4,
      "discussions": 1.3,
      "originals": 0.36,
      "date": "2024-12-17"
    },
    {
      "rank": 24,
      "title": "私人影院790元套餐可舌吻触摸隐私部位",
      "category": "社会",
      "heat": 85.43,
      "reads": 6040.2,
      "discussions": 0.72,
      "originals": 0.13,
      "date": "2024-12-17"
    },
    {
      "rank": 25,
      "title": "我关闭了朋友圈拒绝焦虑与内耗",
      "category": "情感",
      "heat": 83.56,
      "reads": 3455.1,
      "discussions": 0.71,
      "originals": 0.15,
      "date": "2024-12-17"
    },
    {
      "rank": 26,
      "title": "世界上最早的融合菜诞生在澳门",
      "category": "社会",
      "heat": 83.52,
      "reads": 208.0,
      "discussions": 0.04,
      "originals": 0.01,
      "date": "2024-12-17"
    },
    {
      "rank": 27,
      "title": "iPhone或迎六年来首次设计大换代",
      "category": "财经",
      "heat": 82.82,
      "reads": 4255.2,
      "discussions": 0.99,
      "originals": 0.16,
      "date": "2024-12-17"
    },
    {
      "rank": 28,
      "title": "桃黑黑发长文",
      "category": "",
      "heat": 80.05,
      "reads": 423.1,
      "discussions": 0.09,
      "originals": 0.05,
      "date": "2024-12-17"
    },
    {
      "rank": 29,
      "title": "奚梦瑶被夸状态好坦言要做医美",
      "category": "明星",
      "heat": 74.98,
      "reads": 6273.9,
      "discussions": 0.57,
      "originals": 0.08,
      "date": "2024-12-17"
    },
    {
      "rank": 30,
      "title": "王鹤棣歌词 猴子温朱",
      "category": "",
      "heat": 73.65,
      "reads": 1677.2,
      "discussions": 2.0,
      "originals": 0.36,
      "date": "2024-12-17"
    },
    {
      "rank": 31,
      "title": "卢昱晓 刘亦菲在那里我也想去",
      "category": "",
      "heat": 72.21,
      "reads": 3020.8,
      "discussions": 1.1,
      "originals": 0.14,
      "date": "2024-12-17"
    },
    {
      "rank": 32,
      "title": "给宠物做殡葬真的有必要吗",
      "category": "社会",
      "heat": 72.15,
      "reads": 2715.4,
      "discussions": 0.8,
      "originals": 0.16,
      "date": "2024-12-17"
    },
    {
      "rank": 33,
      "title": "尹锡悦戒严令背后惊天阴谋曝光",
      "category": "",
      "heat": 71.8,
      "reads": 2924.5,
      "discussions": 0.49,
      "originals": 0.04,
      "date": "2024-12-17"
    },
    {
      "rank": 34,
      "title": "时宴没有被邀请",
      "category": "",
      "heat": 71.42,
      "reads": 2380.7,
      "discussions": 1.9,
      "originals": 0.29,
      "date": "2024-12-17"
    },
    {
      "rank": 35,
      "title": "高校回应男生将女生按地上强吻",
      "category": "社会",
      "heat": 68.28,
      "reads": 1503.8,
      "discussions": 0.23,
      "originals": 0.06,
      "date": "2024-12-17"
    },
    {
      "rank": 36,
      "title": "湖南卫视跨年全阵容",
      "category": "综艺",
      "heat": 67.93,
      "reads": 32000.0,
      "discussions": 274.9,
      "originals": 0.63,
      "date": "2024-12-17"
    },
    {
      "rank": 37,
      "title": "主播为骗人站大楼前就说楼是自己的",
      "category": "社会",
      "heat": 67.61,
      "reads": 2997.6,
      "discussions": 0.52,
      "originals": 0.08,
      "date": "2024-12-17"
    },
    {
      "rank": 38,
      "title": "殡葬单位称在遗体冷藏室10分钟是考试方法",
      "category": "社会",
      "heat": 67.51,
      "reads": 591.5,
      "discussions": 0.02,
      "originals": 0.01,
      "date": "2024-12-17"
    },
    {
      "rank": 39,
      "title": "过境免签外国人停留时间延长为240小时",
      "category": "社会",
      "heat": 67.5,
      "reads": 2752.3,
      "discussions": 0.59,
      "originals": 0.08,
      "date": "2024-12-17"
    },
    {
      "rank": 40,
      "title": "市监局称羊汤发白是加了羊油",
      "category": "社会",
      "heat": 66.42,
      "reads": 2445.2,
      "discussions": 0.46,
      "originals": 0.05,
      "date": "2024-12-17"
    },
    {
      "rank": 41,
      "title": "为什么年轻人越来越热衷玄学",
      "category": "星座",
      "heat": 65.96,
      "reads": 163.1,
      "discussions": 0.03,
      "originals": 0.01,
      "date": "2024-12-17"
    },
    {
      "rank": 42,
      "title": "阿里巴巴将银泰卖给雅戈尔",
      "category": "社会",
      "heat": 65.91,
      "reads": 2217.7,
      "discussions": 0.29,
      "originals": 0.03,
      "date": "2024-12-17"
    },
    {
      "rank": 43,
      "title": "青知讲说人",
      "category": "社会",
      "heat": 65.6,
      "reads": 7204.7,
      "discussions": 8.3,
      "originals": 0.05,
      "date": "2024-12-17"
    },
    {
      "rank": 44,
      "title": "中国144小时变240小时",
      "category": "社会",
      "heat": 65.4,
      "reads": 5076.4,
      "discussions": 1.0,
      "originals": 0.13,
      "date": "2024-12-17"
    },
    {
      "rank": 45,
      "title": "张馨予老公接机",
      "category": "明星",
      "heat": 65.02,
      "reads": 6831.5,
      "discussions": 0.57,
      "originals": 0.12,
      "date": "2024-12-17"
    },
    {
      "rank": 46,
      "title": "免费为多名老人做手术医院已被限消",
      "category": "社会",
      "heat": 64.7,
      "reads": 514.9,
      "discussions": 0.02,
      "originals": 0.01,
      "date": "2024-12-17"
    },
    {
      "rank": 47,
      "title": "为什么创业的年轻人越来越多了",
      "category": "社会",
      "heat": 64.05,
      "reads": 698.1,
      "discussions": 0.78,
      "originals": 0.07,
      "date": "2024-12-17"
    },
    {
      "rank": 48,
      "title": "王楚钦说我们跨年见",
      "category": "",
      "heat": 62.35,
      "reads": 302.4,
      "discussions": 0.05,
      "originals": 0.03,
      "date": "2024-12-17"
    },
    {
      "rank": 49,
      "title": "宋墨只能活一年",
      "category": "",
      "heat": 61.57,
      "reads": 1313.9,
      "discussions": 1.3,
      "originals": 0.17,
      "date": "2024-12-17"
    },
    {
      "rank": 50,
      "title": "当你不停运动三个月后",
      "category": "",
      "heat": 60.38,
      "reads": 815.5,
      "discussions": 0.3,
      "originals": 0.06,
      "date": "2024-12-17"
    },
    {
      "rank": 51,
      "title": "江小白为啥不火了",
      "category": "社会",
      "heat": 59.51,
      "reads": 1643.2,
      "discussions": 0.27,
      "originals": 0.07,
      "date": "2024-12-17"
    },
    {
      "rank": 52,
      "title": "刁爱青家属代理律师呼吁尊重历史事实",
      "category": "社会",
      "heat": 57.42,
      "reads": 2279.0,
      "discussions": 0.26,
      "originals": 0.03,
      "date": "2024-12-17"
    },
    {
      "rank": 53,
      "title": "檀健次圆梦螺蛳粉",
      "category": "明星",
      "heat": 57.12,
      "reads": 436.5,
      "discussions": 6.6,
      "originals": 0.2,
      "date": "2024-12-17"
    },
    {
      "rank": 54,
      "title": "鹿晗猝不及防的互拍",
      "category": "",
      "heat": 56.18,
      "reads": 858.1,
      "discussions": 0.94,
      "originals": 0.12,
      "date": "2024-12-17"
    },
    {
      "rank": 55,
      "title": "特朗普称俄乌和平协议必须达成",
      "category": "财经",
      "heat": 55.54,
      "reads": 682.4,
      "discussions": 0.06,
      "originals": 0.01,
      "date": "2024-12-17"
    },
    {
      "rank": 56,
      "title": "王楚钦可口可乐活动现场",
      "category": "体育",
      "heat": 55.4,
      "reads": 2952.4,
      "discussions": 1.7,
      "originals": 0.22,
      "date": "2024-12-17"
    },
    {
      "rank": 57,
      "title": "一市民花84元买彩票中834万",
      "category": "社会",
      "heat": 55.19,
      "reads": 6255.3,
      "discussions": 1.9,
      "originals": 0.26,
      "date": "2024-12-17"
    },
    {
      "rank": 58,
      "title": "12306抢票更快的功能一定要知道",
      "category": "社会",
      "heat": 53.83,
      "reads": 2799.1,
      "discussions": 0.72,
      "originals": 0.1,
      "date": "2024-12-17"
    },
    {
      "rank": 59,
      "title": "王楚钦乒超赛后发文",
      "category": "社会",
      "heat": 53.67,
      "reads": 1825.6,
      "discussions": 0.23,
      "originals": 0.08,
      "date": "2024-12-17"
    },
    {
      "rank": 60,
      "title": "九重紫 两世死的都是济宁侯夫人",
      "category": "",
      "heat": 52.89,
      "reads": 1158.3,
      "discussions": 0.75,
      "originals": 0.07,
      "date": "2024-12-17"
    },
    {
      "rank": 61,
      "title": "大奉打更人开播时间",
      "category": "",
      "heat": 52.85,
      "reads": 1747.0,
      "discussions": 1.5,
      "originals": 0.32,
      "date": "2024-12-17"
    },
    {
      "rank": 62,
      "title": "浙江6个口岸过境免签可停留240小时",
      "category": "社会",
      "heat": 52.83,
      "reads": 1051.3,
      "discussions": 0.03,
      "originals": 0.01,
      "date": "2024-12-17"
    },
    {
      "rank": 63,
      "title": "今年外国旅客机票预订量同比增近2倍",
      "category": "财经",
      "heat": 52.83,
      "reads": 79.5,
      "discussions": 0.02,
      "originals": 0.01,
      "date": "2024-12-17"
    },
    {
      "rank": 64,
      "title": "25岁虎牙女主播酷萱疑意外去世",
      "category": "明星",
      "heat": 52.14,
      "reads": 3296.7,
      "discussions": 0.25,
      "originals": 0.04,
      "date": "2024-12-17"
    },
    {
      "rank": 65,
      "title": "和平饭店回应298元套餐仅有水和面包",
      "category": "社会",
      "heat": 51.93,
      "reads": 3606.8,
      "discussions": 0.31,
      "originals": 0.06,
      "date": "2024-12-17"
    },
    {
      "rank": 66,
      "title": "江苏卫视跨年第三波阵容官宣",
      "category": "综艺",
      "heat": 50.82,
      "reads": 69000.0,
      "discussions": 601.0,
      "originals": 0.67,
      "date": "2024-12-17"
    },
    {
      "rank": 67,
      "title": "感受声音里的多彩澳门",
      "category": "社会",
      "heat": 50.59,
      "reads": 51.9,
      "discussions": 0.01,
      "originals": 0.0,
      "date": "2024-12-17"
    },
    {
      "rank": 68,
      "title": "多账号直播展示单县羊汤变白过程",
      "category": "社会",
      "heat": 50.02,
      "reads": 2491.4,
      "discussions": 0.27,
      "originals": 0.04,
      "date": "2024-12-17"
    },
    {
      "rank": 69,
      "title": "搜狐时尚盛典",
      "category": "明星",
      "heat": 49.4,
      "reads": 141000.0,
      "discussions": 540.2,
      "originals": 1.5,
      "date": "2024-12-17"
    },
    {
      "rank": 70,
      "title": "莫斯科爆炸定性为恐怖袭击",
      "category": "社会",
      "heat": 49.27,
      "reads": 1476.9,
      "discussions": 0.16,
      "originals": 0.02,
      "date": "2024-12-17"
    },
    {
      "rank": 71,
      "title": "田嘉瑞和草莓好配",
      "category": "明星",
      "heat": 49.16,
      "reads": 1384.0,
      "discussions": 3.8,
      "originals": 0.05,
      "date": "2024-12-17"
    },
    {
      "rank": 72,
      "title": "杨幂在郭碧婷后面模仿向佐",
      "category": "明星",
      "heat": 48.94,
      "reads": 8250.9,
      "discussions": 1.2,
      "originals": 0.23,
      "date": "2024-12-17"
    },
    {
      "rank": 73,
      "title": "未婚育弟弟照护两个姐姐28年",
      "category": "社会",
      "heat": 47.87,
      "reads": 73.5,
      "discussions": 0.01,
      "originals": 0.0,
      "date": "2024-12-17"
    },
    {
      "rank": 74,
      "title": "秦兵马俑目前仅发现10尊将军俑",
      "category": "社会",
      "heat": 47.16,
      "reads": 1420.8,
      "discussions": 0.23,
      "originals": 0.04,
      "date": "2024-12-17"
    },
    {
      "rank": 75,
      "title": "九重紫团综",
      "category": "综艺",
      "heat": 47.0,
      "reads": 1937.7,
      "discussions": 0.75,
      "originals": 0.14,
      "date": "2024-12-17"
    },
    {
      "rank": 76,
      "title": "特朗普会见TikTok的CEO周受资",
      "category": "科技",
      "heat": 46.93,
      "reads": 3383.7,
      "discussions": 0.39,
      "originals": 0.07,
      "date": "2024-12-17"
    },
    {
      "rank": 77,
      "title": "原来当年拍甄嬛传时大家才20多岁",
      "category": "",
      "heat": 46.93,
      "reads": 1439.5,
      "discussions": 0.93,
      "originals": 0.07,
      "date": "2024-12-17"
    },
    {
      "rank": 78,
      "title": "赵又廷是高圆圆的情绪出口",
      "category": "",
      "heat": 46.62,
      "reads": 2464.2,
      "discussions": 0.91,
      "originals": 0.03,
      "date": "2024-12-17"
    },
    {
      "rank": 79,
      "title": "湖南一高校回应保安被曝虐狗",
      "category": "社会",
      "heat": 45.56,
      "reads": 80.3,
      "discussions": 0.01,
      "originals": 0.0,
      "date": "2024-12-17"
    },
    {
      "rank": 80,
      "title": "疑似涉黄私人影院注册资本仅10万",
      "category": "社会",
      "heat": 45.07,
      "reads": 2333.8,
      "discussions": 0.12,
      "originals": 0.03,
      "date": "2024-12-17"
    },
    {
      "rank": 81,
      "title": "南大碎尸案家属回应张译躺枪",
      "category": "社会",
      "heat": 44.66,
      "reads": 3935.1,
      "discussions": 0.27,
      "originals": 0.06,
      "date": "2024-12-17"
    },
    {
      "rank": 82,
      "title": "樊振东王楚钦 爆分",
      "category": "",
      "heat": 43.91,
      "reads": 4460.8,
      "discussions": 3.5,
      "originals": 0.51,
      "date": "2024-12-17"
    },
    {
      "rank": 83,
      "title": "陈梦马龙对瓶喝啤酒看呆其他选手",
      "category": "体育",
      "heat": 42.43,
      "reads": 1723.9,
      "discussions": 0.09,
      "originals": 0.02,
      "date": "2024-12-17"
    },
    {
      "rank": 84,
      "title": "丁程鑫后援会官博发文",
      "category": "明星",
      "heat": 42.42,
      "reads": 562.2,
      "discussions": 0.48,
      "originals": 0.11,
      "date": "2024-12-17"
    },
    {
      "rank": 85,
      "title": "南大碎尸案家属称剧方不愿公开道歉",
      "category": "社会",
      "heat": 42.38,
      "reads": 191.6,
      "discussions": 0.02,
      "originals": 0.0,
      "date": "2024-12-17"
    },
    {
      "rank": 86,
      "title": "这件衣服救过孙俪的命吗",
      "category": "",
      "heat": 42.29,
      "reads": 2365.8,
      "discussions": 0.16,
      "originals": 0.04,
      "date": "2024-12-17"
    },
    {
      "rank": 87,
      "title": "杨幂对接回应嘉人红毯顺序",
      "category": "明星",
      "heat": 42.1,
      "reads": 7550.9,
      "discussions": 1.6,
      "originals": 0.18,
      "date": "2024-12-17"
    },
    {
      "rank": 88,
      "title": "家长称学校用数智家校查成绩要付费",
      "category": "社会",
      "heat": 42.03,
      "reads": 116.9,
      "discussions": 0.02,
      "originals": 0.0,
      "date": "2024-12-17"
    },
    {
      "rank": 89,
      "title": "外交部回应韩国流行周五下班去中国",
      "category": "社会",
      "heat": 41.88,
      "reads": 1725.4,
      "discussions": 0.35,
      "originals": 0.04,
      "date": "2024-12-17"
    },
    {
      "rank": 90,
      "title": "余衍隆曝阿娇变胖原因",
      "category": "明星",
      "heat": 41.83,
      "reads": 8214.3,
      "discussions": 0.39,
      "originals": 0.07,
      "date": "2024-12-17"
    },
    {
      "rank": 91,
      "title": "孟子义和徐志胜女友煲电话粥",
      "category": "",
      "heat": 41.03,
      "reads": 2527.0,
      "discussions": 0.63,
      "originals": 0.03,
      "date": "2024-12-17"
    },
    {
      "rank": 92,
      "title": "李昀锐十天涨粉百万",
      "category": "明星",
      "heat": 40.98,
      "reads": 2665.6,
      "discussions": 1.1,
      "originals": 0.17,
      "date": "2024-12-17"
    },
    {
      "rank": 93,
      "title": "救场",
      "category": "",
      "heat": 40.65,
      "reads": 2103.4,
      "discussions": 1.5,
      "originals": 0.28,
      "date": "2024-12-17"
    },
    {
      "rank": 94,
      "title": "用户被移动分类为非家庭决策人",
      "category": "社会",
      "heat": 40.63,
      "reads": 64.7,
      "discussions": 0.0,
      "originals": 0.0,
      "date": "2024-12-17"
    },
    {
      "rank": 95,
      "title": "杨紫 唯一90花",
      "category": "",
      "heat": 40.01,
      "reads": 2324.7,
      "discussions": 4.1,
      "originals": 0.55,
      "date": "2024-12-17"
    },
    {
      "rank": 96,
      "title": "2025斯诺克德国大师赛",
      "category": "",
      "heat": 39.06,
      "reads": 162.4,
      "discussions": 0.03,
      "originals": 0.0,
      "date": "2024-12-17"
    },
    {
      "rank": 97,
      "title": "死者父亲称已与儿媳达成和解",
      "category": "社会",
      "heat": 39.05,
      "reads": 8286.6,
      "discussions": 0.7,
      "originals": 0.08,
      "date": "2024-12-17"
    },
    {
      "rank": 98,
      "title": "沈腾 坏了冲我来的",
      "category": "",
      "heat": 38.73,
      "reads": 1066.8,
      "discussions": 0.81,
      "originals": 0.17,
      "date": "2024-12-17"
    },
    {
      "rank": 99,
      "title": "全国散打季军遭多名运动员群殴",
      "category": "社会",
      "heat": 38.62,
      "reads": 802.2,
      "discussions": 0.06,
      "originals": 0.01,
      "date": "2024-12-17"
    },
    {
      "rank": 100,
      "title": "谢娜胡歌高圆圆20年好友",
      "category": "综艺",
      "heat": 38.55,
      "reads": 1702.0,
      "discussions": 0.32,
      "originals": 0.03,
      "date": "2024-12-17"
    },
    {
      "rank": 101,
      "title": "肖战路透",
      "category": "",
      "heat": 38.46,
      "reads": 17000.0,
      "discussions": 14.0,
      "originals": 1.0,
      "date": "2024-12-17"
    },
    {
      "rank": 102,
      "title": "被二姨拐卖28年男子称只憎恶人贩",
      "category": "社会",
      "heat": 38.4,
      "reads": 14.7,
      "discussions": 0.01,
      "originals": 0.0,
      "date": "2024-12-17"
    },
    {
      "rank": 103,
      "title": "17岁男孩系自缢身亡不构成刑事案件",
      "category": "社会",
      "heat": 37.51,
      "reads": 2771.3,
      "discussions": 0.18,
      "originals": 0.03,
      "date": "2024-12-17"
    },
    {
      "rank": 104,
      "title": "王楚钦汪苏泷同台",
      "category": "社会",
      "heat": 37.19,
      "reads": 1882.2,
      "discussions": 0.34,
      "originals": 0.09,
      "date": "2024-12-17"
    },
    {
      "rank": 105,
      "title": "中国代表在安理会驳斥美国无端指责",
      "category": "",
      "heat": 35.85,
      "reads": 283.6,
      "discussions": 0.03,
      "originals": 0.01,
      "date": "2024-12-17"
    },
    {
      "rank": 106,
      "title": "中国海警回应菲向仁爱礁坐滩军舰运补",
      "category": "社会",
      "heat": 35.7,
      "reads": 75.6,
      "discussions": 0.0,
      "originals": 0.0,
      "date": "2024-12-17"
    },
    {
      "rank": 107,
      "title": "孟子义对李昀锐撒娇要衣服",
      "category": "综艺",
      "heat": 35.67,
      "reads": 2242.5,
      "discussions": 0.95,
      "originals": 0.12,
      "date": "2024-12-17"
    },
    {
      "rank": 108,
      "title": "被抱养女子生父母称认亲并非为养老",
      "category": "社会",
      "heat": 35.23,
      "reads": 219.9,
      "discussions": 0.03,
      "originals": 0.01,
      "date": "2024-12-17"
    },
    {
      "rank": 109,
      "title": "阿娇早期微博三大业务",
      "category": "",
      "heat": 35.14,
      "reads": 926.6,
      "discussions": 0.11,
      "originals": 0.02,
      "date": "2024-12-17"
    },
    {
      "rank": 110,
      "title": "2025年火车票明天起售",
      "category": "社会",
      "heat": 34.97,
      "reads": 663.7,
      "discussions": 0.39,
      "originals": 0.06,
      "date": "2024-12-17"
    },
    {
      "rank": 111,
      "title": "樊振东3比1胜王楚钦",
      "category": "社会",
      "heat": 34.78,
      "reads": 7955.5,
      "discussions": 4.7,
      "originals": 0.63,
      "date": "2024-12-17"
    },
    {
      "rank": 112,
      "title": "成毅官宣出演长安二十四计",
      "category": "电视剧",
      "heat": 34.2,
      "reads": 1385.1,
      "discussions": 2.0,
      "originals": 0.38,
      "date": "2024-12-17"
    },
    {
      "rank": 113,
      "title": "河南一景区回应用假雪冒充真雪",
      "category": "社会",
      "heat": 33.77,
      "reads": 175.2,
      "discussions": 0.01,
      "originals": 0.0,
      "date": "2024-12-17"
    },
    {
      "rank": 114,
      "title": "王楚钦说与樊振东的技术差不多",
      "category": "社会",
      "heat": 33.62,
      "reads": 2771.2,
      "discussions": 1.2,
      "originals": 0.21,
      "date": "2024-12-17"
    },
    {
      "rank": 115,
      "title": "租轮椅就不排队爱心通道别被钻空子",
      "category": "社会",
      "heat": 33.56,
      "reads": 102.5,
      "discussions": 0.01,
      "originals": 0.0,
      "date": "2024-12-17"
    },
    {
      "rank": 116,
      "title": "林诗栋谈樊振东对阵王楚钦",
      "category": "社会",
      "heat": 33.45,
      "reads": 809.8,
      "discussions": 0.1,
      "originals": 0.02,
      "date": "2024-12-17"
    },
    {
      "rank": 117,
      "title": "给东方青苍配音磕一个",
      "category": "",
      "heat": 33.41,
      "reads": 1104.1,
      "discussions": 0.99,
      "originals": 0.21,
      "date": "2024-12-17"
    },
    {
      "rank": 118,
      "title": "王灿",
      "category": "明星",
      "heat": 33.21,
      "reads": 5303.8,
      "discussions": 2.3,
      "originals": 0.17,
      "date": "2024-12-17"
    },
    {
      "rank": 119,
      "title": "上海地铁乘客互骂女子怒问你上海几套房",
      "category": "社会",
      "heat": 33.13,
      "reads": 285.0,
      "discussions": 0.03,
      "originals": 0.01,
      "date": "2024-12-17"
    },
    {
      "rank": 120,
      "title": "贾玲说观众是我心底里的光",
      "category": "社会",
      "heat": 32.77,
      "reads": 1249.8,
      "discussions": 0.79,
      "originals": 0.03,
      "date": "2024-12-17"
    },
    {
      "rank": 121,
      "title": "江西一学生发表涉樊振东的不当言论",
      "category": "社会",
      "heat": 32.28,
      "reads": 2906.7,
      "discussions": 1.3,
      "originals": 0.17,
      "date": "2024-12-17"
    },
    {
      "rank": 122,
      "title": "刘亦菲孔雀绿裙",
      "category": "明星",
      "heat": 32.2,
      "reads": 1387.0,
      "discussions": 0.37,
      "originals": 0.05,
      "date": "2024-12-17"
    },
    {
      "rank": 123,
      "title": "网曝教师伪造邀请函致学生被拒签",
      "category": "社会",
      "heat": 32.2,
      "reads": 75.5,
      "discussions": 0.0,
      "originals": 0.0,
      "date": "2024-12-17"
    },
    {
      "rank": 124,
      "title": "媒体谈医院免费为老人做手术",
      "category": "社会",
      "heat": 32.05,
      "reads": 172.5,
      "discussions": 0.01,
      "originals": 0.0,
      "date": "2024-12-17"
    },
    {
      "rank": 125,
      "title": "吴启华说演金庸作品是演员的梦想",
      "category": "明星",
      "heat": 31.92,
      "reads": 89.5,
      "discussions": 0.17,
      "originals": 0.02,
      "date": "2024-12-17"
    },
    {
      "rank": 126,
      "title": "叠纸起诉派克特",
      "category": "明星",
      "heat": 31.9,
      "reads": 862.8,
      "discussions": 0.49,
      "originals": 0.12,
      "date": "2024-12-17"
    },
    {
      "rank": 127,
      "title": "男子患病躺板车30年靠养鹅养活自己",
      "category": "社会",
      "heat": 31.84,
      "reads": 169.4,
      "discussions": 0.02,
      "originals": 0.01,
      "date": "2024-12-17"
    },
    {
      "rank": 128,
      "title": "第一次见地铁户型的家",
      "category": "",
      "heat": 31.72,
      "reads": 620.2,
      "discussions": 0.13,
      "originals": 0.02,
      "date": "2024-12-17"
    },
    {
      "rank": 129,
      "title": "清密15年前浮尸命案再犯案",
      "category": "电视剧",
      "heat": 31.63,
      "reads": 193.3,
      "discussions": 0.45,
      "originals": 0.02,
      "date": "2024-12-17"
    },
    {
      "rank": 130,
      "title": "连云港一村支书4次被处分仍在职",
      "category": "社会",
      "heat": 31.55,
      "reads": 187.8,
      "discussions": 0.03,
      "originals": 0.0,
      "date": "2024-12-17"
    },
    {
      "rank": 131,
      "title": "老板称B太一天吃了七八家店",
      "category": "社会",
      "heat": 31.11,
      "reads": 11000.0,
      "discussions": 0.87,
      "originals": 0.15,
      "date": "2024-12-17"
    },
    {
      "rank": 132,
      "title": "医生眼中的10个疾病面容",
      "category": "健康",
      "heat": 31.03,
      "reads": 684.6,
      "discussions": 0.07,
      "originals": 0.0,
      "date": "2024-12-17"
    },
    {
      "rank": 133,
      "title": "王楚钦想家了",
      "category": "体育",
      "heat": 31.01,
      "reads": 2784.3,
      "discussions": 5.3,
      "originals": 0.05,
      "date": "2024-12-17"
    },
    {
      "rank": 134,
      "title": "戚薇珍珠新娘造型",
      "category": "明星",
      "heat": 30.96,
      "reads": 149.0,
      "discussions": 0.1,
      "originals": 0.01,
      "date": "2024-12-17"
    },
    {
      "rank": 135,
      "title": "折月亮 林一",
      "category": "",
      "heat": 30.76,
      "reads": 430.7,
      "discussions": 0.14,
      "originals": 0.06,
      "date": "2024-12-17"
    },
    {
      "rank": 136,
      "title": "姓A的好处已经尽数体现了",
      "category": "",
      "heat": 30.75,
      "reads": 532.1,
      "discussions": 0.18,
      "originals": 0.02,
      "date": "2024-12-17"
    },
    {
      "rank": 137,
      "title": "湖北一教师被捕兽电网电击身亡",
      "category": "社会",
      "heat": 30.69,
      "reads": 3626.7,
      "discussions": 0.28,
      "originals": 0.05,
      "date": "2024-12-17"
    },
    {
      "rank": 138,
      "title": "嘉人大合照",
      "category": "明星",
      "heat": 30.66,
      "reads": 5631.0,
      "discussions": 2.9,
      "originals": 0.3,
      "date": "2024-12-17"
    },
    {
      "rank": 139,
      "title": "最难的自律是不断突破自己",
      "category": "社会",
      "heat": 30.64,
      "reads": 248.0,
      "discussions": 0.18,
      "originals": 0.01,
      "date": "2024-12-17"
    },
    {
      "rank": 140,
      "title": "嘉人红毯 半天没人走",
      "category": "",
      "heat": 30.6,
      "reads": 10000.0,
      "discussions": 6.1,
      "originals": 0.5,
      "date": "2024-12-17"
    },
    {
      "rank": 141,
      "title": "一片药几分钱最卷集采结果出炉",
      "category": "社会",
      "heat": 30.39,
      "reads": 101.9,
      "discussions": 0.01,
      "originals": 0.0,
      "date": "2024-12-17"
    },
    {
      "rank": 142,
      "title": "张凌赫田曦薇互关微博了",
      "category": "明星",
      "heat": 30.27,
      "reads": 1172.9,
      "discussions": 0.52,
      "originals": 0.09,
      "date": "2024-12-17"
    },
    {
      "rank": 143,
      "title": "宋雨琦内娱第一个跨年舞台",
      "category": "明星",
      "heat": 30.25,
      "reads": 1011.8,
      "discussions": 0.71,
      "originals": 0.08,
      "date": "2024-12-17"
    },
    {
      "rank": 144,
      "title": "王楚钦谈和樊振东交手",
      "category": "社会",
      "heat": 30.2,
      "reads": 1700.1,
      "discussions": 0.34,
      "originals": 0.05,
      "date": "2024-12-17"
    },
    {
      "rank": 145,
      "title": "宋雨琦经纪人夸宁艺卓好看",
      "category": "明星",
      "heat": 29.43,
      "reads": 522.1,
      "discussions": 0.06,
      "originals": 0.02,
      "date": "2024-12-17"
    },
    {
      "rank": 146,
      "title": "发表涉樊振东不当言论学生已被通报",
      "category": "社会",
      "heat": 29.23,
      "reads": 4706.9,
      "discussions": 1.2,
      "originals": 0.16,
      "date": "2024-12-17"
    },
    {
      "rank": 147,
      "title": "家长从学生冬季校服中扯出薄膜",
      "category": "社会",
      "heat": 29.16,
      "reads": 1197.2,
      "discussions": 0.1,
      "originals": 0.02,
      "date": "2024-12-17"
    },
    {
      "rank": 148,
      "title": "32岁减百斤后保持三年的自律生活",
      "category": "",
      "heat": 28.83,
      "reads": 360.8,
      "discussions": 0.09,
      "originals": 0.02,
      "date": "2024-12-17"
    },
    {
      "rank": 149,
      "title": "可口可乐发布会",
      "category": "",
      "heat": 28.75,
      "reads": 3094.0,
      "discussions": 1.3,
      "originals": 0.13,
      "date": "2024-12-17"
    },
    {
      "rank": 150,
      "title": "孟子义李昀锐九重紫团综flag立上了",
      "category": "电视剧",
      "heat": 28.73,
      "reads": 1877.3,
      "discussions": 1.3,
      "originals": 0.12,
      "date": "2024-12-17"
    },
    {
      "rank": 151,
      "title": "B太称从未提过生病与羊汤有关",
      "category": "社会",
      "heat": 28.57,
      "reads": 937.3,
      "discussions": 0.05,
      "originals": 0.01,
      "date": "2024-12-17"
    },
    {
      "rank": 152,
      "title": "家长发现孩子课外书籍掺杂恶俗恶梗",
      "category": "社会",
      "heat": 28.51,
      "reads": 450.3,
      "discussions": 0.04,
      "originals": 0.01,
      "date": "2024-12-17"
    },
    {
      "rank": 153,
      "title": "九重紫",
      "category": "电视剧",
      "heat": 28.29,
      "reads": 256000.0,
      "discussions": 995.1,
      "originals": 8.1,
      "date": "2024-12-17"
    },
    {
      "rank": 154,
      "title": "男子11年结婚5次骗多名前妻上百万",
      "category": "社会",
      "heat": 28.16,
      "reads": 127.1,
      "discussions": 0.02,
      "originals": 0.01,
      "date": "2024-12-17"
    },
    {
      "rank": 155,
      "title": "虞书欣专辑试听",
      "category": "",
      "heat": 28.09,
      "reads": 356.6,
      "discussions": 0.94,
      "originals": 0.16,
      "date": "2024-12-17"
    },
    {
      "rank": 156,
      "title": "被顾客多次掌掴胖东来补偿员工30000元",
      "category": "社会",
      "heat": 27.94,
      "reads": 1721.1,
      "discussions": 0.16,
      "originals": 0.03,
      "date": "2024-12-17"
    },
    {
      "rank": 157,
      "title": "黑神话美术总监回复网友说真的好气",
      "category": "社会",
      "heat": 27.73,
      "reads": 609.8,
      "discussions": 0.05,
      "originals": 0.01,
      "date": "2024-12-17"
    },
    {
      "rank": 158,
      "title": "高校47万余元烟酒欠条背后",
      "category": "社会",
      "heat": 27.49,
      "reads": 112.2,
      "discussions": 0.01,
      "originals": 0.0,
      "date": "2024-12-17"
    },
    {
      "rank": 159,
      "title": "被抱养37年女子称高中每周只用2块",
      "category": "社会",
      "heat": 27.29,
      "reads": 2938.0,
      "discussions": 0.22,
      "originals": 0.03,
      "date": "2024-12-17"
    },
    {
      "rank": 160,
      "title": "打卡四季中国河南篇",
      "category": "社会",
      "heat": 27.19,
      "reads": 183.4,
      "discussions": 0.03,
      "originals": 0.01,
      "date": "2024-12-17"
    },
    {
      "rank": 161,
      "title": "为什么你没有小时候那么讨厌蔬菜了",
      "category": "",
      "heat": 27.19,
      "reads": 137.2,
      "discussions": 0.13,
      "originals": 0.0,
      "date": "2024-12-17"
    },
    {
      "rank": 162,
      "title": "尹锡悦确定律师团",
      "category": "社会",
      "heat": 27.16,
      "reads": 3304.7,
      "discussions": 0.24,
      "originals": 0.03,
      "date": "2024-12-17"
    },
    {
      "rank": 163,
      "title": "李昀锐的水肿不是骗人的",
      "category": "明星",
      "heat": 27.11,
      "reads": 626.4,
      "discussions": 0.53,
      "originals": 0.03,
      "date": "2024-12-17"
    },
    {
      "rank": 164,
      "title": "进一步扩大超长期特别国债发行规模",
      "category": "财经",
      "heat": 27.07,
      "reads": 172.5,
      "discussions": 0.01,
      "originals": 0.01,
      "date": "2024-12-17"
    },
    {
      "rank": 165,
      "title": "原来两个人在一起不一定因为爱情",
      "category": "",
      "heat": 27.03,
      "reads": 98.8,
      "discussions": 0.04,
      "originals": 0.01,
      "date": "2024-12-17"
    },
    {
      "rank": 166,
      "title": "一分钟get虞书欣的旅拍技巧",
      "category": "明星",
      "heat": 26.88,
      "reads": 290.8,
      "discussions": 0.27,
      "originals": 0.02,
      "date": "2024-12-17"
    },
    {
      "rank": 167,
      "title": "书店老板说开书店像一个笑话",
      "category": "社会",
      "heat": 26.68,
      "reads": 248.0,
      "discussions": 0.04,
      "originals": 0.01,
      "date": "2024-12-17"
    },
    {
      "rank": 168,
      "title": "2024令人难忘的同框",
      "category": "社会",
      "heat": 26.65,
      "reads": 872.2,
      "discussions": 0.17,
      "originals": 0.02,
      "date": "2024-12-17"
    },
    {
      "rank": 169,
      "title": "在韩国花71w韩元化妆是什么水平",
      "category": "",
      "heat": 26.58,
      "reads": 208.1,
      "discussions": 0.01,
      "originals": 0.01,
      "date": "2024-12-17"
    },
    {
      "rank": 170,
      "title": "Cici项偞婧风衣蕾丝裙清冷美",
      "category": "时尚",
      "heat": 26.37,
      "reads": 45.6,
      "discussions": 0.01,
      "originals": 0.0,
      "date": "2024-12-17"
    },
    {
      "rank": 171,
      "title": "东皇出现吓倒一片",
      "category": "",
      "heat": 26.27,
      "reads": 449.4,
      "discussions": 0.31,
      "originals": 0.06,
      "date": "2024-12-17"
    },
    {
      "rank": 172,
      "title": "刘亦菲惠英红C位",
      "category": "",
      "heat": 26.24,
      "reads": 1026.4,
      "discussions": 0.13,
      "originals": 0.03,
      "date": "2024-12-17"
    },
    {
      "rank": 173,
      "title": "B太 菏泽",
      "category": "",
      "heat": 26.14,
      "reads": 130.3,
      "discussions": 0.08,
      "originals": 0.02,
      "date": "2024-12-17"
    },
    {
      "rank": 174,
      "title": "陈梦晒图回顾老瓦杯",
      "category": "体育",
      "heat": 26.07,
      "reads": 165.2,
      "discussions": 0.02,
      "originals": 0.01,
      "date": "2024-12-17"
    },
    {
      "rank": 175,
      "title": "米饭仙人 你的菜来了",
      "category": "",
      "heat": 26.03,
      "reads": 577.8,
      "discussions": 0.07,
      "originals": 0.02,
      "date": "2024-12-17"
    },
    {
      "rank": 176,
      "title": "马思纯怎么拍成了这样",
      "category": "",
      "heat": 26.0,
      "reads": 6637.2,
      "discussions": 1.0,
      "originals": 0.28,
      "date": "2024-12-17"
    },
    {
      "rank": 177,
      "title": "离婚夫妻为争女儿互曝黑料",
      "category": "社会",
      "heat": 25.9,
      "reads": 1217.9,
      "discussions": 0.06,
      "originals": 0.02,
      "date": "2024-12-17"
    },
    {
      "rank": 178,
      "title": "陈梦谈退役后的打算",
      "category": "社会",
      "heat": 25.78,
      "reads": 193.3,
      "discussions": 0.03,
      "originals": 0.01,
      "date": "2024-12-17"
    },
    {
      "rank": 179,
      "title": "丁禹兮怕过几个月会查无此人",
      "category": "明星",
      "heat": 25.63,
      "reads": 3915.9,
      "discussions": 13.2,
      "originals": 1.0,
      "date": "2024-12-17"
    },
    {
      "rank": 180,
      "title": "陈梦再谈夺得奥运冠军感受",
      "category": "社会",
      "heat": 25.62,
      "reads": 895.3,
      "discussions": 0.27,
      "originals": 0.05,
      "date": "2024-12-17"
    },
    {
      "rank": 181,
      "title": "白百何 淡颜",
      "category": "",
      "heat": 25.45,
      "reads": 34.4,
      "discussions": 0.43,
      "originals": 0.01,
      "date": "2024-12-17"
    },
    {
      "rank": 182,
      "title": "小伙见女生被偷拍上前阻止遭殴打",
      "category": "社会",
      "heat": 25.36,
      "reads": 1909.0,
      "discussions": 0.34,
      "originals": 0.05,
      "date": "2024-12-17"
    },
    {
      "rank": 183,
      "title": "谁模仿王鹤棣",
      "category": "",
      "heat": 24.94,
      "reads": 3676.4,
      "discussions": 4.2,
      "originals": 0.47,
      "date": "2024-12-17"
    },
    {
      "rank": 184,
      "title": "刘诗诗时尚芭莎2025开年刊",
      "category": "明星",
      "heat": 24.86,
      "reads": 147.3,
      "discussions": 0.01,
      "originals": 0.01,
      "date": "2024-12-17"
    },
    {
      "rank": 185,
      "title": "国漫不一定要赢但是别认",
      "category": "动漫",
      "heat": 24.37,
      "reads": 275.2,
      "discussions": 0.5,
      "originals": 0.05,
      "date": "2024-12-17"
    },
    {
      "rank": 186,
      "title": "可口可乐代言人",
      "category": "",
      "heat": 24.37,
      "reads": 1352.1,
      "discussions": 0.68,
      "originals": 0.1,
      "date": "2024-12-17"
    },
    {
      "rank": 187,
      "title": "最美的夜跨年首波阵容官宣",
      "category": "综艺",
      "heat": 24.21,
      "reads": 373.6,
      "discussions": 16.3,
      "originals": 0.03,
      "date": "2024-12-17"
    },
    {
      "rank": 188,
      "title": "视听中国冰天雪地也是金山银山",
      "category": "",
      "heat": 23.85,
      "reads": 206.8,
      "discussions": 0.06,
      "originals": 0.01,
      "date": "2024-12-17"
    },
    {
      "rank": 189,
      "title": "兵马俑二号坑首次发现高级军吏俑",
      "category": "社会",
      "heat": 23.69,
      "reads": 1068.4,
      "discussions": 0.05,
      "originals": 0.01,
      "date": "2024-12-17"
    },
    {
      "rank": 190,
      "title": "B太称随行的人也拉肚子了",
      "category": "社会",
      "heat": 23.42,
      "reads": 1019.4,
      "discussions": 0.07,
      "originals": 0.02,
      "date": "2024-12-17"
    },
    {
      "rank": 191,
      "title": "长沙一游乐园马戏演员空中坠落",
      "category": "社会",
      "heat": 23.39,
      "reads": 162.0,
      "discussions": 0.02,
      "originals": 0.0,
      "date": "2024-12-17"
    },
    {
      "rank": 192,
      "title": "时代峰峻起诉马嘉祺黑粉",
      "category": "明星",
      "heat": 23.36,
      "reads": 3454.0,
      "discussions": 2.5,
      "originals": 0.51,
      "date": "2024-12-17"
    },
    {
      "rank": 193,
      "title": "澳门2049带你80分钟环游中国",
      "category": "旅游",
      "heat": 23.32,
      "reads": 860.9,
      "discussions": 2.6,
      "originals": 0.01,
      "date": "2024-12-17"
    },
    {
      "rank": 194,
      "title": "男友涉性侵或面临10年以上有期徒刑",
      "category": "社会",
      "heat": 23.17,
      "reads": 3215.9,
      "discussions": 0.27,
      "originals": 0.07,
      "date": "2024-12-17"
    },
    {
      "rank": 195,
      "title": "戚薇为什么你不能做1",
      "category": "明星",
      "heat": 23.0,
      "reads": 401.8,
      "discussions": 0.29,
      "originals": 0.0,
      "date": "2024-12-17"
    },
    {
      "rank": 196,
      "title": "田曦薇方称逐玉绝对平番",
      "category": "明星",
      "heat": 22.98,
      "reads": 2037.7,
      "discussions": 0.67,
      "originals": 0.11,
      "date": "2024-12-17"
    },
    {
      "rank": 197,
      "title": "夏之光说九重紫演爽了",
      "category": "明星",
      "heat": 22.93,
      "reads": 696.0,
      "discussions": 0.43,
      "originals": 0.05,
      "date": "2024-12-17"
    },
    {
      "rank": 198,
      "title": "Falcom创始人去世",
      "category": "游戏",
      "heat": 22.86,
      "reads": 275.2,
      "discussions": 0.02,
      "originals": 0.0,
      "date": "2024-12-17"
    },
    {
      "rank": 199,
      "title": "桃黑黑女寝系列",
      "category": "",
      "heat": 22.69,
      "reads": 7.8,
      "discussions": 0.01,
      "originals": 0.01,
      "date": "2024-12-17"
    },
    {
      "rank": 200,
      "title": "潘展乐说游不动了是真游不动了",
      "category": "社会",
      "heat": 22.61,
      "reads": 1354.0,
      "discussions": 0.04,
      "originals": 0.01,
      "date": "2024-12-17"
    },
    {
      "rank": 201,
      "title": "领克Z10城市NOA首测直播",
      "category": "汽车",
      "heat": 22.6,
      "reads": 1108.1,
      "discussions": 0.34,
      "originals": 0.01,
      "date": "2024-12-17"
    },
    {
      "rank": 202,
      "title": "家族资产30亿豪门艺人王贤志申请破产",
      "category": "明星",
      "heat": 22.51,
      "reads": 181.5,
      "discussions": 0.0,
      "originals": 0.0,
      "date": "2024-12-17"
    },
    {
      "rank": 203,
      "title": "但是我可以选择我的未来",
      "category": "",
      "heat": 22.45,
      "reads": 3.6,
      "discussions": 0.0,
      "originals": 0.0,
      "date": "2024-12-17"
    },
    {
      "rank": 204,
      "title": "杨幂工作室发了时代姐妹花",
      "category": "明星",
      "heat": 22.4,
      "reads": 1818.3,
      "discussions": 0.62,
      "originals": 0.09,
      "date": "2024-12-17"
    },
    {
      "rank": 205,
      "title": "窦昭专治小妈发癫",
      "category": "",
      "heat": 22.39,
      "reads": 48.7,
      "discussions": 0.47,
      "originals": 0.02,
      "date": "2024-12-17"
    },
    {
      "rank": 206,
      "title": "好适合吃饺子的盘子",
      "category": "",
      "heat": 22.3,
      "reads": 306.2,
      "discussions": 0.08,
      "originals": 0.01,
      "date": "2024-12-17"
    },
    {
      "rank": 207,
      "title": "九重紫王映雪下线",
      "category": "",
      "heat": 22.18,
      "reads": 5601.8,
      "discussions": 0.76,
      "originals": 0.03,
      "date": "2024-12-17"
    },
    {
      "rank": 208,
      "title": "女主角搞事业已成古装剧热门赛道",
      "category": "电视剧",
      "heat": 22.13,
      "reads": 137.2,
      "discussions": 0.02,
      "originals": 0.0,
      "date": "2024-12-17"
    },
    {
      "rank": 209,
      "title": "于适入选辽宁朝阳青联委员",
      "category": "明星",
      "heat": 22.12,
      "reads": 182.4,
      "discussions": 0.34,
      "originals": 0.04,
      "date": "2024-12-17"
    },
    {
      "rank": 210,
      "title": "抽象能力成了年轻人社交硬通货",
      "category": "社会",
      "heat": 22.03,
      "reads": 113.4,
      "discussions": 0.0,
      "originals": 0.0,
      "date": "2024-12-17"
    },
    {
      "rank": 211,
      "title": "知名音乐人杨立德逝世",
      "category": "明星",
      "heat": 21.84,
      "reads": 72.7,
      "discussions": 0.0,
      "originals": 0.0,
      "date": "2024-12-17"
    },
    {
      "rank": 212,
      "title": "王楚钦周启豪互动",
      "category": "体育",
      "heat": 21.81,
      "reads": 371.1,
      "discussions": 0.03,
      "originals": 0.01,
      "date": "2024-12-17"
    },
    {
      "rank": 213,
      "title": "54岁香港男星申请破产",
      "category": "明星",
      "heat": 21.76,
      "reads": 2311.5,
      "discussions": 0.05,
      "originals": 0.01,
      "date": "2024-12-17"
    },
    {
      "rank": 214,
      "title": "奇瑞风云A8L发布现场撞车",
      "category": "汽车",
      "heat": 21.66,
      "reads": 508.3,
      "discussions": 0.25,
      "originals": 0.02,
      "date": "2024-12-17"
    },
    {
      "rank": 215,
      "title": "女子付款码收款码切换间隙被盗刷",
      "category": "社会",
      "heat": 21.51,
      "reads": 328.7,
      "discussions": 0.03,
      "originals": 0.01,
      "date": "2024-12-17"
    },
    {
      "rank": 216,
      "title": "被林更新烫到了",
      "category": "",
      "heat": 21.51,
      "reads": 332.3,
      "discussions": 0.15,
      "originals": 0.02,
      "date": "2024-12-17"
    },
    {
      "rank": 217,
      "title": "杨洋汪苏泷王楚钦同框",
      "category": "",
      "heat": 21.47,
      "reads": 1899.1,
      "discussions": 1.2,
      "originals": 0.13,
      "date": "2024-12-17"
    },
    {
      "rank": 218,
      "title": "孙颖莎9900分保持世一",
      "category": "体育",
      "heat": 21.44,
      "reads": 1541.9,
      "discussions": 0.99,
      "originals": 0.24,
      "date": "2024-12-17"
    },
    {
      "rank": 219,
      "title": "Red精彩OK开年刊双封面",
      "category": "时尚",
      "heat": 21.42,
      "reads": 280.2,
      "discussions": 2.4,
      "originals": 0.04,
      "date": "2024-12-17"
    },
    {
      "rank": 220,
      "title": "沈翊戏曲妆梦回陈纫香",
      "category": "电视剧",
      "heat": 21.4,
      "reads": 275.6,
      "discussions": 1.5,
      "originals": 0.12,
      "date": "2024-12-17"
    },
    {
      "rank": 221,
      "title": "考研结束后你最想做什么事",
      "category": "",
      "heat": 21.38,
      "reads": 0.37,
      "discussions": 0.0,
      "originals": 0.0,
      "date": "2024-12-17"
    },
    {
      "rank": 222,
      "title": "马嘉祺皮埃尔定妆视频",
      "category": "明星",
      "heat": 21.37,
      "reads": 195.8,
      "discussions": 0.18,
      "originals": 0.05,
      "date": "2024-12-17"
    },
    {
      "rank": 223,
      "title": "宋旻浩服役被举报不上班",
      "category": "明星",
      "heat": 21.32,
      "reads": 1304.0,
      "discussions": 0.26,
      "originals": 0.04,
      "date": "2024-12-17"
    },
    {
      "rank": 224,
      "title": "神十九航天员第一次出舱圆满完成",
      "category": "社会",
      "heat": 21.27,
      "reads": 470.0,
      "discussions": 0.19,
      "originals": 0.01,
      "date": "2024-12-17"
    },
    {
      "rank": 225,
      "title": "俄罗斯回应俄军三防部队司令身亡",
      "category": "社会",
      "heat": 21.24,
      "reads": 599.1,
      "discussions": 0.07,
      "originals": 0.01,
      "date": "2024-12-17"
    },
    {
      "rank": 226,
      "title": "浙江大学经济学院通报",
      "category": "社会",
      "heat": 21.23,
      "reads": 352.2,
      "discussions": 0.02,
      "originals": 0.0,
      "date": "2024-12-17"
    },
    {
      "rank": 227,
      "title": "章昊回福师大了",
      "category": "",
      "heat": 21.04,
      "reads": 176.4,
      "discussions": 0.2,
      "originals": 0.06,
      "date": "2024-12-17"
    },
    {
      "rank": 228,
      "title": "设置学霸就餐区中学已整改取消",
      "category": "社会",
      "heat": 20.98,
      "reads": 253.5,
      "discussions": 0.05,
      "originals": 0.01,
      "date": "2024-12-17"
    },
    {
      "rank": 229,
      "title": "网传星光大赏座位表",
      "category": "综艺",
      "heat": 20.93,
      "reads": 560.3,
      "discussions": 0.2,
      "originals": 0.03,
      "date": "2024-12-17"
    },
    {
      "rank": 230,
      "title": "10后女生独爱鲶鱼须刘海",
      "category": "社会",
      "heat": 20.86,
      "reads": 3211.2,
      "discussions": 0.23,
      "originals": 0.05,
      "date": "2024-12-17"
    },
    {
      "rank": 231,
      "title": "曾黎不愧是把张柏芝迷住的女人",
      "category": "明星",
      "heat": 20.79,
      "reads": 59.8,
      "discussions": 0.48,
      "originals": 0.01,
      "date": "2024-12-17"
    },
    {
      "rank": 232,
      "title": "台湾旅游",
      "category": "旅游",
      "heat": 20.79,
      "reads": 18000.0,
      "discussions": 14.6,
      "originals": 1.1,
      "date": "2024-12-17"
    },
    {
      "rank": 233,
      "title": "俄罗斯中将基里洛夫在爆炸事件中丧生",
      "category": "军事",
      "heat": 20.68,
      "reads": 324.2,
      "discussions": 0.05,
      "originals": 0.01,
      "date": "2024-12-17"
    },
    {
      "rank": 234,
      "title": "杨洋活动直拍",
      "category": "",
      "heat": 20.55,
      "reads": 574.5,
      "discussions": 1.4,
      "originals": 0.11,
      "date": "2024-12-17"
    },
    {
      "rank": 235,
      "title": "李昀锐 少年感的爹",
      "category": "",
      "heat": 20.42,
      "reads": 1731.0,
      "discussions": 1.2,
      "originals": 0.2,
      "date": "2024-12-17"
    },
    {
      "rank": 236,
      "title": "梅德韦杰夫回应俄三防部队司令死亡",
      "category": "",
      "heat": 20.34,
      "reads": 580.0,
      "discussions": 0.04,
      "originals": 0.01,
      "date": "2024-12-17"
    },
    {
      "rank": 237,
      "title": "一口气看完猎罪2前五案",
      "category": "电视剧",
      "heat": 20.24,
      "reads": 49.2,
      "discussions": 0.61,
      "originals": 0.04,
      "date": "2024-12-17"
    },
    {
      "rank": 238,
      "title": "娜扎和防晒和解",
      "category": "明星",
      "heat": 20.22,
      "reads": 460.6,
      "discussions": 0.03,
      "originals": 0.0,
      "date": "2024-12-17"
    },
    {
      "rank": 239,
      "title": "白鹿 我再也不相信孟子义了",
      "category": "",
      "heat": 20.17,
      "reads": 214.2,
      "discussions": 0.5,
      "originals": 0.03,
      "date": "2024-12-17"
    },
    {
      "rank": 240,
      "title": "蜜雪冰城多门店饮品涨价1块",
      "category": "社会",
      "heat": 20.16,
      "reads": 173.1,
      "discussions": 0.01,
      "originals": 0.01,
      "date": "2024-12-17"
    },
    {
      "rank": 241,
      "title": "女子推理社",
      "category": "综艺",
      "heat": 20.0,
      "reads": 321000.0,
      "discussions": 995.5,
      "originals": 4.4,
      "date": "2024-12-17"
    },
    {
      "rank": 242,
      "title": "樊振东超级全满贯",
      "category": "体育",
      "heat": 19.87,
      "reads": 7054.6,
      "discussions": 49.3,
      "originals": 0.46,
      "date": "2024-12-17"
    },
    {
      "rank": 243,
      "title": "1个墙缝同时卡住2个孩子",
      "category": "社会",
      "heat": 19.87,
      "reads": 1092.4,
      "discussions": 0.25,
      "originals": 0.04,
      "date": "2024-12-17"
    },
    {
      "rank": 244,
      "title": "贾玲 新华社采访",
      "category": "",
      "heat": 19.79,
      "reads": 232.0,
      "discussions": 0.08,
      "originals": 0.01,
      "date": "2024-12-17"
    },
    {
      "rank": 245,
      "title": "韩国演员马东锡到底有多强",
      "category": "明星",
      "heat": 19.78,
      "reads": 2304.4,
      "discussions": 0.13,
      "originals": 0.02,
      "date": "2024-12-17"
    },
    {
      "rank": 246,
      "title": "呼伦贝尔冷到吹泡泡吹出冰球",
      "category": "社会",
      "heat": 19.78,
      "reads": 919.5,
      "discussions": 0.28,
      "originals": 0.03,
      "date": "2024-12-17"
    },
    {
      "rank": 247,
      "title": "勇敢不是天性而是选择",
      "category": "社会",
      "heat": 19.75,
      "reads": 404.1,
      "discussions": 0.18,
      "originals": 0.01,
      "date": "2024-12-17"
    },
    {
      "rank": 248,
      "title": "美国17岁女生校内开枪致3死",
      "category": "社会",
      "heat": 19.69,
      "reads": 1371.7,
      "discussions": 0.15,
      "originals": 0.03,
      "date": "2024-12-17"
    },
    {
      "rank": 249,
      "title": "自闭症孩子课间撞墙被同学温柔抱住",
      "category": "社会",
      "heat": 19.66,
      "reads": 1742.8,
      "discussions": 0.16,
      "originals": 0.03,
      "date": "2024-12-17"
    },
    {
      "rank": 250,
      "title": "快船把爵士打花了",
      "category": "体育",
      "heat": 19.58,
      "reads": 73.3,
      "discussions": 0.01,
      "originals": 0.0,
      "date": "2024-12-17"
    },
    {
      "rank": 251,
      "title": "原神 男模",
      "category": "",
      "heat": 19.57,
      "reads": 74.6,
      "discussions": 0.03,
      "originals": 0.01,
      "date": "2024-12-17"
    },
    {
      "rank": 252,
      "title": "光遇复刻",
      "category": "游戏",
      "heat": 19.48,
      "reads": 63000.0,
      "discussions": 10.8,
      "originals": 1.8,
      "date": "2024-12-17"
    },
    {
      "rank": 253,
      "title": "大奉打更人",
      "category": "电视剧",
      "heat": 19.48,
      "reads": 376000.0,
      "discussions": 4363.3,
      "originals": 144.0,
      "date": "2024-12-17"
    },
    {
      "rank": 254,
      "title": "云间",
      "category": "",
      "heat": 19.41,
      "reads": 161.9,
      "discussions": 0.21,
      "originals": 0.1,
      "date": "2024-12-17"
    },
    {
      "rank": 255,
      "title": "张馨予换了造型师",
      "category": "明星",
      "heat": 19.29,
      "reads": 124.9,
      "discussions": 0.03,
      "originals": 0.01,
      "date": "2024-12-17"
    },
    {
      "rank": 256,
      "title": "北大天文学系吴月芳教授逝世",
      "category": "社会",
      "heat": 19.06,
      "reads": 428.2,
      "discussions": 0.01,
      "originals": 0.0,
      "date": "2024-12-17"
    },
    {
      "rank": 257,
      "title": "理想汽车",
      "category": "",
      "heat": 18.85,
      "reads": 79000.0,
      "discussions": 52.5,
      "originals": 4.2,
      "date": "2024-12-17"
    },
    {
      "rank": 258,
      "title": "弟弟去世后哥哥状告弟媳争房子",
      "category": "社会",
      "heat": 18.81,
      "reads": 1125.9,
      "discussions": 0.08,
      "originals": 0.01,
      "date": "2024-12-17"
    },
    {
      "rank": 259,
      "title": "李昀锐工作室有我们自己人",
      "category": "",
      "heat": 18.77,
      "reads": 348.0,
      "discussions": 0.22,
      "originals": 0.03,
      "date": "2024-12-17"
    },
    {
      "rank": 260,
      "title": "任嘉伦直播",
      "category": "明星",
      "heat": 18.61,
      "reads": 166000.0,
      "discussions": 180.2,
      "originals": 6.3,
      "date": "2024-12-17"
    },
    {
      "rank": 261,
      "title": "女子网上兼职配音被骗走7万多",
      "category": "社会",
      "heat": 18.58,
      "reads": 137.9,
      "discussions": 0.03,
      "originals": 0.01,
      "date": "2024-12-17"
    },
    {
      "rank": 262,
      "title": "医生上报12岁女孩感染HPV反遭质问",
      "category": "社会",
      "heat": 18.58,
      "reads": 2488.7,
      "discussions": 0.36,
      "originals": 0.04,
      "date": "2024-12-17"
    },
    {
      "rank": 263,
      "title": "丁禹兮空降",
      "category": "",
      "heat": 18.48,
      "reads": 2282.7,
      "discussions": 17.4,
      "originals": 1.2,
      "date": "2024-12-17"
    },
    {
      "rank": 264,
      "title": "存款特种兵年末再现江湖",
      "category": "社会",
      "heat": 18.45,
      "reads": 92.1,
      "discussions": 0.0,
      "originals": 0.0,
      "date": "2024-12-17"
    },
    {
      "rank": 265,
      "title": "谌龙出任羽毛球国青队教练",
      "category": "体育",
      "heat": 18.4,
      "reads": 479.7,
      "discussions": 0.04,
      "originals": 0.01,
      "date": "2024-12-17"
    },
    {
      "rank": 266,
      "title": "九重紫和巴啦啦小魔仙同一个取景地",
      "category": "",
      "heat": 18.36,
      "reads": 116.0,
      "discussions": 0.1,
      "originals": 0.01,
      "date": "2024-12-17"
    },
    {
      "rank": 267,
      "title": "有一种骄傲叫舷号17",
      "category": "社会",
      "heat": 18.03,
      "reads": 798.9,
      "discussions": 0.32,
      "originals": 0.05,
      "date": "2024-12-17"
    },
    {
      "rank": 268,
      "title": "杨洋红丝绒西装",
      "category": "明星",
      "heat": 18.0,
      "reads": 1147.3,
      "discussions": 3.4,
      "originals": 0.09,
      "date": "2024-12-17"
    },
    {
      "rank": 269,
      "title": "醪糟麻薯撞奶",
      "category": "",
      "heat": 17.85,
      "reads": 0.44,
      "discussions": 0.0,
      "originals": 0.0,
      "date": "2024-12-17"
    },
    {
      "rank": 270,
      "title": "虞书欣专辑制作阵容",
      "category": "明星",
      "heat": 17.83,
      "reads": 159.5,
      "discussions": 0.06,
      "originals": 0.02,
      "date": "2024-12-17"
    },
    {
      "rank": 271,
      "title": "刘宇救场闫桉",
      "category": "",
      "heat": 17.79,
      "reads": 2026.1,
      "discussions": 0.87,
      "originals": 0.15,
      "date": "2024-12-17"
    },
    {
      "rank": 272,
      "title": "张萌演技",
      "category": "明星",
      "heat": 17.76,
      "reads": 584.3,
      "discussions": 0.59,
      "originals": 0.03,
      "date": "2024-12-17"
    },
    {
      "rank": 273,
      "title": "今年的双旦不约而同都在工作日",
      "category": "社会",
      "heat": 17.73,
      "reads": 600.4,
      "discussions": 0.18,
      "originals": 0.05,
      "date": "2024-12-17"
    },
    {
      "rank": 274,
      "title": "一家5口住也能实现独居的120平房子",
      "category": "",
      "heat": 17.52,
      "reads": 4.2,
      "discussions": 0.0,
      "originals": 0.0,
      "date": "2024-12-17"
    },
    {
      "rank": 275,
      "title": "肖战睡衣路透",
      "category": "明星",
      "heat": 17.36,
      "reads": 462.5,
      "discussions": 0.57,
      "originals": 0.12,
      "date": "2024-12-17"
    },
    {
      "rank": 276,
      "title": "乒超四强出炉",
      "category": "明星",
      "heat": 17.31,
      "reads": 857.0,
      "discussions": 0.05,
      "originals": 0.01,
      "date": "2024-12-17"
    },
    {
      "rank": 277,
      "title": "朱婷女排世俱杯首秀",
      "category": "体育",
      "heat": 17.19,
      "reads": 163.6,
      "discussions": 0.03,
      "originals": 0.01,
      "date": "2024-12-17"
    },
    {
      "rank": 278,
      "title": "虞书欣老舅合作新专主打中文版",
      "category": "音乐",
      "heat": 17.16,
      "reads": 660.9,
      "discussions": 0.46,
      "originals": 0.07,
      "date": "2024-12-17"
    },
    {
      "rank": 279,
      "title": "陈梦曾因非议陷入自我怀疑",
      "category": "社会",
      "heat": 17.06,
      "reads": 1393.4,
      "discussions": 0.37,
      "originals": 0.06,
      "date": "2024-12-17"
    },
    {
      "rank": 280,
      "title": "学校营造比拼氛围何必在食堂",
      "category": "社会",
      "heat": 16.88,
      "reads": 140.7,
      "discussions": 0.01,
      "originals": 0.0,
      "date": "2024-12-17"
    },
    {
      "rank": 281,
      "title": "橙香暖冬热红酒",
      "category": "",
      "heat": 16.84,
      "reads": 0.06,
      "discussions": 0.0,
      "originals": 0.0,
      "date": "2024-12-17"
    },
    {
      "rank": 282,
      "title": "韩国吃外卖两分钟 扔外卖两小时",
      "category": "",
      "heat": 16.82,
      "reads": 9.4,
      "discussions": 0.0,
      "originals": 0.0,
      "date": "2024-12-17"
    },
    {
      "rank": 283,
      "title": "这个世界有点美好",
      "category": "",
      "heat": 16.57,
      "reads": 4.7,
      "discussions": 0.01,
      "originals": 0.0,
      "date": "2024-12-17"
    },
    {
      "rank": 284,
      "title": "中国话感觉良好再次进入太空",
      "category": "社会",
      "heat": 16.53,
      "reads": 273.5,
      "discussions": 0.07,
      "originals": 0.01,
      "date": "2024-12-17"
    },
    {
      "rank": 285,
      "title": "为护女性遭邻居捅伤19岁小伙现状",
      "category": "社会",
      "heat": 16.32,
      "reads": 1222.0,
      "discussions": 0.15,
      "originals": 0.01,
      "date": "2024-12-17"
    },
    {
      "rank": 286,
      "title": "阿萨德离开叙利亚后首次发表声明",
      "category": "社会",
      "heat": 16.18,
      "reads": 3876.6,
      "discussions": 0.38,
      "originals": 0.04,
      "date": "2024-12-17"
    },
    {
      "rank": 287,
      "title": "嘉人红毯空场20分钟",
      "category": "",
      "heat": 16.1,
      "reads": 44.1,
      "discussions": 0.11,
      "originals": 0.02,
      "date": "2024-12-17"
    },
    {
      "rank": 288,
      "title": "宋佳女孩子就该一尘不染的漂亮",
      "category": "明星",
      "heat": 16.05,
      "reads": 1143.4,
      "discussions": 0.06,
      "originals": 0.01,
      "date": "2024-12-17"
    },
    {
      "rank": 289,
      "title": "B太 菏泽羊汤",
      "category": "",
      "heat": 15.9,
      "reads": 5.0,
      "discussions": 0.0,
      "originals": 0.0,
      "date": "2024-12-17"
    },
    {
      "rank": 290,
      "title": "阴阳师",
      "category": "游戏",
      "heat": 15.9,
      "reads": 1107000.0,
      "discussions": 981.0,
      "originals": 121.0,
      "date": "2024-12-17"
    },
    {
      "rank": 291,
      "title": "郭培谈为什么高定青睐迪丽热巴",
      "category": "明星",
      "heat": 15.85,
      "reads": 1434.6,
      "discussions": 1.7,
      "originals": 0.24,
      "date": "2024-12-17"
    },
    {
      "rank": 292,
      "title": "宋旻浩被兵务厅调查",
      "category": "明星",
      "heat": 15.82,
      "reads": 251.0,
      "discussions": 0.01,
      "originals": 0.0,
      "date": "2024-12-17"
    },
    {
      "rank": 293,
      "title": "嘉人 一言自明",
      "category": "",
      "heat": 15.82,
      "reads": 9.7,
      "discussions": 0.01,
      "originals": 0.0,
      "date": "2024-12-17"
    },
    {
      "rank": 294,
      "title": "保时捷中国裁员",
      "category": "汽车",
      "heat": 15.81,
      "reads": 636.1,
      "discussions": 0.13,
      "originals": 0.02,
      "date": "2024-12-17"
    },
    {
      "rank": 295,
      "title": "刘亦菲压轴",
      "category": "",
      "heat": 15.79,
      "reads": 16000.0,
      "discussions": 12.6,
      "originals": 1.1,
      "date": "2024-12-17"
    },
    {
      "rank": 296,
      "title": "蔡徐坤的苹果头",
      "category": "明星",
      "heat": 15.73,
      "reads": 605.5,
      "discussions": 0.35,
      "originals": 0.1,
      "date": "2024-12-17"
    },
    {
      "rank": 297,
      "title": "汪苏泷还能找到调也是不容易",
      "category": "明星",
      "heat": 15.7,
      "reads": 69.4,
      "discussions": 0.39,
      "originals": 0.01,
      "date": "2024-12-17"
    },
    {
      "rank": 298,
      "title": "在东北拖把和锅能用来玩冰壶",
      "category": "社会",
      "heat": 15.64,
      "reads": 248.4,
      "discussions": 0.06,
      "originals": 0.01,
      "date": "2024-12-17"
    },
    {
      "rank": 299,
      "title": "大明星何群带乌龟妹上跨晚了",
      "category": "",
      "heat": 15.59,
      "reads": 431.5,
      "discussions": 0.47,
      "originals": 0.02,
      "date": "2024-12-17"
    },
    {
      "rank": 300,
      "title": "玩一下智能手机 别管了",
      "category": "",
      "heat": 15.58,
      "reads": 12.9,
      "discussions": 0.03,
      "originals": 0.0,
      "date": "2024-12-17"
    },
    {
      "rank": 301,
      "title": "A股出现三大变化",
      "category": "财经",
      "heat": 15.56,
      "reads": 434.5,
      "discussions": 0.1,
      "originals": 0.03,
      "date": "2024-12-17"
    },
    {
      "rank": 302,
      "title": "癌症科学家孙少聪离开美国前往中国",
      "category": "社会",
      "heat": 15.5,
      "reads": 1020.8,
      "discussions": 0.03,
      "originals": 0.0,
      "date": "2024-12-17"
    },
    {
      "rank": 303,
      "title": "外卖小哥5年帮144名走失者找到家",
      "category": "社会",
      "heat": 15.48,
      "reads": 118.8,
      "discussions": 0.37,
      "originals": 0.11,
      "date": "2024-12-17"
    },
    {
      "rank": 304,
      "title": "柳智敏申有娜雪允合作舞台",
      "category": "明星",
      "heat": 15.37,
      "reads": 404.2,
      "discussions": 0.15,
      "originals": 0.04,
      "date": "2024-12-17"
    },
    {
      "rank": 305,
      "title": "李兰迪 小胡同文学",
      "category": "",
      "heat": 15.35,
      "reads": 141.1,
      "discussions": 0.03,
      "originals": 0.01,
      "date": "2024-12-17"
    },
    {
      "rank": 306,
      "title": "虞书欣欣愿party公式照",
      "category": "明星",
      "heat": 15.34,
      "reads": 206.2,
      "discussions": 0.01,
      "originals": 0.01,
      "date": "2024-12-17"
    },
    {
      "rank": 307,
      "title": "浮光春放 人生不相见",
      "category": "",
      "heat": 15.12,
      "reads": 0.18,
      "discussions": 0.0,
      "originals": 0.0,
      "date": "2024-12-17"
    },
    {
      "rank": 308,
      "title": "胖东来客流比5A景区还多",
      "category": "社会",
      "heat": 15.09,
      "reads": 449.0,
      "discussions": 0.1,
      "originals": 0.01,
      "date": "2024-12-17"
    },
    {
      "rank": 309,
      "title": "我国成功发射一箭四星",
      "category": "社会",
      "heat": 15.01,
      "reads": 19000.0,
      "discussions": 47.1,
      "originals": 0.41,
      "date": "2024-12-17"
    },
    {
      "rank": 310,
      "title": "昭昭墨墨年末我吃太好了",
      "category": "电视剧",
      "heat": 14.98,
      "reads": 82.6,
      "discussions": 0.46,
      "originals": 0.02,
      "date": "2024-12-17"
    },
    {
      "rank": 311,
      "title": "夏目友人帐 最意难平的一集",
      "category": "",
      "heat": 14.96,
      "reads": 28.2,
      "discussions": 0.01,
      "originals": 0.0,
      "date": "2024-12-17"
    },
    {
      "rank": 312,
      "title": "花粉事业心",
      "category": "明星",
      "heat": 14.92,
      "reads": 72.1,
      "discussions": 0.03,
      "originals": 0.01,
      "date": "2024-12-17"
    },
    {
      "rank": 313,
      "title": "一个人睡觉需要两个枕头",
      "category": "社会",
      "heat": 14.9,
      "reads": 1300.2,
      "discussions": 0.16,
      "originals": 0.03,
      "date": "2024-12-17"
    },
    {
      "rank": 314,
      "title": "江苏省体育局训练中心已报警",
      "category": "社会",
      "heat": 14.84,
      "reads": 482.8,
      "discussions": 0.01,
      "originals": 0.0,
      "date": "2024-12-17"
    },
    {
      "rank": 315,
      "title": "成毅粉丝拒绝认领长安二十四计",
      "category": "电视剧",
      "heat": 14.83,
      "reads": 2512.1,
      "discussions": 1.9,
      "originals": 0.5,
      "date": "2024-12-17"
    },
    {
      "rank": 316,
      "title": "A股大小盘股走势分化",
      "category": "财经",
      "heat": 14.71,
      "reads": 188.6,
      "discussions": 0.05,
      "originals": 0.01,
      "date": "2024-12-17"
    },
    {
      "rank": 317,
      "title": "5个动作预防颈椎曲度变直",
      "category": "社会",
      "heat": 14.59,
      "reads": 1426.9,
      "discussions": 0.8,
      "originals": 0.05,
      "date": "2024-12-17"
    },
    {
      "rank": 318,
      "title": "在西藏修铁路最怕高反被开除",
      "category": "社会",
      "heat": 14.57,
      "reads": 171.1,
      "discussions": 1.2,
      "originals": 0.02,
      "date": "2024-12-17"
    },
    {
      "rank": 319,
      "title": "谁说这柯南老了这柯南太浪漫了",
      "category": "动漫",
      "heat": 14.56,
      "reads": 85.2,
      "discussions": 0.7,
      "originals": 0.03,
      "date": "2024-12-17"
    },
    {
      "rank": 320,
      "title": "桃晚安 双排",
      "category": "",
      "heat": 14.44,
      "reads": 27.0,
      "discussions": 0.05,
      "originals": 0.02,
      "date": "2024-12-17"
    },
    {
      "rank": 321,
      "title": "沪深市场A股分红派息手续费减半",
      "category": "财经",
      "heat": 14.43,
      "reads": 74.4,
      "discussions": 0.0,
      "originals": 0.0,
      "date": "2024-12-17"
    },
    {
      "rank": 322,
      "title": "家暴受害人起诉离婚需45天冷静期",
      "category": "社会",
      "heat": 14.19,
      "reads": 1992.7,
      "discussions": 0.47,
      "originals": 0.1,
      "date": "2024-12-17"
    },
    {
      "rank": 323,
      "title": "TT晋级2024德杯八强",
      "category": "游戏",
      "heat": 14.19,
      "reads": 307.1,
      "discussions": 0.06,
      "originals": 0.0,
      "date": "2024-12-17"
    },
    {
      "rank": 324,
      "title": "宋佳钟楚曦一见面就哭了",
      "category": "明星",
      "heat": 14.16,
      "reads": 3189.8,
      "discussions": 0.09,
      "originals": 0.03,
      "date": "2024-12-17"
    },
    {
      "rank": 325,
      "title": "骨科医生都推荐的睡姿",
      "category": "搞笑",
      "heat": 14.11,
      "reads": 3855.9,
      "discussions": 0.73,
      "originals": 0.05,
      "date": "2024-12-17"
    },
    {
      "rank": 326,
      "title": "南大碎尸案逝者家属代理律师回应",
      "category": "社会",
      "heat": 14.09,
      "reads": 827.0,
      "discussions": 0.09,
      "originals": 0.01,
      "date": "2024-12-17"
    },
    {
      "rank": 327,
      "title": "刘诗诗 群像",
      "category": "",
      "heat": 14.08,
      "reads": 2070.3,
      "discussions": 1.4,
      "originals": 0.15,
      "date": "2024-12-17"
    },
    {
      "rank": 328,
      "title": "杨紫状态",
      "category": "明星",
      "heat": 14.06,
      "reads": 2307.6,
      "discussions": 7.9,
      "originals": 0.74,
      "date": "2024-12-17"
    },
    {
      "rank": 329,
      "title": "和平饭店298套餐买的是情绪价值吗",
      "category": "社会",
      "heat": 14.05,
      "reads": 525.5,
      "discussions": 0.06,
      "originals": 0.01,
      "date": "2024-12-17"
    },
    {
      "rank": 330,
      "title": "以色列空袭叙军事基地炸出蘑菇云",
      "category": "社会",
      "heat": 14.02,
      "reads": 742.7,
      "discussions": 0.07,
      "originals": 0.01,
      "date": "2024-12-17"
    },
    {
      "rank": 331,
      "title": "猎罪图鉴2断更",
      "category": "电视剧",
      "heat": 14.01,
      "reads": 5007.5,
      "discussions": 5.8,
      "originals": 0.88,
      "date": "2024-12-17"
    },
    {
      "rank": 332,
      "title": "李昀锐十秒三次转头看孟子义",
      "category": "明星",
      "heat": 13.99,
      "reads": 3407.0,
      "discussions": 1.1,
      "originals": 0.12,
      "date": "2024-12-17"
    },
    {
      "rank": 333,
      "title": "福宝进一步检查需根据福宝情况来安排",
      "category": "社会",
      "heat": 13.95,
      "reads": 114.8,
      "discussions": 0.01,
      "originals": 0.0,
      "date": "2024-12-17"
    },
    {
      "rank": 334,
      "title": "文俊辉自己吓自己",
      "category": "",
      "heat": 13.83,
      "reads": 97.2,
      "discussions": 0.71,
      "originals": 0.06,
      "date": "2024-12-17"
    },
    {
      "rank": 335,
      "title": "奇瑞直播",
      "category": "",
      "heat": 13.81,
      "reads": 5.0,
      "discussions": 0.01,
      "originals": 0.0,
      "date": "2024-12-17"
    },
    {
      "rank": 336,
      "title": "录音师把孟子义哄成胚胎了",
      "category": "",
      "heat": 13.74,
      "reads": 229.3,
      "discussions": 0.03,
      "originals": 0.01,
      "date": "2024-12-17"
    },
    {
      "rank": 337,
      "title": "辅警输液时听到验证码立马起身",
      "category": "社会",
      "heat": 13.66,
      "reads": 618.7,
      "discussions": 0.03,
      "originals": 0.01,
      "date": "2024-12-17"
    },
    {
      "rank": 338,
      "title": "秋冬离不开的妆前好物",
      "category": "",
      "heat": 13.63,
      "reads": 0.21,
      "discussions": 0.0,
      "originals": 0.0,
      "date": "2024-12-17"
    },
    {
      "rank": 339,
      "title": "娜扎曾因压力大长霰粒肿",
      "category": "明星",
      "heat": 13.62,
      "reads": 1604.8,
      "discussions": 0.12,
      "originals": 0.02,
      "date": "2024-12-17"
    },
    {
      "rank": 340,
      "title": "欢迎外国朋友们继续种草中国",
      "category": "社会",
      "heat": 13.39,
      "reads": 249.4,
      "discussions": 0.2,
      "originals": 0.01,
      "date": "2024-12-17"
    },
    {
      "rank": 341,
      "title": "于东来辟谣499元羽绒服",
      "category": "财经",
      "heat": 13.28,
      "reads": 288.8,
      "discussions": 0.02,
      "originals": 0.01,
      "date": "2024-12-17"
    },
    {
      "rank": 342,
      "title": "清密中年组天降完胜竹马",
      "category": "",
      "heat": 13.28,
      "reads": 80.6,
      "discussions": 0.62,
      "originals": 0.02,
      "date": "2024-12-17"
    },
    {
      "rank": 343,
      "title": "宋佳杨幂刘诗诗嘉人合照",
      "category": "明星",
      "heat": 13.24,
      "reads": 635.0,
      "discussions": 0.45,
      "originals": 0.04,
      "date": "2024-12-17"
    },
    {
      "rank": 344,
      "title": "白鹿1到30岁颜值变化",
      "category": "明星",
      "heat": 13.21,
      "reads": 947.5,
      "discussions": 1.0,
      "originals": 0.11,
      "date": "2024-12-17"
    },
    {
      "rank": 345,
      "title": "昭昭墨墨 在空中还啄了一口",
      "category": "",
      "heat": 13.16,
      "reads": 105.7,
      "discussions": 0.04,
      "originals": 0.01,
      "date": "2024-12-17"
    },
    {
      "rank": 346,
      "title": "董明珠称做芯片没拿国家一分钱",
      "category": "财经",
      "heat": 13.07,
      "reads": 556.7,
      "discussions": 0.09,
      "originals": 0.02,
      "date": "2024-12-17"
    },
    {
      "rank": 347,
      "title": "尤长靖 披哥留下了我炙热的三十岁",
      "category": "",
      "heat": 13.04,
      "reads": 206.4,
      "discussions": 0.95,
      "originals": 0.05,
      "date": "2024-12-17"
    },
    {
      "rank": 348,
      "title": "雷军公布小米su7冬季续航测试成绩",
      "category": "社会",
      "heat": 12.91,
      "reads": 220.0,
      "discussions": 0.02,
      "originals": 0.0,
      "date": "2024-12-17"
    },
    {
      "rank": 349,
      "title": "关晓彤林一cp感",
      "category": "电视剧",
      "heat": 12.88,
      "reads": 613.2,
      "discussions": 0.24,
      "originals": 0.06,
      "date": "2024-12-17"
    },
    {
      "rank": 350,
      "title": "王楚钦将在总决赛全力以赴",
      "category": "体育",
      "heat": 12.68,
      "reads": 939.8,
      "discussions": 0.08,
      "originals": 0.01,
      "date": "2024-12-17"
    },
    {
      "rank": 351,
      "title": "周深陶喆在聊什么",
      "category": "明星",
      "heat": 12.66,
      "reads": 35.5,
      "discussions": 0.45,
      "originals": 0.03,
      "date": "2024-12-17"
    },
    {
      "rank": 352,
      "title": "王灿聊住家阿姨的分寸感",
      "category": "",
      "heat": 12.63,
      "reads": 1322.4,
      "discussions": 0.04,
      "originals": 0.02,
      "date": "2024-12-17"
    },
    {
      "rank": 353,
      "title": "魏大勋 有多久没站到中间了",
      "category": "",
      "heat": 12.59,
      "reads": 250.5,
      "discussions": 0.98,
      "originals": 0.09,
      "date": "2024-12-17"
    },
    {
      "rank": 354,
      "title": "孙正义现身特朗普海湖庄园",
      "category": "社会",
      "heat": 12.29,
      "reads": 564.3,
      "discussions": 0.03,
      "originals": 0.01,
      "date": "2024-12-17"
    },
    {
      "rank": 355,
      "title": "张韶涵被催了5年的新专辑来了",
      "category": "音乐",
      "heat": 12.25,
      "reads": 919.1,
      "discussions": 0.49,
      "originals": 0.04,
      "date": "2024-12-17"
    },
    {
      "rank": 356,
      "title": "我干嘛要去学什么园林设计",
      "category": "",
      "heat": 11.94,
      "reads": 275.7,
      "discussions": 0.1,
      "originals": 0.03,
      "date": "2024-12-17"
    },
    {
      "rank": 357,
      "title": "韩国大叔已第5次来张家界天门山",
      "category": "社会",
      "heat": 11.93,
      "reads": 263.9,
      "discussions": 0.01,
      "originals": 0.01,
      "date": "2024-12-17"
    },
    {
      "rank": 358,
      "title": "ChatGPT搜索功能向全体用户免费开放",
      "category": "社会",
      "heat": 11.83,
      "reads": 194.8,
      "discussions": 0.02,
      "originals": 0.0,
      "date": "2024-12-17"
    },
    {
      "rank": 359,
      "title": "刘雨辰回应成绩没有黄雅琼好",
      "category": "体育",
      "heat": 11.77,
      "reads": 326.2,
      "discussions": 0.02,
      "originals": 0.01,
      "date": "2024-12-17"
    },
    {
      "rank": 360,
      "title": "九重紫预告",
      "category": "电视剧",
      "heat": 11.76,
      "reads": 1771.7,
      "discussions": 0.5,
      "originals": 0.02,
      "date": "2024-12-17"
    },
    {
      "rank": 361,
      "title": "终于还是抠抠搜搜地花了很多钱",
      "category": "社会",
      "heat": 11.7,
      "reads": 1186.1,
      "discussions": 0.11,
      "originals": 0.03,
      "date": "2024-12-17"
    },
    {
      "rank": 362,
      "title": "外国人嗑瓜子真的很忙",
      "category": "社会",
      "heat": 11.62,
      "reads": 1391.2,
      "discussions": 0.69,
      "originals": 0.07,
      "date": "2024-12-17"
    },
    {
      "rank": 363,
      "title": "鸿蒙智行与时代同行",
      "category": "社会",
      "heat": 11.5,
      "reads": 18.8,
      "discussions": 0.26,
      "originals": 0.01,
      "date": "2024-12-17"
    },
    {
      "rank": 364,
      "title": "梁王组合男双世排第二",
      "category": "体育",
      "heat": 11.5,
      "reads": 281.7,
      "discussions": 0.01,
      "originals": 0.01,
      "date": "2024-12-17"
    },
    {
      "rank": 365,
      "title": "加沙北部最后一名骨外科医生被打死",
      "category": "",
      "heat": 11.47,
      "reads": 822.8,
      "discussions": 0.09,
      "originals": 0.01,
      "date": "2024-12-17"
    },
    {
      "rank": 366,
      "title": "马斯克身价突破4700亿美元",
      "category": "财经",
      "heat": 11.01,
      "reads": 223.0,
      "discussions": 0.04,
      "originals": 0.01,
      "date": "2024-12-17"
    },
    {
      "rank": 367,
      "title": "爱做饭的人值得珍惜",
      "category": "社会",
      "heat": 10.93,
      "reads": 616.1,
      "discussions": 0.34,
      "originals": 0.02,
      "date": "2024-12-17"
    },
    {
      "rank": 368,
      "title": "王楚钦世排8825分持续第一",
      "category": "社会",
      "heat": 10.61,
      "reads": 261.3,
      "discussions": 0.02,
      "originals": 0.01,
      "date": "2024-12-17"
    },
    {
      "rank": 369,
      "title": "杨幂 今天我们相聚在这里",
      "category": "",
      "heat": 10.56,
      "reads": 2274.3,
      "discussions": 1.5,
      "originals": 0.17,
      "date": "2024-12-17"
    },
    {
      "rank": 370,
      "title": "特斯拉市值一夜涨超6200亿元",
      "category": "财经",
      "heat": 10.49,
      "reads": 874.9,
      "discussions": 0.16,
      "originals": 0.02,
      "date": "2024-12-17"
    },
    {
      "rank": 371,
      "title": "教育局回应教师赌博被罚10年后记过",
      "category": "社会",
      "heat": 10.2,
      "reads": 320.1,
      "discussions": 0.03,
      "originals": 0.01,
      "date": "2024-12-17"
    },
    {
      "rank": 372,
      "title": "学校通报食堂设置学霸就餐区",
      "category": "社会",
      "heat": 9.81,
      "reads": 261.2,
      "discussions": 0.06,
      "originals": 0.01,
      "date": "2024-12-17"
    },
    {
      "rank": 373,
      "title": "王亚飞发了卢昱晓妆造vlog",
      "category": "明星",
      "heat": 9.35,
      "reads": 157.4,
      "discussions": 0.27,
      "originals": 0.02,
      "date": "2024-12-17"
    },
    {
      "rank": 374,
      "title": "上海和平饭店298元套餐遭吐槽",
      "category": "社会",
      "heat": 8.87,
      "reads": 6187.5,
      "discussions": 1.0,
      "originals": 0.14,
      "date": "2024-12-17"
    },
    {
      "rank": 375,
      "title": "潘展乐回应被各国选手逐帧研究",
      "category": "体育",
      "heat": 8.82,
      "reads": 913.6,
      "discussions": 0.11,
      "originals": 0.02,
      "date": "2024-12-17"
    },
    {
      "rank": 376,
      "title": "阿萨德称离开叙利亚不是计划好的",
      "category": "社会",
      "heat": 8.8,
      "reads": 2051.5,
      "discussions": 0.18,
      "originals": 0.01,
      "date": "2024-12-17"
    },
    {
      "rank": 377,
      "title": "星光大赏阵容",
      "category": "电视剧",
      "heat": 8.8,
      "reads": 105000.0,
      "discussions": 109.2,
      "originals": 4.3,
      "date": "2024-12-17"
    },
    {
      "rank": 378,
      "title": "张小斐你丝袜破了",
      "category": "明星",
      "heat": 8.79,
      "reads": 7145.3,
      "discussions": 1.1,
      "originals": 0.12,
      "date": "2024-12-17"
    },
    {
      "rank": 379,
      "title": "杨紫王子文拥抱",
      "category": "明星",
      "heat": 8.79,
      "reads": 2292.1,
      "discussions": 1.4,
      "originals": 0.23,
      "date": "2024-12-17"
    },
    {
      "rank": 380,
      "title": "水瓶座会把自己的心保护得很好",
      "category": "星座",
      "heat": 8.79,
      "reads": 1431.9,
      "discussions": 0.21,
      "originals": 0.03,
      "date": "2024-12-17"
    },
    {
      "rank": 381,
      "title": "清密双头藏尸命案",
      "category": "",
      "heat": 8.79,
      "reads": 514.5,
      "discussions": 0.45,
      "originals": 0.03,
      "date": "2024-12-17"
    },
    {
      "rank": 382,
      "title": "疯驴子在清密揍高启强",
      "category": "",
      "heat": 8.79,
      "reads": 89.1,
      "discussions": 0.26,
      "originals": 0.01,
      "date": "2024-12-17"
    },
    {
      "rank": 383,
      "title": "王楚钦说想去面对比赛是积极信号",
      "category": "社会",
      "heat": 8.79,
      "reads": 1072.4,
      "discussions": 0.2,
      "originals": 0.02,
      "date": "2024-12-17"
    },
    {
      "rank": 384,
      "title": "樊振东王楚钦发型的较量",
      "category": "体育",
      "heat": 8.79,
      "reads": 672.2,
      "discussions": 0.56,
      "originals": 0.05,
      "date": "2024-12-17"
    },
    {
      "rank": 385,
      "title": "戚薇从嘉人晚宴逃出来直播",
      "category": "明星",
      "heat": 8.79,
      "reads": 1196.9,
      "discussions": 0.22,
      "originals": 0.04,
      "date": "2024-12-17"
    },
    {
      "rank": 386,
      "title": "男子疑因护士妻子出轨自杀一事已立案",
      "category": "社会",
      "heat": 8.79,
      "reads": 3169.1,
      "discussions": 0.49,
      "originals": 0.05,
      "date": "2024-12-17"
    },
    {
      "rank": 387,
      "title": "推动经济持续回升向好",
      "category": "社会",
      "heat": 7.43,
      "reads": 466.8,
      "discussions": 0.09,
      "originals": 0.01,
      "date": "2024-12-17"
    },
    {
      "rank": 388,
      "title": "飞鹤",
      "category": "",
      "heat": 6.9,
      "reads": 2226.6,
      "discussions": 11.4,
      "originals": 0.12,
      "date": "2024-12-17"
    },
    {
      "rank": 389,
      "title": "秦新宇 妈生鼻回家",
      "category": "",
      "heat": 6.9,
      "reads": 136.2,
      "discussions": 0.04,
      "originals": 0.01,
      "date": "2024-12-17"
    },
    {
      "rank": 390,
      "title": "FIFA年度颁奖典礼明日举行",
      "category": "体育",
      "heat": 6.84,
      "reads": 107.9,
      "discussions": 0.01,
      "originals": 0.01,
      "date": "2024-12-17"
    },
    {
      "rank": 391,
      "title": "杨幂 性感辣妹",
      "category": "",
      "heat": 6.63,
      "reads": 1740.6,
      "discussions": 2.4,
      "originals": 0.15,
      "date": "2024-12-17"
    },
    {
      "rank": 392,
      "title": "王楚钦赢下决胜盘",
      "category": "体育",
      "heat": 5.9,
      "reads": 77.1,
      "discussions": 0.02,
      "originals": 0.0,
      "date": "2024-12-17"
    },
    {
      "rank": 393,
      "title": "涉事领导回应职工为其买酒赊账9万",
      "category": "社会",
      "heat": 5.71,
      "reads": 439.8,
      "discussions": 0.02,
      "originals": 0.0,
      "date": "2024-12-17"
    },
    {
      "rank": 394,
      "title": "李昀锐反差感",
      "category": "明星",
      "heat": 5.35,
      "reads": 343.8,
      "discussions": 1.4,
      "originals": 0.1,
      "date": "2024-12-17"
    },
    {
      "rank": 395,
      "title": "娜然 海带精",
      "category": "",
      "heat": 5.12,
      "reads": 321.9,
      "discussions": 0.12,
      "originals": 0.03,
      "date": "2024-12-17"
    },
    {
      "rank": 396,
      "title": "重庆大叔们近0度冰水中救起4人",
      "category": "社会",
      "heat": 5.12,
      "reads": 256.8,
      "discussions": 0.02,
      "originals": 0.0,
      "date": "2024-12-17"
    },
    {
      "rank": 397,
      "title": "钎城守约露头就秒",
      "category": "",
      "heat": 5.12,
      "reads": 11.7,
      "discussions": 0.01,
      "originals": 0.0,
      "date": "2024-12-17"
    },
    {
      "rank": 398,
      "title": "樊振东3比0胜周启豪",
      "category": "社会",
      "heat": 5.11,
      "reads": 1297.1,
      "discussions": 0.25,
      "originals": 0.03,
      "date": "2024-12-17"
    },
    {
      "rank": 399,
      "title": "樊振东vs王楚钦",
      "category": "体育",
      "heat": 5.11,
      "reads": 95000.0,
      "discussions": 32.2,
      "originals": 6.1,
      "date": "2024-12-17"
    },
    {
      "rank": 400,
      "title": "我国成为世界第1核电大国",
      "category": "社会",
      "heat": 5.04,
      "reads": 381.8,
      "discussions": 0.04,
      "originals": 0.01,
      "date": "2024-12-17"
    },
    {
      "rank": 401,
      "title": "谷歌前CEO称中国AI以惊人速度追赶美国",
      "category": "",
      "heat": 4.91,
      "reads": 713.3,
      "discussions": 0.04,
      "originals": 0.01,
      "date": "2024-12-17"
    },
    {
      "rank": 402,
      "title": "为中国航天点赞",
      "category": "社会",
      "heat": 4.85,
      "reads": 134000.0,
      "discussions": 140.9,
      "originals": 2.9,
      "date": "2024-12-17"
    },
    {
      "rank": 403,
      "title": "玩雪这一块哈尔滨还是太超前了",
      "category": "社会",
      "heat": 4.65,
      "reads": 236.7,
      "discussions": 0.04,
      "originals": 0.0,
      "date": "2024-12-17"
    },
    {
      "rank": 404,
      "title": "零售业创新提升工程实施方案",
      "category": "社会",
      "heat": 4.6,
      "reads": 67.6,
      "discussions": 0.01,
      "originals": 0.0,
      "date": "2024-12-17"
    },
    {
      "rank": 405,
      "title": "迷路后妹妹带哥哥找警察寻帮助",
      "category": "社会",
      "heat": 4.45,
      "reads": 342.5,
      "discussions": 0.11,
      "originals": 0.01,
      "date": "2024-12-17"
    },
    {
      "rank": 406,
      "title": "鞠婧祎陈昊宇红毯生图",
      "category": "明星",
      "heat": 4.22,
      "reads": 217.9,
      "discussions": 0.32,
      "originals": 0.07,
      "date": "2024-12-17"
    },
    {
      "rank": 407,
      "title": "檀健次沈翊平行时空宿命感",
      "category": "电视剧",
      "heat": 4.17,
      "reads": 160.4,
      "discussions": 1.9,
      "originals": 0.18,
      "date": "2024-12-17"
    },
    {
      "rank": 408,
      "title": "唐钱婷2024完美收官",
      "category": "体育",
      "heat": 3.77,
      "reads": 61.3,
      "discussions": 0.01,
      "originals": 0.01,
      "date": "2024-12-17"
    },
    {
      "rank": 409,
      "title": "王俊凯确定出席2025巴黎时装周",
      "category": "明星",
      "heat": 2.67,
      "reads": 423.4,
      "discussions": 0.63,
      "originals": 0.13,
      "date": "2024-12-17"
    },
    {
      "rank": 410,
      "title": "尹锡悦组建团队应对弹劾案",
      "category": "社会",
      "heat": 2.66,
      "reads": 383.1,
      "discussions": 0.05,
      "originals": 0.01,
      "date": "2024-12-17"
    },
    {
      "rank": 411,
      "title": "71岁大爷14秒内跑完100米",
      "category": "社会",
      "heat": 2.62,
      "reads": 459.7,
      "discussions": 0.11,
      "originals": 0.01,
      "date": "2024-12-17"
    },
    {
      "rank": 412,
      "title": "湖北一教师遭捕兽电网电击身亡",
      "category": "社会",
      "heat": 2.6,
      "reads": 161.9,
      "discussions": 0.02,
      "originals": 0.0,
      "date": "2024-12-17"
    },
    {
      "rank": 413,
      "title": "雪龙号中山站已卸货798.1吨",
      "category": "社会",
      "heat": 2.6,
      "reads": 216.5,
      "discussions": 0.08,
      "originals": 0.0,
      "date": "2024-12-17"
    },
    {
      "rank": 414,
      "title": "世界之外",
      "category": "游戏",
      "heat": 2.59,
      "reads": 163000.0,
      "discussions": 193.0,
      "originals": 10.7,
      "date": "2024-12-17"
    },
    {
      "rank": 415,
      "title": "芝童",
      "category": "",
      "heat": 2.59,
      "reads": 730.2,
      "discussions": 0.87,
      "originals": 0.06,
      "date": "2024-12-17"
    },
    {
      "rank": 416,
      "title": "飞鹤陕西因抽检不合格被责令整改",
      "category": "社会",
      "heat": 1.83,
      "reads": 353.2,
      "discussions": 0.03,
      "originals": 0.01,
      "date": "2024-12-17"
    },
    {
      "rank": 417,
      "title": "以色列为何频繁破防",
      "category": "社会",
      "heat": 1.78,
      "reads": 358.1,
      "discussions": 0.06,
      "originals": 0.01,
      "date": "2024-12-17"
    },
    {
      "rank": 418,
      "title": "清明上河图密码质感",
      "category": "电视剧",
      "heat": 1.57,
      "reads": 40.6,
      "discussions": 0.03,
      "originals": 0.0,
      "date": "2024-12-17"
    }
  ]
}