{
  "date": "2025-03-27",
  "count": 398,
  "data": [
    {
      "rank": 1,
      "title": "被擦妆5次艺考生被中国传媒大学录取",
      "category": "社会",
      "heat": 227.84,
      "reads": 9616.4,
      "discussions": 1.2,
      "originals": 0.23,
      "date": "2025-03-27"
    },
    {
      "rank": 2,
      "title": "黄圣依回应和张凌赫共用一张脸",
      "category": "明星",
      "heat": 190.31,
      "reads": 6900.4,
      "discussions": 1.4,
      "originals": 0.22,
      "date": "2025-03-27"
    },
    {
      "rank": 3,
      "title": "印度遭奸杀女医生案内幕曝光",
      "category": "社会",
      "heat": 164.6,
      "reads": 12000.0,
      "discussions": 0.86,
      "originals": 0.24,
      "date": "2025-03-27"
    },
    {
      "rank": 4,
      "title": "金价",
      "category": "财经",
      "heat": 152.8,
      "reads": 155000.0,
      "discussions": 116.6,
      "originals": 9.3,
      "date": "2025-03-27"
    },
    {
      "rank": 5,
      "title": "小米的mi倒过来就是仙桃的仙",
      "category": "社会",
      "heat": 145.35,
      "reads": 6777.6,
      "discussions": 0.83,
      "originals": 0.13,
      "date": "2025-03-27"
    },
    {
      "rank": 6,
      "title": "谢霆锋的烤肠卖了15亿元",
      "category": "社会",
      "heat": 137.04,
      "reads": 5759.3,
      "discussions": 1.1,
      "originals": 0.34,
      "date": "2025-03-27"
    },
    {
      "rank": 7,
      "title": "爸爸去世女儿被判和4个姑姑平分遗产",
      "category": "社会",
      "heat": 123.88,
      "reads": 12000.0,
      "discussions": 1.3,
      "originals": 0.16,
      "date": "2025-03-27"
    },
    {
      "rank": 8,
      "title": "于正 我从此不敢看观音",
      "category": "",
      "heat": 116.68,
      "reads": 2328.3,
      "discussions": 0.58,
      "originals": 0.25,
      "date": "2025-03-27"
    },
    {
      "rank": 9,
      "title": "万千气象看江苏",
      "category": "",
      "heat": 113.35,
      "reads": 32000.0,
      "discussions": 2.4,
      "originals": 0.1,
      "date": "2025-03-27"
    },
    {
      "rank": 10,
      "title": "找17岁女孩代孕男子生气信息被泄漏",
      "category": "社会",
      "heat": 113.25,
      "reads": 1554.8,
      "discussions": 0.42,
      "originals": 0.04,
      "date": "2025-03-27"
    },
    {
      "rank": 11,
      "title": "唐嫣 你的兵来了",
      "category": "",
      "heat": 108.72,
      "reads": 1999.8,
      "discussions": 0.93,
      "originals": 0.24,
      "date": "2025-03-27"
    },
    {
      "rank": 12,
      "title": "3年赚70万网约司机春节没休息过",
      "category": "社会",
      "heat": 108.43,
      "reads": 576.9,
      "discussions": 0.05,
      "originals": 0.01,
      "date": "2025-03-27"
    },
    {
      "rank": 13,
      "title": "香飘飘奶茶涨价至16元一杯",
      "category": "社会",
      "heat": 90.15,
      "reads": 7050.6,
      "discussions": 2.0,
      "originals": 0.51,
      "date": "2025-03-27"
    },
    {
      "rank": 14,
      "title": "那些美到极致的中国锦绣",
      "category": "社会",
      "heat": 86.74,
      "reads": 477.5,
      "discussions": 0.11,
      "originals": 0.03,
      "date": "2025-03-27"
    },
    {
      "rank": 15,
      "title": "今年5月只用上19天班",
      "category": "社会",
      "heat": 86.13,
      "reads": 5458.6,
      "discussions": 1.8,
      "originals": 0.34,
      "date": "2025-03-27"
    },
    {
      "rank": 16,
      "title": "12届中国网络视听大会开幕",
      "category": "互联网",
      "heat": 85.52,
      "reads": 969.0,
      "discussions": 0.08,
      "originals": 0.02,
      "date": "2025-03-27"
    },
    {
      "rank": 17,
      "title": "冰箱贴是年轻人的到此一游",
      "category": "社会",
      "heat": 82.79,
      "reads": 3557.7,
      "discussions": 0.96,
      "originals": 0.21,
      "date": "2025-03-27"
    },
    {
      "rank": 18,
      "title": "舒马赫近乎植物人",
      "category": "体育",
      "heat": 76.21,
      "reads": 3173.0,
      "discussions": 0.19,
      "originals": 0.05,
      "date": "2025-03-27"
    },
    {
      "rank": 19,
      "title": "防水冲锋衣可能影响女性怀孕",
      "category": "社会",
      "heat": 73.24,
      "reads": 8839.2,
      "discussions": 1.1,
      "originals": 0.35,
      "date": "2025-03-27"
    },
    {
      "rank": 20,
      "title": "网络视听成全网民的数字空气",
      "category": "互联网",
      "heat": 72.54,
      "reads": 2774.0,
      "discussions": 0.45,
      "originals": 0.04,
      "date": "2025-03-27"
    },
    {
      "rank": 21,
      "title": "一组数据看美丽中国颜值有多高",
      "category": "社会",
      "heat": 72.21,
      "reads": 747.8,
      "discussions": 0.11,
      "originals": 0.03,
      "date": "2025-03-27"
    },
    {
      "rank": 22,
      "title": "找17岁女孩代孕男子领孩子多付20万",
      "category": "社会",
      "heat": 72.2,
      "reads": 2580.1,
      "discussions": 0.21,
      "originals": 0.05,
      "date": "2025-03-27"
    },
    {
      "rank": 23,
      "title": "my name is jeff 嘟嘟嘟嘟",
      "category": "",
      "heat": 71.6,
      "reads": 1128.7,
      "discussions": 0.37,
      "originals": 0.16,
      "date": "2025-03-27"
    },
    {
      "rank": 24,
      "title": "陈都灵晒辛云来煮的米线",
      "category": "明星",
      "heat": 70.61,
      "reads": 6637.2,
      "discussions": 0.81,
      "originals": 0.22,
      "date": "2025-03-27"
    },
    {
      "rank": 25,
      "title": "马拉松亲密事件拍摄者再发声",
      "category": "社会",
      "heat": 65.62,
      "reads": 2293.5,
      "discussions": 0.13,
      "originals": 0.03,
      "date": "2025-03-27"
    },
    {
      "rank": 26,
      "title": "见到这种草莓熊瓶子请立刻报警",
      "category": "社会",
      "heat": 61.36,
      "reads": 3519.6,
      "discussions": 0.29,
      "originals": 0.07,
      "date": "2025-03-27"
    },
    {
      "rank": 27,
      "title": "我国大国基建加一",
      "category": "社会",
      "heat": 57.18,
      "reads": 589.3,
      "discussions": 0.03,
      "originals": 0.01,
      "date": "2025-03-27"
    },
    {
      "rank": 28,
      "title": "张馨予说管不住嘴就看钟楚曦",
      "category": "明星",
      "heat": 56.77,
      "reads": 2969.2,
      "discussions": 0.2,
      "originals": 0.06,
      "date": "2025-03-27"
    },
    {
      "rank": 29,
      "title": "国防部提醒日本",
      "category": "社会",
      "heat": 56.34,
      "reads": 2760.9,
      "discussions": 0.27,
      "originals": 0.04,
      "date": "2025-03-27"
    },
    {
      "rank": 30,
      "title": "你醒啦 现在是2008年",
      "category": "",
      "heat": 55.59,
      "reads": 1192.9,
      "discussions": 0.89,
      "originals": 0.13,
      "date": "2025-03-27"
    },
    {
      "rank": 31,
      "title": "李佳航对李晟一见钟情",
      "category": "明星",
      "heat": 55.38,
      "reads": 5725.1,
      "discussions": 0.63,
      "originals": 0.12,
      "date": "2025-03-27"
    },
    {
      "rank": 32,
      "title": "孟美岐黄圣依跑马拉松",
      "category": "明星",
      "heat": 54.4,
      "reads": 2862.3,
      "discussions": 0.83,
      "originals": 0.09,
      "date": "2025-03-27"
    },
    {
      "rank": 33,
      "title": "特朗普成为史上最富有的美国总统",
      "category": "社会",
      "heat": 54.39,
      "reads": 240.5,
      "discussions": 0.01,
      "originals": 0.01,
      "date": "2025-03-27"
    },
    {
      "rank": 34,
      "title": "沙溢发文回应美黑",
      "category": "",
      "heat": 53.68,
      "reads": 1015.9,
      "discussions": 0.12,
      "originals": 0.02,
      "date": "2025-03-27"
    },
    {
      "rank": 35,
      "title": "四川乐山966万大奖得主踩点领奖",
      "category": "社会",
      "heat": 51.91,
      "reads": 1861.5,
      "discussions": 0.21,
      "originals": 0.05,
      "date": "2025-03-27"
    },
    {
      "rank": 36,
      "title": "外交部回应长江和记集团出售海外港口",
      "category": "",
      "heat": 50.58,
      "reads": 1785.3,
      "discussions": 0.17,
      "originals": 0.03,
      "date": "2025-03-27"
    },
    {
      "rank": 37,
      "title": "詹姆斯绝杀",
      "category": "体育",
      "heat": 49.88,
      "reads": 7068.9,
      "discussions": 2.1,
      "originals": 0.26,
      "date": "2025-03-27"
    },
    {
      "rank": 38,
      "title": "赵露思生病前每天只睡2小时",
      "category": "明星",
      "heat": 48.68,
      "reads": 3452.7,
      "discussions": 1.3,
      "originals": 0.26,
      "date": "2025-03-27"
    },
    {
      "rank": 39,
      "title": "白宫泄密群聊完整记录公布",
      "category": "",
      "heat": 47.64,
      "reads": 2652.9,
      "discussions": 0.29,
      "originals": 0.04,
      "date": "2025-03-27"
    },
    {
      "rank": 40,
      "title": "成都沙尘暴",
      "category": "",
      "heat": 47.52,
      "reads": 902.7,
      "discussions": 0.82,
      "originals": 0.23,
      "date": "2025-03-27"
    },
    {
      "rank": 41,
      "title": "黑心食品厂用臭蛋做网红蛋糕",
      "category": "社会",
      "heat": 47.11,
      "reads": 1281.7,
      "discussions": 0.2,
      "originals": 0.04,
      "date": "2025-03-27"
    },
    {
      "rank": 42,
      "title": "佛山一公司要求员工每月加班10晚以上",
      "category": "社会",
      "heat": 46.13,
      "reads": 599.6,
      "discussions": 0.06,
      "originals": 0.01,
      "date": "2025-03-27"
    },
    {
      "rank": 43,
      "title": "你以为的毒贩vs你不知道的伪装",
      "category": "社会",
      "heat": 45.16,
      "reads": 3435.4,
      "discussions": 0.66,
      "originals": 0.09,
      "date": "2025-03-27"
    },
    {
      "rank": 44,
      "title": "17岁代孕女孩产下双胞胎已上户口",
      "category": "社会",
      "heat": 45.08,
      "reads": 2585.0,
      "discussions": 0.45,
      "originals": 0.18,
      "date": "2025-03-27"
    },
    {
      "rank": 45,
      "title": "赵露思承认对生命没有敬畏",
      "category": "综艺",
      "heat": 43.67,
      "reads": 6605.4,
      "discussions": 1.4,
      "originals": 0.44,
      "date": "2025-03-27"
    },
    {
      "rank": 46,
      "title": "疑把R听成L韩客机降错跑道险撞机",
      "category": "社会",
      "heat": 43.59,
      "reads": 874.7,
      "discussions": 0.05,
      "originals": 0.01,
      "date": "2025-03-27"
    },
    {
      "rank": 47,
      "title": "胡静卖老公跑车三个男人心碎了",
      "category": "",
      "heat": 43.58,
      "reads": 2518.5,
      "discussions": 0.77,
      "originals": 0.09,
      "date": "2025-03-27"
    },
    {
      "rank": 48,
      "title": "赵露思因为躯体化记不住台词",
      "category": "明星",
      "heat": 43.47,
      "reads": 5642.7,
      "discussions": 1.4,
      "originals": 0.47,
      "date": "2025-03-27"
    },
    {
      "rank": 49,
      "title": "丹宁高速桥梁垮塌43名公职人员被问责",
      "category": "社会",
      "heat": 43.42,
      "reads": 421.2,
      "discussions": 0.02,
      "originals": 0.01,
      "date": "2025-03-27"
    },
    {
      "rank": 50,
      "title": "允在允荷分手",
      "category": "综艺",
      "heat": 43.37,
      "reads": 371.4,
      "discussions": 0.13,
      "originals": 0.06,
      "date": "2025-03-27"
    },
    {
      "rank": 51,
      "title": "2人身绑28只活体龟入境",
      "category": "社会",
      "heat": 42.96,
      "reads": 1987.9,
      "discussions": 0.17,
      "originals": 0.05,
      "date": "2025-03-27"
    },
    {
      "rank": 52,
      "title": "特朗普宣布对进口汽车征收25%关税",
      "category": "社会",
      "heat": 42.44,
      "reads": 2818.0,
      "discussions": 0.59,
      "originals": 0.1,
      "date": "2025-03-27"
    },
    {
      "rank": 53,
      "title": "王宝强新剧78秒8个假动作",
      "category": "",
      "heat": 42.32,
      "reads": 967.5,
      "discussions": 0.75,
      "originals": 0.06,
      "date": "2025-03-27"
    },
    {
      "rank": 54,
      "title": "97年女生身高1.6米体重50斤",
      "category": "社会",
      "heat": 41.32,
      "reads": 11000.0,
      "discussions": 1.4,
      "originals": 0.21,
      "date": "2025-03-27"
    },
    {
      "rank": 55,
      "title": "店长回应早产儿蛋糕已下架销毁",
      "category": "社会",
      "heat": 41.05,
      "reads": 7379.5,
      "discussions": 0.44,
      "originals": 0.15,
      "date": "2025-03-27"
    },
    {
      "rank": 56,
      "title": "001号龙标给了河南台",
      "category": "社会",
      "heat": 40.71,
      "reads": 2291.0,
      "discussions": 0.13,
      "originals": 0.04,
      "date": "2025-03-27"
    },
    {
      "rank": 57,
      "title": "李宏毅在机场遭粉丝围堵大喊走开",
      "category": "社会",
      "heat": 40.06,
      "reads": 3072.6,
      "discussions": 0.49,
      "originals": 0.13,
      "date": "2025-03-27"
    },
    {
      "rank": 58,
      "title": "陈都灵 凤凰哀鸣",
      "category": "",
      "heat": 39.15,
      "reads": 1713.9,
      "discussions": 0.58,
      "originals": 0.13,
      "date": "2025-03-27"
    },
    {
      "rank": 59,
      "title": "看得出蓝盈莹是畲族公主",
      "category": "",
      "heat": 39.06,
      "reads": 1170.4,
      "discussions": 0.18,
      "originals": 0.05,
      "date": "2025-03-27"
    },
    {
      "rank": 60,
      "title": "权志龙又染银发了",
      "category": "明星",
      "heat": 38.76,
      "reads": 2890.5,
      "discussions": 0.67,
      "originals": 0.12,
      "date": "2025-03-27"
    },
    {
      "rank": 61,
      "title": "人民网评古偶失灵",
      "category": "电视剧",
      "heat": 38.5,
      "reads": 937.0,
      "discussions": 0.13,
      "originals": 0.03,
      "date": "2025-03-27"
    },
    {
      "rank": 62,
      "title": "孟子义李昀锐跑男路透",
      "category": "明星",
      "heat": 38.02,
      "reads": 2149.6,
      "discussions": 0.98,
      "originals": 0.11,
      "date": "2025-03-27"
    },
    {
      "rank": 63,
      "title": "雁回时热度",
      "category": "电视剧",
      "heat": 37.08,
      "reads": 4390.7,
      "discussions": 1.8,
      "originals": 0.37,
      "date": "2025-03-27"
    },
    {
      "rank": 64,
      "title": "唐嫣台词",
      "category": "",
      "heat": 37.05,
      "reads": 516.9,
      "discussions": 0.29,
      "originals": 0.06,
      "date": "2025-03-27"
    },
    {
      "rank": 65,
      "title": "祝绪丹被所有姐姐现场吃瓜",
      "category": "",
      "heat": 37.02,
      "reads": 2017.0,
      "discussions": 0.98,
      "originals": 0.07,
      "date": "2025-03-27"
    },
    {
      "rank": 66,
      "title": "短剧阵容这么顶了吗",
      "category": "明星",
      "heat": 36.94,
      "reads": 1627.5,
      "discussions": 0.78,
      "originals": 0.1,
      "date": "2025-03-27"
    },
    {
      "rank": 67,
      "title": "男子在工地宿舍睡觉被工友捅刺身亡",
      "category": "社会",
      "heat": 36.92,
      "reads": 1432.0,
      "discussions": 0.11,
      "originals": 0.03,
      "date": "2025-03-27"
    },
    {
      "rank": 68,
      "title": "儿子给腰突父亲买40小时硬座票",
      "category": "社会",
      "heat": 36.82,
      "reads": 11000.0,
      "discussions": 0.88,
      "originals": 0.19,
      "date": "2025-03-27"
    },
    {
      "rank": 69,
      "title": "酒店前台违规办房卡致女子被侵犯",
      "category": "社会",
      "heat": 36.79,
      "reads": 2875.1,
      "discussions": 0.21,
      "originals": 0.04,
      "date": "2025-03-27"
    },
    {
      "rank": 70,
      "title": "不允许再使用零添加等用语",
      "category": "社会",
      "heat": 36.72,
      "reads": 2410.7,
      "discussions": 0.43,
      "originals": 0.08,
      "date": "2025-03-27"
    },
    {
      "rank": 71,
      "title": "黄圣依说录制再见爱人很真实",
      "category": "",
      "heat": 36.64,
      "reads": 848.7,
      "discussions": 0.58,
      "originals": 0.04,
      "date": "2025-03-27"
    },
    {
      "rank": 72,
      "title": "金赛纶写给文彬的信",
      "category": "明星",
      "heat": 36.29,
      "reads": 2379.2,
      "discussions": 0.31,
      "originals": 0.12,
      "date": "2025-03-27"
    },
    {
      "rank": 73,
      "title": "念无双 老年宣发",
      "category": "",
      "heat": 36.11,
      "reads": 621.1,
      "discussions": 0.24,
      "originals": 0.06,
      "date": "2025-03-27"
    },
    {
      "rank": 74,
      "title": "为何父母的缺点又出现在了我身上",
      "category": "社会",
      "heat": 36.03,
      "reads": 152.7,
      "discussions": 0.03,
      "originals": 0.0,
      "date": "2025-03-27"
    },
    {
      "rank": 75,
      "title": "接下来这波降温有多猛",
      "category": "社会",
      "heat": 35.98,
      "reads": 611.4,
      "discussions": 0.14,
      "originals": 0.03,
      "date": "2025-03-27"
    },
    {
      "rank": 76,
      "title": "3年赚70万司机从晚6干到早6",
      "category": "社会",
      "heat": 35.85,
      "reads": 1724.9,
      "discussions": 0.29,
      "originals": 0.05,
      "date": "2025-03-27"
    },
    {
      "rank": 77,
      "title": "大鹅多处被烤熟仍不离开被烧死同伴",
      "category": "社会",
      "heat": 35.83,
      "reads": 2539.9,
      "discussions": 0.32,
      "originals": 0.03,
      "date": "2025-03-27"
    },
    {
      "rank": 78,
      "title": "预包装食品可自愿标示消费保存期",
      "category": "社会",
      "heat": 35.66,
      "reads": 687.1,
      "discussions": 0.07,
      "originals": 0.02,
      "date": "2025-03-27"
    },
    {
      "rank": 79,
      "title": "淘宝率先打击AI假图",
      "category": "社会",
      "heat": 35.66,
      "reads": 487.0,
      "discussions": 0.28,
      "originals": 0.03,
      "date": "2025-03-27"
    },
    {
      "rank": 80,
      "title": "医生连续六年下班卖小吃月入近2万",
      "category": "社会",
      "heat": 35.47,
      "reads": 2438.1,
      "discussions": 0.26,
      "originals": 0.05,
      "date": "2025-03-27"
    },
    {
      "rank": 81,
      "title": "赵露思形容焦虑症的惊恐和高反一样",
      "category": "明星",
      "heat": 35.45,
      "reads": 1905.8,
      "discussions": 0.45,
      "originals": 0.08,
      "date": "2025-03-27"
    },
    {
      "rank": 82,
      "title": "黑代孕称除北上广深都可办理出生证明",
      "category": "社会",
      "heat": 35.37,
      "reads": 61.2,
      "discussions": 0.01,
      "originals": 0.0,
      "date": "2025-03-27"
    },
    {
      "rank": 83,
      "title": "王传福称新能源车进入四电时代",
      "category": "汽车",
      "heat": 35.16,
      "reads": 8287.8,
      "discussions": 0.74,
      "originals": 0.03,
      "date": "2025-03-27"
    },
    {
      "rank": 84,
      "title": "张一鸣655亿美元身家登顶中国首富",
      "category": "财经",
      "heat": 35.16,
      "reads": 1990.1,
      "discussions": 0.18,
      "originals": 0.04,
      "date": "2025-03-27"
    },
    {
      "rank": 85,
      "title": "金秀贤想抱着未成年的金赛纶睡觉",
      "category": "明星",
      "heat": 35.15,
      "reads": 6777.3,
      "discussions": 1.4,
      "originals": 0.32,
      "date": "2025-03-27"
    },
    {
      "rank": 86,
      "title": "赵露思生病前和家人几乎不联系",
      "category": "综艺",
      "heat": 35.12,
      "reads": 2587.4,
      "discussions": 0.73,
      "originals": 0.15,
      "date": "2025-03-27"
    },
    {
      "rank": 87,
      "title": "金莎孙丞潇吵架靠狗制止",
      "category": "",
      "heat": 35.09,
      "reads": 709.8,
      "discussions": 0.86,
      "originals": 0.05,
      "date": "2025-03-27"
    },
    {
      "rank": 88,
      "title": "赵雅芝72岁跑马拉松",
      "category": "",
      "heat": 34.98,
      "reads": 1493.1,
      "discussions": 0.31,
      "originals": 0.08,
      "date": "2025-03-27"
    },
    {
      "rank": 89,
      "title": "张檬自曝孕35周臀位绕颈",
      "category": "明星",
      "heat": 34.72,
      "reads": 16000.0,
      "discussions": 0.95,
      "originals": 0.26,
      "date": "2025-03-27"
    },
    {
      "rank": 90,
      "title": "韩安冉妈妈回应女儿参加变形记",
      "category": "明星",
      "heat": 33.97,
      "reads": 3754.4,
      "discussions": 0.2,
      "originals": 0.05,
      "date": "2025-03-27"
    },
    {
      "rank": 91,
      "title": "祝绪丹当着侯佩岑的面说喜欢周杰伦",
      "category": "综艺",
      "heat": 33.31,
      "reads": 6191.2,
      "discussions": 0.71,
      "originals": 0.16,
      "date": "2025-03-27"
    },
    {
      "rank": 92,
      "title": "怪盗基德好伟大的脸",
      "category": "",
      "heat": 32.89,
      "reads": 238.3,
      "discussions": 0.1,
      "originals": 0.04,
      "date": "2025-03-27"
    },
    {
      "rank": 93,
      "title": "泰媒报道迪丽热巴中国娱乐圈女王",
      "category": "明星",
      "heat": 32.79,
      "reads": 2779.1,
      "discussions": 0.99,
      "originals": 0.21,
      "date": "2025-03-27"
    },
    {
      "rank": 94,
      "title": "陈都灵辛云来房车合体",
      "category": "电视剧",
      "heat": 32.33,
      "reads": 2643.0,
      "discussions": 0.65,
      "originals": 0.1,
      "date": "2025-03-27"
    },
    {
      "rank": 95,
      "title": "李嘉诚要卖43个港口给美国企业",
      "category": "",
      "heat": 32.11,
      "reads": 17000.0,
      "discussions": 6.0,
      "originals": 0.32,
      "date": "2025-03-27"
    },
    {
      "rank": 96,
      "title": "吴宣仪宋妍霏合跳kisskissshyshy",
      "category": "",
      "heat": 31.46,
      "reads": 1421.6,
      "discussions": 0.46,
      "originals": 0.05,
      "date": "2025-03-27"
    },
    {
      "rank": 97,
      "title": "51岁男子找17岁女孩代孕前已离异",
      "category": "社会",
      "heat": 31.38,
      "reads": 936.3,
      "discussions": 0.12,
      "originals": 0.03,
      "date": "2025-03-27"
    },
    {
      "rank": 98,
      "title": "八项规定是共产党人应做到的基本要求",
      "category": "社会",
      "heat": 31.37,
      "reads": 2027.2,
      "discussions": 0.13,
      "originals": 0.02,
      "date": "2025-03-27"
    },
    {
      "rank": 99,
      "title": "双洁党",
      "category": "",
      "heat": 31.33,
      "reads": 477.8,
      "discussions": 0.2,
      "originals": 0.1,
      "date": "2025-03-27"
    },
    {
      "rank": 100,
      "title": "漫威直播公布复联5阵容",
      "category": "电影",
      "heat": 31.31,
      "reads": 4873.2,
      "discussions": 1.1,
      "originals": 0.1,
      "date": "2025-03-27"
    },
    {
      "rank": 101,
      "title": "50项食品安全国家标准发布",
      "category": "社会",
      "heat": 31.15,
      "reads": 734.1,
      "discussions": 0.23,
      "originals": 0.04,
      "date": "2025-03-27"
    },
    {
      "rank": 102,
      "title": "百万网红自曝确诊多囊卵巢综合征",
      "category": "社会",
      "heat": 31.12,
      "reads": 4601.9,
      "discussions": 0.27,
      "originals": 0.07,
      "date": "2025-03-27"
    },
    {
      "rank": 103,
      "title": "雷军回母校遭遇两级反转",
      "category": "社会",
      "heat": 30.91,
      "reads": 3132.3,
      "discussions": 0.36,
      "originals": 0.04,
      "date": "2025-03-27"
    },
    {
      "rank": 104,
      "title": "周如音黑化",
      "category": "",
      "heat": 30.51,
      "reads": 314.5,
      "discussions": 0.09,
      "originals": 0.03,
      "date": "2025-03-27"
    },
    {
      "rank": 105,
      "title": "金赛纶挚友曝金秀贤出轨",
      "category": "明星",
      "heat": 30.38,
      "reads": 8627.5,
      "discussions": 0.66,
      "originals": 0.15,
      "date": "2025-03-27"
    },
    {
      "rank": 106,
      "title": "于正狂赞赵晴绝世容颜",
      "category": "明星",
      "heat": 30.34,
      "reads": 5689.7,
      "discussions": 0.5,
      "originals": 0.12,
      "date": "2025-03-27"
    },
    {
      "rank": 107,
      "title": "抢凤冠冰箱贴的队排到了国博大门外",
      "category": "社会",
      "heat": 30.29,
      "reads": 1751.0,
      "discussions": 0.31,
      "originals": 0.03,
      "date": "2025-03-27"
    },
    {
      "rank": 108,
      "title": "A股",
      "category": "财经",
      "heat": 29.92,
      "reads": 3942000.0,
      "discussions": 1802.5,
      "originals": 69.0,
      "date": "2025-03-27"
    },
    {
      "rank": 109,
      "title": "喻恩泰演技",
      "category": "电视剧",
      "heat": 29.73,
      "reads": 1087.8,
      "discussions": 0.54,
      "originals": 0.04,
      "date": "2025-03-27"
    },
    {
      "rank": 110,
      "title": "北京国际电影节",
      "category": "电影",
      "heat": 28.86,
      "reads": 983000.0,
      "discussions": 4210.4,
      "originals": 10.9,
      "date": "2025-03-27"
    },
    {
      "rank": 111,
      "title": "秦岭这次没能挡住沙尘",
      "category": "社会",
      "heat": 28.84,
      "reads": 987.8,
      "discussions": 0.07,
      "originals": 0.02,
      "date": "2025-03-27"
    },
    {
      "rank": 112,
      "title": "张子枫北影节创投评委",
      "category": "电影",
      "heat": 28.76,
      "reads": 102.3,
      "discussions": 0.05,
      "originals": 0.03,
      "date": "2025-03-27"
    },
    {
      "rank": 113,
      "title": "17岁女孩代孕医院曾被罚300多万",
      "category": "社会",
      "heat": 28.37,
      "reads": 32.5,
      "discussions": 0.01,
      "originals": 0.0,
      "date": "2025-03-27"
    },
    {
      "rank": 114,
      "title": "那些主动退学的博士生",
      "category": "社会",
      "heat": 28.0,
      "reads": 111.5,
      "discussions": 0.01,
      "originals": 0.0,
      "date": "2025-03-27"
    },
    {
      "rank": 115,
      "title": "宋茜回应没喝中药",
      "category": "明星",
      "heat": 27.98,
      "reads": 1745.2,
      "discussions": 0.16,
      "originals": 0.05,
      "date": "2025-03-27"
    },
    {
      "rank": 116,
      "title": "周四是工作效率最低的一天",
      "category": "",
      "heat": 27.97,
      "reads": 3448.3,
      "discussions": 1.9,
      "originals": 0.14,
      "date": "2025-03-27"
    },
    {
      "rank": 117,
      "title": "金秀贤金赛纶2016年聊天记录",
      "category": "明星",
      "heat": 27.75,
      "reads": 2924.1,
      "discussions": 0.92,
      "originals": 0.05,
      "date": "2025-03-27"
    },
    {
      "rank": 118,
      "title": "金赛纶和朋友的聊天记录公开",
      "category": "明星",
      "heat": 27.51,
      "reads": 858.9,
      "discussions": 0.07,
      "originals": 0.02,
      "date": "2025-03-27"
    },
    {
      "rank": 119,
      "title": "吃饭跑步和恋爱",
      "category": "电视剧",
      "heat": 27.14,
      "reads": 17000.0,
      "discussions": 1110.6,
      "originals": 0.73,
      "date": "2025-03-27"
    },
    {
      "rank": 120,
      "title": "小S把粉丝送的礼物珍藏十年",
      "category": "明星",
      "heat": 27.11,
      "reads": 2760.2,
      "discussions": 0.25,
      "originals": 0.05,
      "date": "2025-03-27"
    },
    {
      "rank": 121,
      "title": "王一博现身宁波国际赛道",
      "category": "体育",
      "heat": 27.04,
      "reads": 699.1,
      "discussions": 1.2,
      "originals": 0.17,
      "date": "2025-03-27"
    },
    {
      "rank": 122,
      "title": "错误洗头方式会导致脂溢性皮炎",
      "category": "社会",
      "heat": 26.76,
      "reads": 7906.4,
      "discussions": 1.1,
      "originals": 0.26,
      "date": "2025-03-27"
    },
    {
      "rank": 123,
      "title": "刘雯VOGUE四月刊封面",
      "category": "时尚",
      "heat": 26.56,
      "reads": 366.3,
      "discussions": 0.17,
      "originals": 0.01,
      "date": "2025-03-27"
    },
    {
      "rank": 124,
      "title": "男子有6次抢劫前科又当街作案",
      "category": "社会",
      "heat": 26.09,
      "reads": 137.6,
      "discussions": 0.02,
      "originals": 0.01,
      "date": "2025-03-27"
    },
    {
      "rank": 125,
      "title": "拔牙坠楼身亡女子家属最新发声",
      "category": "社会",
      "heat": 25.78,
      "reads": 1736.0,
      "discussions": 0.1,
      "originals": 0.03,
      "date": "2025-03-27"
    },
    {
      "rank": 126,
      "title": "曾黎闲鱼",
      "category": "",
      "heat": 25.28,
      "reads": 7529.4,
      "discussions": 1.9,
      "originals": 0.79,
      "date": "2025-03-27"
    },
    {
      "rank": 127,
      "title": "辛云来疯子",
      "category": "",
      "heat": 25.0,
      "reads": 1746.5,
      "discussions": 0.16,
      "originals": 0.06,
      "date": "2025-03-27"
    },
    {
      "rank": 128,
      "title": "羽衣甘蓝奶茶或热量超标",
      "category": "社会",
      "heat": 24.85,
      "reads": 2172.9,
      "discussions": 0.35,
      "originals": 0.08,
      "date": "2025-03-27"
    },
    {
      "rank": 129,
      "title": "阮惜文下线",
      "category": "电视剧",
      "heat": 24.61,
      "reads": 1452.0,
      "discussions": 0.85,
      "originals": 0.16,
      "date": "2025-03-27"
    },
    {
      "rank": 130,
      "title": "念无双",
      "category": "电视剧",
      "heat": 24.37,
      "reads": 90000.0,
      "discussions": 1254.5,
      "originals": 2.3,
      "date": "2025-03-27"
    },
    {
      "rank": 131,
      "title": "王一博刘雨昕登MIV媒体影响力榜",
      "category": "明星",
      "heat": 24.24,
      "reads": 358.2,
      "discussions": 0.31,
      "originals": 0.05,
      "date": "2025-03-27"
    },
    {
      "rank": 132,
      "title": "IU权志龙再唱Palette",
      "category": "明星",
      "heat": 24.12,
      "reads": 2075.1,
      "discussions": 0.81,
      "originals": 0.09,
      "date": "2025-03-27"
    },
    {
      "rank": 133,
      "title": "肖战满头小夹子",
      "category": "明星",
      "heat": 24.11,
      "reads": 4435.1,
      "discussions": 16.5,
      "originals": 1.7,
      "date": "2025-03-27"
    },
    {
      "rank": 134,
      "title": "理想开源汽车操作系统",
      "category": "社会",
      "heat": 23.97,
      "reads": 716.5,
      "discussions": 1.4,
      "originals": 0.03,
      "date": "2025-03-27"
    },
    {
      "rank": 135,
      "title": "嫁反派",
      "category": "",
      "heat": 23.94,
      "reads": 871.6,
      "discussions": 0.88,
      "originals": 0.13,
      "date": "2025-03-27"
    },
    {
      "rank": 136,
      "title": "故意让内向的孩子抽到了空白签",
      "category": "社会",
      "heat": 23.54,
      "reads": 1378.4,
      "discussions": 0.24,
      "originals": 0.06,
      "date": "2025-03-27"
    },
    {
      "rank": 137,
      "title": "王宝强脚趾抠地追剧",
      "category": "",
      "heat": 23.51,
      "reads": 365.2,
      "discussions": 0.38,
      "originals": 0.02,
      "date": "2025-03-27"
    },
    {
      "rank": 138,
      "title": "复联5 万磁王",
      "category": "",
      "heat": 23.44,
      "reads": 151.7,
      "discussions": 0.03,
      "originals": 0.02,
      "date": "2025-03-27"
    },
    {
      "rank": 139,
      "title": "凤凰传奇曾毅勇闯电影圈",
      "category": "电影",
      "heat": 23.35,
      "reads": 282.3,
      "discussions": 0.21,
      "originals": 0.02,
      "date": "2025-03-27"
    },
    {
      "rank": 140,
      "title": "张元英宝格丽新闻图",
      "category": "明星",
      "heat": 23.33,
      "reads": 1037.4,
      "discussions": 0.42,
      "originals": 0.08,
      "date": "2025-03-27"
    },
    {
      "rank": 141,
      "title": "女子晒洁癖公公全副武装探望婆婆",
      "category": "社会",
      "heat": 22.73,
      "reads": 908.0,
      "discussions": 0.05,
      "originals": 0.01,
      "date": "2025-03-27"
    },
    {
      "rank": 142,
      "title": "纽约丈夫曝金赛纶给自己的信",
      "category": "明星",
      "heat": 22.64,
      "reads": 6382.9,
      "discussions": 0.73,
      "originals": 0.15,
      "date": "2025-03-27"
    },
    {
      "rank": 143,
      "title": "吴宣仪赛前秀第一",
      "category": "综艺",
      "heat": 22.58,
      "reads": 1581.7,
      "discussions": 1.6,
      "originals": 0.14,
      "date": "2025-03-27"
    },
    {
      "rank": 144,
      "title": "小钺钺被捅伤案件伤人者被判6年",
      "category": "社会",
      "heat": 22.52,
      "reads": 421.2,
      "discussions": 0.02,
      "originals": 0.01,
      "date": "2025-03-27"
    },
    {
      "rank": 145,
      "title": "小红书AI 贴吧男",
      "category": "",
      "heat": 22.5,
      "reads": 409.5,
      "discussions": 0.14,
      "originals": 0.04,
      "date": "2025-03-27"
    },
    {
      "rank": 146,
      "title": "马丽监制首作好好的入围北影节",
      "category": "电影",
      "heat": 22.49,
      "reads": 245.4,
      "discussions": 0.56,
      "originals": 0.06,
      "date": "2025-03-27"
    },
    {
      "rank": 147,
      "title": "00后靠国补狂省两个月生活费",
      "category": "社会",
      "heat": 22.48,
      "reads": 482.9,
      "discussions": 1.1,
      "originals": 0.04,
      "date": "2025-03-27"
    },
    {
      "rank": 148,
      "title": "那些社交互动困难的特殊儿童",
      "category": "社会",
      "heat": 22.48,
      "reads": 82.4,
      "discussions": 0.0,
      "originals": 0.0,
      "date": "2025-03-27"
    },
    {
      "rank": 149,
      "title": "张馨予发体重记录",
      "category": "明星",
      "heat": 22.47,
      "reads": 1075.4,
      "discussions": 0.04,
      "originals": 0.01,
      "date": "2025-03-27"
    },
    {
      "rank": 150,
      "title": "金赛纶问金秀贤我这么让你讨厌吗",
      "category": "社会",
      "heat": 22.46,
      "reads": 2577.4,
      "discussions": 0.34,
      "originals": 0.03,
      "date": "2025-03-27"
    },
    {
      "rank": 151,
      "title": "张佳宁脸肿成了蜜蜂小狗",
      "category": "明星",
      "heat": 22.46,
      "reads": 1297.7,
      "discussions": 0.08,
      "originals": 0.02,
      "date": "2025-03-27"
    },
    {
      "rank": 152,
      "title": "于正曝男演员删女主戏份",
      "category": "明星",
      "heat": 22.45,
      "reads": 1826.0,
      "discussions": 0.07,
      "originals": 0.03,
      "date": "2025-03-27"
    },
    {
      "rank": 153,
      "title": "朝鲜公布新型无人机画面",
      "category": "社会",
      "heat": 22.45,
      "reads": 372.6,
      "discussions": 0.03,
      "originals": 0.01,
      "date": "2025-03-27"
    },
    {
      "rank": 154,
      "title": "孙颖莎解锁拍照新动作",
      "category": "",
      "heat": 22.44,
      "reads": 13.1,
      "discussions": 0.01,
      "originals": 0.01,
      "date": "2025-03-27"
    },
    {
      "rank": 155,
      "title": "丹宁高速水阳段桥梁垮塌灾害调查评估报告",
      "category": "社会",
      "heat": 22.44,
      "reads": 289.3,
      "discussions": 0.04,
      "originals": 0.0,
      "date": "2025-03-27"
    },
    {
      "rank": 156,
      "title": "14岁男孩为躲狗追被卷车底致截肢",
      "category": "社会",
      "heat": 22.43,
      "reads": 170.7,
      "discussions": 0.01,
      "originals": 0.0,
      "date": "2025-03-27"
    },
    {
      "rank": 157,
      "title": "小齐机器人是来加入这个家的",
      "category": "",
      "heat": 22.43,
      "reads": 0.0,
      "discussions": 0.0,
      "originals": 0.0,
      "date": "2025-03-27"
    },
    {
      "rank": 158,
      "title": "美涉密群聊拉错人事件持续发酵",
      "category": "社会",
      "heat": 22.34,
      "reads": 935.3,
      "discussions": 0.1,
      "originals": 0.02,
      "date": "2025-03-27"
    },
    {
      "rank": 159,
      "title": "IG战胜LNG",
      "category": "游戏",
      "heat": 22.3,
      "reads": 12000.0,
      "discussions": 1.8,
      "originals": 0.05,
      "date": "2025-03-27"
    },
    {
      "rank": 160,
      "title": "赵雅芝回应儿子是男版的自己",
      "category": "明星",
      "heat": 22.1,
      "reads": 1506.3,
      "discussions": 0.11,
      "originals": 0.03,
      "date": "2025-03-27"
    },
    {
      "rank": 161,
      "title": "智搜预测未来中国首富",
      "category": "互联网",
      "heat": 21.95,
      "reads": 192.1,
      "discussions": 0.02,
      "originals": 0.01,
      "date": "2025-03-27"
    },
    {
      "rank": 162,
      "title": "刘晓庆回应演短剧遭朋友质疑丢人",
      "category": "社会",
      "heat": 21.69,
      "reads": 1954.1,
      "discussions": 0.08,
      "originals": 0.02,
      "date": "2025-03-27"
    },
    {
      "rank": 163,
      "title": "王俊凯邪恶叮当猫",
      "category": "电影",
      "heat": 21.66,
      "reads": 617.0,
      "discussions": 0.46,
      "originals": 0.17,
      "date": "2025-03-27"
    },
    {
      "rank": 164,
      "title": "赵丽颖模仿孙悟空海边奔跑",
      "category": "明星",
      "heat": 21.66,
      "reads": 2025.9,
      "discussions": 0.32,
      "originals": 0.06,
      "date": "2025-03-27"
    },
    {
      "rank": 165,
      "title": "4岁双胞胎捐髓救妈妈",
      "category": "社会",
      "heat": 21.65,
      "reads": 345.3,
      "discussions": 0.05,
      "originals": 0.01,
      "date": "2025-03-27"
    },
    {
      "rank": 166,
      "title": "范丞丞淋过雨所以给张真源撑伞",
      "category": "",
      "heat": 21.59,
      "reads": 543.7,
      "discussions": 1.2,
      "originals": 0.12,
      "date": "2025-03-27"
    },
    {
      "rank": 167,
      "title": "刘晓庆短剧中演婆婆被儿媳台词震惊",
      "category": "",
      "heat": 21.43,
      "reads": 2155.2,
      "discussions": 0.11,
      "originals": 0.02,
      "date": "2025-03-27"
    },
    {
      "rank": 168,
      "title": "今屿痞帅全开",
      "category": "游戏",
      "heat": 21.39,
      "reads": 39.0,
      "discussions": 0.26,
      "originals": 0.01,
      "date": "2025-03-27"
    },
    {
      "rank": 169,
      "title": "湖南卫视重映新还珠格格",
      "category": "电视剧",
      "heat": 21.18,
      "reads": 2233.5,
      "discussions": 1.6,
      "originals": 0.26,
      "date": "2025-03-27"
    },
    {
      "rank": 170,
      "title": "中方反对侵犯损害他国正当权益行为",
      "category": "",
      "heat": 21.13,
      "reads": 786.8,
      "discussions": 0.07,
      "originals": 0.01,
      "date": "2025-03-27"
    },
    {
      "rank": 171,
      "title": "玫瑰 想离婚",
      "category": "",
      "heat": 21.12,
      "reads": 3058.6,
      "discussions": 0.44,
      "originals": 0.17,
      "date": "2025-03-27"
    },
    {
      "rank": 172,
      "title": "宋茜听不懂中药梗",
      "category": "明星",
      "heat": 21.12,
      "reads": 404.6,
      "discussions": 0.04,
      "originals": 0.01,
      "date": "2025-03-27"
    },
    {
      "rank": 173,
      "title": "奔跑吧全员黄鹤楼开跑",
      "category": "社会",
      "heat": 21.11,
      "reads": 2135.3,
      "discussions": 1.2,
      "originals": 0.1,
      "date": "2025-03-27"
    },
    {
      "rank": 174,
      "title": "又一批马拉松亲密事件照外泄",
      "category": "社会",
      "heat": 21.09,
      "reads": 1967.2,
      "discussions": 0.1,
      "originals": 0.02,
      "date": "2025-03-27"
    },
    {
      "rank": 175,
      "title": "盘点近10年龙标001号故事片电影",
      "category": "电影",
      "heat": 21.08,
      "reads": 17.7,
      "discussions": 0.0,
      "originals": 0.0,
      "date": "2025-03-27"
    },
    {
      "rank": 176,
      "title": "莲花味精辟谣穷得只剩一栋办公楼",
      "category": "社会",
      "heat": 21.05,
      "reads": 4935.2,
      "discussions": 0.41,
      "originals": 0.08,
      "date": "2025-03-27"
    },
    {
      "rank": 177,
      "title": "法国向乌克兰追加20亿欧元军援",
      "category": "社会",
      "heat": 21.04,
      "reads": 22.0,
      "discussions": 0.0,
      "originals": 0.0,
      "date": "2025-03-27"
    },
    {
      "rank": 178,
      "title": "男子给情人转账50万妻子起诉要回",
      "category": "社会",
      "heat": 21.02,
      "reads": 123.4,
      "discussions": 0.01,
      "originals": 0.0,
      "date": "2025-03-27"
    },
    {
      "rank": 179,
      "title": "玫瑰 毛子",
      "category": "",
      "heat": 21.0,
      "reads": 269.5,
      "discussions": 0.03,
      "originals": 0.02,
      "date": "2025-03-27"
    },
    {
      "rank": 180,
      "title": "杨紫国色芳华琼台玉露照进现实",
      "category": "电视剧",
      "heat": 21.0,
      "reads": 523.7,
      "discussions": 2.1,
      "originals": 0.22,
      "date": "2025-03-27"
    },
    {
      "rank": 181,
      "title": "谢娜纪念偶像来了十周年",
      "category": "明星",
      "heat": 20.99,
      "reads": 1448.5,
      "discussions": 0.1,
      "originals": 0.04,
      "date": "2025-03-27"
    },
    {
      "rank": 182,
      "title": "小婉管乐连睡觉都分不开",
      "category": "",
      "heat": 20.91,
      "reads": 651.4,
      "discussions": 0.56,
      "originals": 0.02,
      "date": "2025-03-27"
    },
    {
      "rank": 183,
      "title": "马斯克再登顶世界首富",
      "category": "财经",
      "heat": 20.89,
      "reads": 773.4,
      "discussions": 0.06,
      "originals": 0.01,
      "date": "2025-03-27"
    },
    {
      "rank": 184,
      "title": "为啥过敏后会觉得那么痒",
      "category": "社会",
      "heat": 20.86,
      "reads": 163.5,
      "discussions": 0.16,
      "originals": 0.03,
      "date": "2025-03-27"
    },
    {
      "rank": 185,
      "title": "曝光千奇百怪的走私方式",
      "category": "社会",
      "heat": 20.79,
      "reads": 604.7,
      "discussions": 0.11,
      "originals": 0.02,
      "date": "2025-03-27"
    },
    {
      "rank": 186,
      "title": "美涉密群聊内容具体到战机起飞时间",
      "category": "社会",
      "heat": 20.77,
      "reads": 432.8,
      "discussions": 0.06,
      "originals": 0.01,
      "date": "2025-03-27"
    },
    {
      "rank": 187,
      "title": "Ning回应乐言",
      "category": "游戏",
      "heat": 20.53,
      "reads": 372.5,
      "discussions": 0.07,
      "originals": 0.0,
      "date": "2025-03-27"
    },
    {
      "rank": 188,
      "title": "辛云来 单麦王子",
      "category": "",
      "heat": 20.38,
      "reads": 232.1,
      "discussions": 0.1,
      "originals": 0.04,
      "date": "2025-03-27"
    },
    {
      "rank": 189,
      "title": "王者荣耀",
      "category": "游戏",
      "heat": 20.36,
      "reads": 14313000.0,
      "discussions": 9237.2,
      "originals": 233.0,
      "date": "2025-03-27"
    },
    {
      "rank": 190,
      "title": "傅云夕女儿 亲生",
      "category": "",
      "heat": 20.28,
      "reads": 4091.3,
      "discussions": 1.9,
      "originals": 0.66,
      "date": "2025-03-27"
    },
    {
      "rank": 191,
      "title": "黄圣依要重回影视圈了",
      "category": "",
      "heat": 20.16,
      "reads": 241.2,
      "discussions": 0.44,
      "originals": 0.03,
      "date": "2025-03-27"
    },
    {
      "rank": 192,
      "title": "老祖宗暴躁咆哮我们会心一笑",
      "category": "社会",
      "heat": 20.01,
      "reads": 79.6,
      "discussions": 0.01,
      "originals": 0.0,
      "date": "2025-03-27"
    },
    {
      "rank": 193,
      "title": "盒子里的猫",
      "category": "综艺",
      "heat": 19.64,
      "reads": 190000.0,
      "discussions": 2325.4,
      "originals": 4.4,
      "date": "2025-03-27"
    },
    {
      "rank": 194,
      "title": "日本环球影城偶遇吴磊",
      "category": "明星",
      "heat": 19.62,
      "reads": 292.5,
      "discussions": 0.38,
      "originals": 0.03,
      "date": "2025-03-27"
    },
    {
      "rank": 195,
      "title": "儿童断指事件后小鹏汽车升级防夹功能",
      "category": "社会",
      "heat": 19.61,
      "reads": 206.0,
      "discussions": 0.02,
      "originals": 0.0,
      "date": "2025-03-27"
    },
    {
      "rank": 196,
      "title": "胖东来回应胖都来",
      "category": "财经",
      "heat": 19.6,
      "reads": 1652.0,
      "discussions": 0.07,
      "originals": 0.02,
      "date": "2025-03-27"
    },
    {
      "rank": 197,
      "title": "许佳琪少年阮惜文杀青",
      "category": "",
      "heat": 19.48,
      "reads": 46.2,
      "discussions": 0.05,
      "originals": 0.01,
      "date": "2025-03-27"
    },
    {
      "rank": 198,
      "title": "雁回时",
      "category": "电视剧",
      "heat": 19.45,
      "reads": 83000.0,
      "discussions": 409.1,
      "originals": 3.6,
      "date": "2025-03-27"
    },
    {
      "rank": 199,
      "title": "黄奕惹到王俊凯算是踢到铁板了",
      "category": "综艺",
      "heat": 19.26,
      "reads": 655.1,
      "discussions": 0.39,
      "originals": 0.04,
      "date": "2025-03-27"
    },
    {
      "rank": 200,
      "title": "俄乌停火协议最新进展",
      "category": "",
      "heat": 18.9,
      "reads": 553.1,
      "discussions": 0.03,
      "originals": 0.0,
      "date": "2025-03-27"
    },
    {
      "rank": 201,
      "title": "雁回时预告",
      "category": "电视剧",
      "heat": 18.89,
      "reads": 839.3,
      "discussions": 0.11,
      "originals": 0.01,
      "date": "2025-03-27"
    },
    {
      "rank": 202,
      "title": "食品安全对零添加的要求更严格了",
      "category": "社会",
      "heat": 18.89,
      "reads": 185.2,
      "discussions": 0.03,
      "originals": 0.01,
      "date": "2025-03-27"
    },
    {
      "rank": 203,
      "title": "画江湖之不良人",
      "category": "动漫",
      "heat": 18.8,
      "reads": 118000.0,
      "discussions": 113.2,
      "originals": 7.6,
      "date": "2025-03-27"
    },
    {
      "rank": 204,
      "title": "蜜雪集团2024年利润44.542亿元",
      "category": "社会",
      "heat": 18.77,
      "reads": 1641.1,
      "discussions": 0.14,
      "originals": 0.03,
      "date": "2025-03-27"
    },
    {
      "rank": 205,
      "title": "阿瑟请开跑",
      "category": "",
      "heat": 18.64,
      "reads": 209.1,
      "discussions": 0.7,
      "originals": 0.02,
      "date": "2025-03-27"
    },
    {
      "rank": 206,
      "title": "鸣潮",
      "category": "游戏",
      "heat": 18.51,
      "reads": 224000.0,
      "discussions": 138.4,
      "originals": 3.9,
      "date": "2025-03-27"
    },
    {
      "rank": 207,
      "title": "吴艳妮积分首登亚洲第一",
      "category": "体育",
      "heat": 18.47,
      "reads": 827.7,
      "discussions": 0.04,
      "originals": 0.01,
      "date": "2025-03-27"
    },
    {
      "rank": 208,
      "title": "山东一任教31年教师临近退休突遭解聘",
      "category": "社会",
      "heat": 18.46,
      "reads": 832.2,
      "discussions": 0.06,
      "originals": 0.01,
      "date": "2025-03-27"
    },
    {
      "rank": 209,
      "title": "医院穿刺抽液时导丝落入男童胸腔",
      "category": "社会",
      "heat": 18.45,
      "reads": 1001.4,
      "discussions": 0.03,
      "originals": 0.01,
      "date": "2025-03-27"
    },
    {
      "rank": 210,
      "title": "飞鹤奶粉补贴惊到宝宝了",
      "category": "社会",
      "heat": 18.34,
      "reads": 2549.1,
      "discussions": 1.0,
      "originals": 0.01,
      "date": "2025-03-27"
    },
    {
      "rank": 211,
      "title": "千禾回应不允许再使用零添加",
      "category": "财经",
      "heat": 18.3,
      "reads": 170.8,
      "discussions": 0.01,
      "originals": 0.0,
      "date": "2025-03-27"
    },
    {
      "rank": 212,
      "title": "宋雨琦 受伤",
      "category": "",
      "heat": 18.11,
      "reads": 57.8,
      "discussions": 0.07,
      "originals": 0.02,
      "date": "2025-03-27"
    },
    {
      "rank": 213,
      "title": "宋茜 喝什么中药一起喝茶吧",
      "category": "",
      "heat": 17.99,
      "reads": 139.7,
      "discussions": 0.05,
      "originals": 0.01,
      "date": "2025-03-27"
    },
    {
      "rank": 214,
      "title": "王楚钦拍公式照",
      "category": "",
      "heat": 17.9,
      "reads": 100.6,
      "discussions": 0.07,
      "originals": 0.03,
      "date": "2025-03-27"
    },
    {
      "rank": 215,
      "title": "云来意味不明的演技让剧情扑朔迷离",
      "category": "",
      "heat": 17.89,
      "reads": 15.8,
      "discussions": 0.02,
      "originals": 0.0,
      "date": "2025-03-27"
    },
    {
      "rank": 216,
      "title": "嚼口香糖会释放微塑料进入唾液",
      "category": "健康",
      "heat": 17.88,
      "reads": 75.5,
      "discussions": 0.0,
      "originals": 0.0,
      "date": "2025-03-27"
    },
    {
      "rank": 217,
      "title": "多所院校发布考研录取名单",
      "category": "",
      "heat": 17.88,
      "reads": 88.4,
      "discussions": 0.23,
      "originals": 0.0,
      "date": "2025-03-27"
    },
    {
      "rank": 218,
      "title": "孙颖莎与队友合照好开心",
      "category": "",
      "heat": 17.87,
      "reads": 112.9,
      "discussions": 0.08,
      "originals": 0.04,
      "date": "2025-03-27"
    },
    {
      "rank": 219,
      "title": "小鹏方回应车屏幕夹断男童手指",
      "category": "社会",
      "heat": 17.75,
      "reads": 408.0,
      "discussions": 0.02,
      "originals": 0.0,
      "date": "2025-03-27"
    },
    {
      "rank": 220,
      "title": "国防部称将坚决打掉一切台独分裂图谋",
      "category": "社会",
      "heat": 17.75,
      "reads": 275.8,
      "discussions": 0.04,
      "originals": 0.01,
      "date": "2025-03-27"
    },
    {
      "rank": 221,
      "title": "刘学义男妲己",
      "category": "电视剧",
      "heat": 17.72,
      "reads": 210.9,
      "discussions": 0.59,
      "originals": 0.05,
      "date": "2025-03-27"
    },
    {
      "rank": 222,
      "title": "马拉松",
      "category": "",
      "heat": 17.64,
      "reads": 188000.0,
      "discussions": 120.7,
      "originals": 8.6,
      "date": "2025-03-27"
    },
    {
      "rank": 223,
      "title": "曹颖倪虹洁都以为吴宣仪20岁",
      "category": "",
      "heat": 17.61,
      "reads": 1210.5,
      "discussions": 0.67,
      "originals": 0.03,
      "date": "2025-03-27"
    },
    {
      "rank": 224,
      "title": "不良人",
      "category": "动漫",
      "heat": 17.55,
      "reads": 14000.0,
      "discussions": 11.2,
      "originals": 2.0,
      "date": "2025-03-27"
    },
    {
      "rank": 225,
      "title": "4名美军士兵在立陶宛失踪",
      "category": "",
      "heat": 17.51,
      "reads": 679.8,
      "discussions": 0.08,
      "originals": 0.01,
      "date": "2025-03-27"
    },
    {
      "rank": 226,
      "title": "国家发改委原副主任徐宪平被查",
      "category": "",
      "heat": 17.16,
      "reads": 211.7,
      "discussions": 0.01,
      "originals": 0.01,
      "date": "2025-03-27"
    },
    {
      "rank": 227,
      "title": "不会做蛋糕也能开蛋糕店了",
      "category": "",
      "heat": 17.11,
      "reads": 26.7,
      "discussions": 0.01,
      "originals": 0.0,
      "date": "2025-03-27"
    },
    {
      "rank": 228,
      "title": "女人别总说对不起",
      "category": "",
      "heat": 17.06,
      "reads": 37.8,
      "discussions": 0.36,
      "originals": 0.01,
      "date": "2025-03-27"
    },
    {
      "rank": 229,
      "title": "派出所回应银行门口疑似有人抢钱",
      "category": "社会",
      "heat": 16.87,
      "reads": 4.0,
      "discussions": 0.02,
      "originals": 0.0,
      "date": "2025-03-27"
    },
    {
      "rank": 230,
      "title": "学校回应教师临近退休突遭解聘",
      "category": "社会",
      "heat": 16.85,
      "reads": 531.7,
      "discussions": 0.05,
      "originals": 0.01,
      "date": "2025-03-27"
    },
    {
      "rank": 231,
      "title": "张馨予的瘦身思路",
      "category": "明星",
      "heat": 16.73,
      "reads": 962.6,
      "discussions": 0.04,
      "originals": 0.01,
      "date": "2025-03-27"
    },
    {
      "rank": 232,
      "title": "中国为什么更适合造智能车和机器人",
      "category": "社会",
      "heat": 16.71,
      "reads": 177.0,
      "discussions": 0.02,
      "originals": 0.0,
      "date": "2025-03-27"
    },
    {
      "rank": 233,
      "title": "金赛纶曾打电话给自杀预防中心",
      "category": "社会",
      "heat": 16.6,
      "reads": 749.6,
      "discussions": 0.02,
      "originals": 0.0,
      "date": "2025-03-27"
    },
    {
      "rank": 234,
      "title": "电动车标成新型烟卡",
      "category": "社会",
      "heat": 16.43,
      "reads": 553.6,
      "discussions": 0.02,
      "originals": 0.01,
      "date": "2025-03-27"
    },
    {
      "rank": 235,
      "title": "肖战胶片唱针",
      "category": "明星",
      "heat": 16.31,
      "reads": 165.5,
      "discussions": 0.2,
      "originals": 0.06,
      "date": "2025-03-27"
    },
    {
      "rank": 236,
      "title": "樊振东19岁首夺三大赛冠军",
      "category": "体育",
      "heat": 16.22,
      "reads": 1561.7,
      "discussions": 0.19,
      "originals": 0.04,
      "date": "2025-03-27"
    },
    {
      "rank": 237,
      "title": "小小的勇气开播",
      "category": "综艺",
      "heat": 16.12,
      "reads": 400.3,
      "discussions": 0.44,
      "originals": 0.02,
      "date": "2025-03-27"
    },
    {
      "rank": 238,
      "title": "怎么都爱找赵丽颖拍现实主义",
      "category": "",
      "heat": 15.96,
      "reads": 107.3,
      "discussions": 0.05,
      "originals": 0.02,
      "date": "2025-03-27"
    },
    {
      "rank": 239,
      "title": "李晟参加浪姐后瘦了10斤",
      "category": "综艺",
      "heat": 15.87,
      "reads": 1105.8,
      "discussions": 0.07,
      "originals": 0.01,
      "date": "2025-03-27"
    },
    {
      "rank": 240,
      "title": "黄子佼承认持有7名少女非法影片",
      "category": "明星",
      "heat": 15.69,
      "reads": 8762.4,
      "discussions": 0.53,
      "originals": 0.17,
      "date": "2025-03-27"
    },
    {
      "rank": 241,
      "title": "黄圣依说和张凌赫搭什么都可以",
      "category": "明星",
      "heat": 15.52,
      "reads": 178.4,
      "discussions": 0.02,
      "originals": 0.01,
      "date": "2025-03-27"
    },
    {
      "rank": 242,
      "title": "雁回时 烧脑",
      "category": "",
      "heat": 15.28,
      "reads": 116.0,
      "discussions": 0.14,
      "originals": 0.01,
      "date": "2025-03-27"
    },
    {
      "rank": 243,
      "title": "WTT印度金奈站场馆掉鸟屎",
      "category": "体育",
      "heat": 15.26,
      "reads": 161.7,
      "discussions": 0.02,
      "originals": 0.01,
      "date": "2025-03-27"
    },
    {
      "rank": 244,
      "title": "晋江小说疑似抄袭明日方舟",
      "category": "",
      "heat": 15.2,
      "reads": 433.6,
      "discussions": 0.08,
      "originals": 0.03,
      "date": "2025-03-27"
    },
    {
      "rank": 245,
      "title": "原神",
      "category": "游戏",
      "heat": 15.18,
      "reads": 4660000.0,
      "discussions": 3644.9,
      "originals": 179.9,
      "date": "2025-03-27"
    },
    {
      "rank": 246,
      "title": "孟美岐回应千万直拍",
      "category": "明星",
      "heat": 15.17,
      "reads": 1293.1,
      "discussions": 0.19,
      "originals": 0.04,
      "date": "2025-03-27"
    },
    {
      "rank": 247,
      "title": "姚安娜王安宇华为阔折叠一用就爱",
      "category": "明星",
      "heat": 15.16,
      "reads": 126.5,
      "discussions": 0.52,
      "originals": 0.01,
      "date": "2025-03-27"
    },
    {
      "rank": 248,
      "title": "陈冠希回应未来是否拍戏",
      "category": "明星",
      "heat": 15.16,
      "reads": 1278.5,
      "discussions": 0.06,
      "originals": 0.01,
      "date": "2025-03-27"
    },
    {
      "rank": 249,
      "title": "女孩遭强奸案民警被控渎职不予立案",
      "category": "社会",
      "heat": 15.13,
      "reads": 1366.4,
      "discussions": 0.14,
      "originals": 0.02,
      "date": "2025-03-27"
    },
    {
      "rank": 250,
      "title": "金晨官宣北影节评委",
      "category": "电影",
      "heat": 15.06,
      "reads": 507.9,
      "discussions": 0.58,
      "originals": 0.04,
      "date": "2025-03-27"
    },
    {
      "rank": 251,
      "title": "下岗女工干快递15年领数千退休金",
      "category": "社会",
      "heat": 15.02,
      "reads": 627.4,
      "discussions": 0.31,
      "originals": 0.16,
      "date": "2025-03-27"
    },
    {
      "rank": 252,
      "title": "头一次见这么有活人感的舞蹈",
      "category": "搞笑",
      "heat": 14.92,
      "reads": 10.2,
      "discussions": 0.08,
      "originals": 0.02,
      "date": "2025-03-27"
    },
    {
      "rank": 253,
      "title": "李晟为什么爆火出圈",
      "category": "明星",
      "heat": 14.85,
      "reads": 3066.6,
      "discussions": 0.66,
      "originals": 0.08,
      "date": "2025-03-27"
    },
    {
      "rank": 254,
      "title": "任天堂直面会",
      "category": "游戏",
      "heat": 14.75,
      "reads": 48000.0,
      "discussions": 17.6,
      "originals": 0.22,
      "date": "2025-03-27"
    },
    {
      "rank": 255,
      "title": "国防部回应福建舰第7次海试",
      "category": "军事",
      "heat": 14.68,
      "reads": 317.7,
      "discussions": 0.02,
      "originals": 0.0,
      "date": "2025-03-27"
    },
    {
      "rank": 256,
      "title": "国博C位冰箱贴原型禁止出境展览",
      "category": "社会",
      "heat": 14.55,
      "reads": 328.3,
      "discussions": 0.12,
      "originals": 0.01,
      "date": "2025-03-27"
    },
    {
      "rank": 257,
      "title": "中央气象台5个预警齐发",
      "category": "社会",
      "heat": 14.53,
      "reads": 652.3,
      "discussions": 0.2,
      "originals": 0.03,
      "date": "2025-03-27"
    },
    {
      "rank": 258,
      "title": "国防部称日方最没有资格拿台湾说事",
      "category": "",
      "heat": 14.53,
      "reads": 362.5,
      "discussions": 0.03,
      "originals": 0.0,
      "date": "2025-03-27"
    },
    {
      "rank": 259,
      "title": "陈都灵桃花写真",
      "category": "明星",
      "heat": 14.37,
      "reads": 367.5,
      "discussions": 0.11,
      "originals": 0.04,
      "date": "2025-03-27"
    },
    {
      "rank": 260,
      "title": "林俊杰44岁生日照",
      "category": "明星",
      "heat": 14.35,
      "reads": 254.7,
      "discussions": 0.02,
      "originals": 0.01,
      "date": "2025-03-27"
    },
    {
      "rank": 261,
      "title": "周杰伦昆凌穿情侣装看展",
      "category": "明星",
      "heat": 14.34,
      "reads": 753.6,
      "discussions": 0.03,
      "originals": 0.01,
      "date": "2025-03-27"
    },
    {
      "rank": 262,
      "title": "哈马斯发言人遭轰炸身亡",
      "category": "社会",
      "heat": 14.33,
      "reads": 943.6,
      "discussions": 0.08,
      "originals": 0.01,
      "date": "2025-03-27"
    },
    {
      "rank": 263,
      "title": "0.03元开通试用后每个月被扣近百元",
      "category": "社会",
      "heat": 14.28,
      "reads": 572.3,
      "discussions": 0.08,
      "originals": 0.01,
      "date": "2025-03-27"
    },
    {
      "rank": 264,
      "title": "李晟唱功",
      "category": "综艺",
      "heat": 14.24,
      "reads": 950.6,
      "discussions": 0.09,
      "originals": 0.01,
      "date": "2025-03-27"
    },
    {
      "rank": 265,
      "title": "林允古早千金文女主",
      "category": "",
      "heat": 14.24,
      "reads": 36.7,
      "discussions": 0.57,
      "originals": 0.02,
      "date": "2025-03-27"
    },
    {
      "rank": 266,
      "title": "Doinb确定明年不打LPL",
      "category": "游戏",
      "heat": 14.14,
      "reads": 1179.8,
      "discussions": 0.13,
      "originals": 0.01,
      "date": "2025-03-27"
    },
    {
      "rank": 267,
      "title": "迪丽热巴海边六宫格",
      "category": "明星",
      "heat": 14.13,
      "reads": 254.4,
      "discussions": 0.05,
      "originals": 0.02,
      "date": "2025-03-27"
    },
    {
      "rank": 268,
      "title": "IG战胜LGD",
      "category": "游戏",
      "heat": 14.06,
      "reads": 14000.0,
      "discussions": 1.6,
      "originals": 0.06,
      "date": "2025-03-27"
    },
    {
      "rank": 269,
      "title": "金莎追星赵雅芝成功",
      "category": "明星",
      "heat": 14.06,
      "reads": 634.9,
      "discussions": 0.11,
      "originals": 0.04,
      "date": "2025-03-27"
    },
    {
      "rank": 270,
      "title": "肖战是歌手也是策划",
      "category": "明星",
      "heat": 14.0,
      "reads": 141.6,
      "discussions": 0.16,
      "originals": 0.05,
      "date": "2025-03-27"
    },
    {
      "rank": 271,
      "title": "留给蒋璐霞的兵种不多了",
      "category": "",
      "heat": 13.97,
      "reads": 40.1,
      "discussions": 0.58,
      "originals": 0.01,
      "date": "2025-03-27"
    },
    {
      "rank": 272,
      "title": "邮管局回应云南乡镇快递强收跑腿费",
      "category": "社会",
      "heat": 13.96,
      "reads": 11.8,
      "discussions": 0.0,
      "originals": 0.0,
      "date": "2025-03-27"
    },
    {
      "rank": 273,
      "title": "伊万将对两场国足比赛进行总结",
      "category": "体育",
      "heat": 13.96,
      "reads": 48.5,
      "discussions": 0.01,
      "originals": 0.01,
      "date": "2025-03-27"
    },
    {
      "rank": 274,
      "title": "金秀贤知道金赛纶的一切",
      "category": "明星",
      "heat": 13.76,
      "reads": 1679.4,
      "discussions": 0.06,
      "originals": 0.01,
      "date": "2025-03-27"
    },
    {
      "rank": 275,
      "title": "梁田和混血弟弟纯正年下感",
      "category": "",
      "heat": 13.74,
      "reads": 885.8,
      "discussions": 0.99,
      "originals": 0.02,
      "date": "2025-03-27"
    },
    {
      "rank": 276,
      "title": "猫猫撒娇摔错方向",
      "category": "",
      "heat": 13.68,
      "reads": 90.1,
      "discussions": 0.02,
      "originals": 0.01,
      "date": "2025-03-27"
    },
    {
      "rank": 277,
      "title": "刘学义这次怎么不吃了",
      "category": "明星",
      "heat": 13.62,
      "reads": 370.1,
      "discussions": 0.13,
      "originals": 0.03,
      "date": "2025-03-27"
    },
    {
      "rank": 278,
      "title": "快给陈都灵个种田文剧本",
      "category": "明星",
      "heat": 13.57,
      "reads": 67.0,
      "discussions": 0.49,
      "originals": 0.03,
      "date": "2025-03-27"
    },
    {
      "rank": 279,
      "title": "寒潮带来新一轮气温满减",
      "category": "社会",
      "heat": 13.56,
      "reads": 1030.7,
      "discussions": 0.41,
      "originals": 0.05,
      "date": "2025-03-27"
    },
    {
      "rank": 280,
      "title": "成都浮尘成因",
      "category": "公益",
      "heat": 13.49,
      "reads": 62.2,
      "discussions": 0.06,
      "originals": 0.0,
      "date": "2025-03-27"
    },
    {
      "rank": 281,
      "title": "大16岁女友离世被赶出门男子发声",
      "category": "社会",
      "heat": 13.47,
      "reads": 4030.3,
      "discussions": 0.31,
      "originals": 0.06,
      "date": "2025-03-27"
    },
    {
      "rank": 282,
      "title": "允许自己是一朵晚开的花",
      "category": "社会",
      "heat": 13.42,
      "reads": 799.8,
      "discussions": 0.55,
      "originals": 0.02,
      "date": "2025-03-27"
    },
    {
      "rank": 283,
      "title": "教育局回应小学校门口有学生搜身",
      "category": "社会",
      "heat": 13.37,
      "reads": 762.0,
      "discussions": 0.07,
      "originals": 0.01,
      "date": "2025-03-27"
    },
    {
      "rank": 284,
      "title": "山西午睡文化",
      "category": "",
      "heat": 13.37,
      "reads": 114.1,
      "discussions": 0.07,
      "originals": 0.03,
      "date": "2025-03-27"
    },
    {
      "rank": 285,
      "title": "冲锋衣",
      "category": "",
      "heat": 13.21,
      "reads": 5661.8,
      "discussions": 12.0,
      "originals": 0.95,
      "date": "2025-03-27"
    },
    {
      "rank": 286,
      "title": "台独分子想玩火就别想跑",
      "category": "社会",
      "heat": 13.0,
      "reads": 630.3,
      "discussions": 0.08,
      "originals": 0.01,
      "date": "2025-03-27"
    },
    {
      "rank": 287,
      "title": "奔跑吧",
      "category": "综艺",
      "heat": 12.97,
      "reads": 7941000.0,
      "discussions": 57000.0,
      "originals": 375.8,
      "date": "2025-03-27"
    },
    {
      "rank": 288,
      "title": "美防长否认在有记者的群发作战计划",
      "category": "社会",
      "heat": 12.97,
      "reads": 755.5,
      "discussions": 0.01,
      "originals": 0.0,
      "date": "2025-03-27"
    },
    {
      "rank": 289,
      "title": "NBA",
      "category": "体育",
      "heat": 12.95,
      "reads": 6280000.0,
      "discussions": 2788.2,
      "originals": 84.7,
      "date": "2025-03-27"
    },
    {
      "rank": 290,
      "title": "大张伟爷爷去哪儿",
      "category": "",
      "heat": 12.95,
      "reads": 91.0,
      "discussions": 0.12,
      "originals": 0.02,
      "date": "2025-03-27"
    },
    {
      "rank": 291,
      "title": "零添加究竟带来哪些消费误区",
      "category": "健康",
      "heat": 12.92,
      "reads": 128.8,
      "discussions": 0.06,
      "originals": 0.0,
      "date": "2025-03-27"
    },
    {
      "rank": 292,
      "title": "2024中国科学十大进展发布",
      "category": "社会",
      "heat": 12.9,
      "reads": 492.2,
      "discussions": 0.14,
      "originals": 0.02,
      "date": "2025-03-27"
    },
    {
      "rank": 293,
      "title": "生双胞胎17岁代孕女孩已嫁人",
      "category": "社会",
      "heat": 12.83,
      "reads": 115.6,
      "discussions": 0.01,
      "originals": 0.0,
      "date": "2025-03-27"
    },
    {
      "rank": 294,
      "title": "马拉松职业私兔最高月入4万",
      "category": "社会",
      "heat": 12.8,
      "reads": 1401.3,
      "discussions": 0.14,
      "originals": 0.03,
      "date": "2025-03-27"
    },
    {
      "rank": 295,
      "title": "脾胃不好的8个典型症状",
      "category": "社会",
      "heat": 12.79,
      "reads": 1056.3,
      "discussions": 0.36,
      "originals": 0.02,
      "date": "2025-03-27"
    },
    {
      "rank": 296,
      "title": "国防部批驳七国集团",
      "category": "",
      "heat": 12.7,
      "reads": 27.3,
      "discussions": 0.0,
      "originals": 0.0,
      "date": "2025-03-27"
    },
    {
      "rank": 297,
      "title": "九紫离火运的旺运tips",
      "category": "",
      "heat": 12.68,
      "reads": 11.5,
      "discussions": 0.3,
      "originals": 0.0,
      "date": "2025-03-27"
    },
    {
      "rank": 298,
      "title": "金赛纶方发布会信息汇总",
      "category": "社会",
      "heat": 12.68,
      "reads": 538.7,
      "discussions": 0.04,
      "originals": 0.0,
      "date": "2025-03-27"
    },
    {
      "rank": 299,
      "title": "李嘉诚",
      "category": "",
      "heat": 12.67,
      "reads": 0.0,
      "discussions": 0.0,
      "originals": 0.0,
      "date": "2025-03-27"
    },
    {
      "rank": 300,
      "title": "种地吧",
      "category": "综艺",
      "heat": 12.61,
      "reads": 2874000.0,
      "discussions": 20000.0,
      "originals": 68.0,
      "date": "2025-03-27"
    },
    {
      "rank": 301,
      "title": "晚宴的张艺兴",
      "category": "明星",
      "heat": 12.6,
      "reads": 382.9,
      "discussions": 0.18,
      "originals": 0.01,
      "date": "2025-03-27"
    },
    {
      "rank": 302,
      "title": "河北沧州发生2.8级地震",
      "category": "社会",
      "heat": 12.56,
      "reads": 647.1,
      "discussions": 0.05,
      "originals": 0.02,
      "date": "2025-03-27"
    },
    {
      "rank": 303,
      "title": "中国将择机降准降息",
      "category": "财经",
      "heat": 12.52,
      "reads": 80.6,
      "discussions": 0.02,
      "originals": 0.01,
      "date": "2025-03-27"
    },
    {
      "rank": 304,
      "title": "夏目友人帐绝美一幕",
      "category": "",
      "heat": 12.45,
      "reads": 1.6,
      "discussions": 0.0,
      "originals": 0.0,
      "date": "2025-03-27"
    },
    {
      "rank": 305,
      "title": "赵子豪说澳门见",
      "category": "",
      "heat": 12.32,
      "reads": 16.5,
      "discussions": 0.01,
      "originals": 0.01,
      "date": "2025-03-27"
    },
    {
      "rank": 306,
      "title": "蔡文静穿搭",
      "category": "",
      "heat": 12.32,
      "reads": 316.6,
      "discussions": 0.07,
      "originals": 0.01,
      "date": "2025-03-27"
    },
    {
      "rank": 307,
      "title": "李晟拉高收视率",
      "category": "综艺",
      "heat": 12.3,
      "reads": 893.0,
      "discussions": 0.31,
      "originals": 0.06,
      "date": "2025-03-27"
    },
    {
      "rank": 308,
      "title": "沧州2.8级地震",
      "category": "",
      "heat": 12.09,
      "reads": 134.8,
      "discussions": 0.02,
      "originals": 0.01,
      "date": "2025-03-27"
    },
    {
      "rank": 309,
      "title": "尹正机场冒充刘端端站哥",
      "category": "",
      "heat": 12.08,
      "reads": 164.9,
      "discussions": 0.53,
      "originals": 0.04,
      "date": "2025-03-27"
    },
    {
      "rank": 310,
      "title": "吴艳妮说困难越大越有动力",
      "category": "社会",
      "heat": 11.97,
      "reads": 112.4,
      "discussions": 0.01,
      "originals": 0.0,
      "date": "2025-03-27"
    },
    {
      "rank": 311,
      "title": "全球资金持续流入中国",
      "category": "社会",
      "heat": 11.96,
      "reads": 551.0,
      "discussions": 0.07,
      "originals": 0.02,
      "date": "2025-03-27"
    },
    {
      "rank": 312,
      "title": "每个人都有属于自己的花期",
      "category": "社会",
      "heat": 11.94,
      "reads": 669.1,
      "discussions": 0.79,
      "originals": 0.04,
      "date": "2025-03-27"
    },
    {
      "rank": 313,
      "title": "何泓姗花精灵具象化",
      "category": "",
      "heat": 11.93,
      "reads": 23.0,
      "discussions": 0.54,
      "originals": 0.01,
      "date": "2025-03-27"
    },
    {
      "rank": 314,
      "title": "王宝强回应腹肌消失",
      "category": "社会",
      "heat": 11.89,
      "reads": 722.7,
      "discussions": 0.07,
      "originals": 0.01,
      "date": "2025-03-27"
    },
    {
      "rank": 315,
      "title": "西藏日喀则定日发生3.4级地震",
      "category": "社会",
      "heat": 11.88,
      "reads": 1644.6,
      "discussions": 0.1,
      "originals": 0.04,
      "date": "2025-03-27"
    },
    {
      "rank": 316,
      "title": "福宝上演空中一字马",
      "category": "社会",
      "heat": 11.82,
      "reads": 681.3,
      "discussions": 0.12,
      "originals": 0.02,
      "date": "2025-03-27"
    },
    {
      "rank": 317,
      "title": "刘学义念无双裸上身",
      "category": "电视剧",
      "heat": 11.79,
      "reads": 602.8,
      "discussions": 0.2,
      "originals": 0.05,
      "date": "2025-03-27"
    },
    {
      "rank": 318,
      "title": "小伙靠书法帮父母清债2000万",
      "category": "社会",
      "heat": 11.61,
      "reads": 2157.4,
      "discussions": 0.15,
      "originals": 0.02,
      "date": "2025-03-27"
    },
    {
      "rank": 319,
      "title": "高二女生用扭扭棒复刻明凤冠",
      "category": "社会",
      "heat": 11.6,
      "reads": 336.4,
      "discussions": 0.03,
      "originals": 0.01,
      "date": "2025-03-27"
    },
    {
      "rank": 320,
      "title": "陕西大桥",
      "category": "",
      "heat": 11.6,
      "reads": 1.9,
      "discussions": 0.0,
      "originals": 0.0,
      "date": "2025-03-27"
    },
    {
      "rank": 321,
      "title": "陈哲远好真诚的一款财神爷",
      "category": "明星",
      "heat": 11.53,
      "reads": 17.7,
      "discussions": 0.05,
      "originals": 0.02,
      "date": "2025-03-27"
    },
    {
      "rank": 322,
      "title": "小米王化回应雷军广告报价",
      "category": "财经",
      "heat": 11.38,
      "reads": 368.1,
      "discussions": 0.05,
      "originals": 0.01,
      "date": "2025-03-27"
    },
    {
      "rank": 323,
      "title": "长沙多地发布雷雨大风蓝色预警",
      "category": "社会",
      "heat": 11.3,
      "reads": 249.4,
      "discussions": 0.02,
      "originals": 0.01,
      "date": "2025-03-27"
    },
    {
      "rank": 324,
      "title": "竹林中的刘诗诗",
      "category": "明星",
      "heat": 11.29,
      "reads": 564.9,
      "discussions": 0.12,
      "originals": 0.04,
      "date": "2025-03-27"
    },
    {
      "rank": 325,
      "title": "第五人格七周年",
      "category": "游戏",
      "heat": 11.23,
      "reads": 18000.0,
      "discussions": 25.5,
      "originals": 0.06,
      "date": "2025-03-27"
    },
    {
      "rank": 326,
      "title": "Uzi起诉RNG",
      "category": "游戏",
      "heat": 11.22,
      "reads": 2615.0,
      "discussions": 0.23,
      "originals": 0.02,
      "date": "2025-03-27"
    },
    {
      "rank": 327,
      "title": "念无双今日开播",
      "category": "电视剧",
      "heat": 11.06,
      "reads": 414.0,
      "discussions": 13.2,
      "originals": 0.02,
      "date": "2025-03-27"
    },
    {
      "rank": 328,
      "title": "无锡马拉松",
      "category": "",
      "heat": 11.01,
      "reads": 86000.0,
      "discussions": 29.0,
      "originals": 1.3,
      "date": "2025-03-27"
    },
    {
      "rank": 329,
      "title": "胖东来4月10日起施行实名结账",
      "category": "社会",
      "heat": 11.0,
      "reads": 253.9,
      "discussions": 0.02,
      "originals": 0.01,
      "date": "2025-03-27"
    },
    {
      "rank": 330,
      "title": "湖南卫视连发20条李晟",
      "category": "综艺",
      "heat": 10.97,
      "reads": 755.0,
      "discussions": 0.25,
      "originals": 0.02,
      "date": "2025-03-27"
    },
    {
      "rank": 331,
      "title": "起底臭蛋蛋糕厂",
      "category": "社会",
      "heat": 10.94,
      "reads": 422.0,
      "discussions": 0.06,
      "originals": 0.01,
      "date": "2025-03-27"
    },
    {
      "rank": 332,
      "title": "沙尘暴",
      "category": "",
      "heat": 10.82,
      "reads": 80000.0,
      "discussions": 27.0,
      "originals": 4.4,
      "date": "2025-03-27"
    },
    {
      "rank": 333,
      "title": "王宝强要这么演我可不困了",
      "category": "",
      "heat": 10.78,
      "reads": 227.8,
      "discussions": 0.21,
      "originals": 0.02,
      "date": "2025-03-27"
    },
    {
      "rank": 334,
      "title": "北大教授谈北大和清华学生区别",
      "category": "财经",
      "heat": 10.74,
      "reads": 1943.6,
      "discussions": 0.22,
      "originals": 0.03,
      "date": "2025-03-27"
    },
    {
      "rank": 335,
      "title": "唐嫣吊威亚",
      "category": "电视剧",
      "heat": 10.71,
      "reads": 301.3,
      "discussions": 0.02,
      "originals": 0.01,
      "date": "2025-03-27"
    },
    {
      "rank": 336,
      "title": "棋士 黑色幽默",
      "category": "",
      "heat": 10.68,
      "reads": 72.0,
      "discussions": 0.02,
      "originals": 0.01,
      "date": "2025-03-27"
    },
    {
      "rank": 337,
      "title": "祝绪丹神女执弓",
      "category": "明星",
      "heat": 10.63,
      "reads": 976.5,
      "discussions": 0.31,
      "originals": 0.07,
      "date": "2025-03-27"
    },
    {
      "rank": 338,
      "title": "天链二号04星发射成功",
      "category": "社会",
      "heat": 10.62,
      "reads": 591.4,
      "discussions": 0.17,
      "originals": 0.03,
      "date": "2025-03-27"
    },
    {
      "rank": 339,
      "title": "张晚意越低调网友越多疑",
      "category": "明星",
      "heat": 10.6,
      "reads": 3333.7,
      "discussions": 3.0,
      "originals": 1.3,
      "date": "2025-03-27"
    },
    {
      "rank": 340,
      "title": "潘粤明评国足8场6败",
      "category": "明星",
      "heat": 10.57,
      "reads": 915.3,
      "discussions": 0.05,
      "originals": 0.01,
      "date": "2025-03-27"
    },
    {
      "rank": 341,
      "title": "柯淳这阴湿男鬼味",
      "category": "",
      "heat": 10.55,
      "reads": 6.0,
      "discussions": 0.02,
      "originals": 0.0,
      "date": "2025-03-27"
    },
    {
      "rank": 342,
      "title": "何俊宏爱玩游戏成工作优势",
      "category": "",
      "heat": 10.49,
      "reads": 2503.0,
      "discussions": 0.38,
      "originals": 0.0,
      "date": "2025-03-27"
    },
    {
      "rank": 343,
      "title": "刘耀文Chapter03",
      "category": "",
      "heat": 10.46,
      "reads": 15.2,
      "discussions": 0.08,
      "originals": 0.02,
      "date": "2025-03-27"
    },
    {
      "rank": 344,
      "title": "于正谈爆剧又爆人",
      "category": "社会",
      "heat": 10.45,
      "reads": 822.4,
      "discussions": 0.03,
      "originals": 0.01,
      "date": "2025-03-27"
    },
    {
      "rank": 345,
      "title": "国际乒联称樊振东是世界杯之王",
      "category": "体育",
      "heat": 10.44,
      "reads": 400.8,
      "discussions": 0.31,
      "originals": 0.09,
      "date": "2025-03-27"
    },
    {
      "rank": 346,
      "title": "消息称谷歌将停止Android开源项目",
      "category": "财经",
      "heat": 10.22,
      "reads": 62.0,
      "discussions": 0.01,
      "originals": 0.0,
      "date": "2025-03-27"
    },
    {
      "rank": 347,
      "title": "孟子义李昀锐校园风造型",
      "category": "明星",
      "heat": 10.18,
      "reads": 332.0,
      "discussions": 0.11,
      "originals": 0.02,
      "date": "2025-03-27"
    },
    {
      "rank": 348,
      "title": "苹果电影模式 大疆效果",
      "category": "",
      "heat": 10.12,
      "reads": 29.0,
      "discussions": 0.01,
      "originals": 0.0,
      "date": "2025-03-27"
    },
    {
      "rank": 349,
      "title": "魏大勋小小的侦探脾气爆",
      "category": "",
      "heat": 10.02,
      "reads": 69.8,
      "discussions": 0.68,
      "originals": 0.06,
      "date": "2025-03-27"
    },
    {
      "rank": 350,
      "title": "iG全神班五连胜",
      "category": "游戏",
      "heat": 9.91,
      "reads": 449.1,
      "discussions": 0.09,
      "originals": 0.01,
      "date": "2025-03-27"
    },
    {
      "rank": 351,
      "title": "王安宇哭戏从青年到中年",
      "category": "",
      "heat": 9.91,
      "reads": 71.9,
      "discussions": 0.49,
      "originals": 0.02,
      "date": "2025-03-27"
    },
    {
      "rank": 352,
      "title": "短剧家里家外拍摄17天成本仅300万",
      "category": "电视剧",
      "heat": 9.75,
      "reads": 2044.2,
      "discussions": 0.11,
      "originals": 0.02,
      "date": "2025-03-27"
    },
    {
      "rank": 353,
      "title": "东北夫妻在淮安开店遭刁难亏本后续",
      "category": "社会",
      "heat": 9.68,
      "reads": 534.9,
      "discussions": 0.04,
      "originals": 0.0,
      "date": "2025-03-27"
    },
    {
      "rank": 354,
      "title": "王安宇王玉雯新剧18年爱情长跑",
      "category": "",
      "heat": 9.68,
      "reads": 226.3,
      "discussions": 0.6,
      "originals": 0.03,
      "date": "2025-03-27"
    },
    {
      "rank": 355,
      "title": "戍边民警对女儿说伤疤是爸爸的勋章",
      "category": "社会",
      "heat": 9.62,
      "reads": 289.3,
      "discussions": 0.08,
      "originals": 0.02,
      "date": "2025-03-27"
    },
    {
      "rank": 356,
      "title": "廊坊2.2级地震",
      "category": "",
      "heat": 9.57,
      "reads": 6.8,
      "discussions": 0.0,
      "originals": 0.0,
      "date": "2025-03-27"
    },
    {
      "rank": 357,
      "title": "B站网红大祥哥被骗1249万",
      "category": "社会",
      "heat": 9.43,
      "reads": 1381.5,
      "discussions": 0.04,
      "originals": 0.01,
      "date": "2025-03-27"
    },
    {
      "rank": 358,
      "title": "萨摩耶绝育后的哭声响彻整个医院",
      "category": "搞笑",
      "heat": 9.29,
      "reads": 958.7,
      "discussions": 0.03,
      "originals": 0.01,
      "date": "2025-03-27"
    },
    {
      "rank": 359,
      "title": "杨超越马里奥造型",
      "category": "明星",
      "heat": 9.23,
      "reads": 581.0,
      "discussions": 0.15,
      "originals": 0.04,
      "date": "2025-03-27"
    },
    {
      "rank": 360,
      "title": "李晟回应断层第一",
      "category": "明星",
      "heat": 9.2,
      "reads": 18000.0,
      "discussions": 3.9,
      "originals": 0.62,
      "date": "2025-03-27"
    },
    {
      "rank": 361,
      "title": "美高官群聊完整记录公布",
      "category": "",
      "heat": 8.95,
      "reads": 543.2,
      "discussions": 0.15,
      "originals": 0.0,
      "date": "2025-03-27"
    },
    {
      "rank": 362,
      "title": "莲花味精被传穷得只剩1栋办公楼",
      "category": "社会",
      "heat": 8.91,
      "reads": 1126.8,
      "discussions": 0.04,
      "originals": 0.01,
      "date": "2025-03-27"
    },
    {
      "rank": 363,
      "title": "jiejie采访",
      "category": "游戏",
      "heat": 8.9,
      "reads": 551.5,
      "discussions": 0.07,
      "originals": 0.0,
      "date": "2025-03-27"
    },
    {
      "rank": 364,
      "title": "娜扎猜猜头上有多少个卡子",
      "category": "明星",
      "heat": 8.59,
      "reads": 1000.7,
      "discussions": 0.03,
      "originals": 0.01,
      "date": "2025-03-27"
    },
    {
      "rank": 365,
      "title": "燃罪最大的刀来了",
      "category": "",
      "heat": 8.56,
      "reads": 17.4,
      "discussions": 0.36,
      "originals": 0.0,
      "date": "2025-03-27"
    },
    {
      "rank": 366,
      "title": "考北大的意义在这一刻具像化了",
      "category": "",
      "heat": 8.42,
      "reads": 291.9,
      "discussions": 0.38,
      "originals": 0.01,
      "date": "2025-03-27"
    },
    {
      "rank": 367,
      "title": "短视频应用人均单日使用156分钟",
      "category": "社会",
      "heat": 8.4,
      "reads": 749.9,
      "discussions": 0.11,
      "originals": 0.01,
      "date": "2025-03-27"
    },
    {
      "rank": 368,
      "title": "田曦薇小红裙进妆look",
      "category": "明星",
      "heat": 8.09,
      "reads": 1568.2,
      "discussions": 0.42,
      "originals": 0.08,
      "date": "2025-03-27"
    },
    {
      "rank": 369,
      "title": "湖人vs步行者",
      "category": "体育",
      "heat": 8.0,
      "reads": 26000.0,
      "discussions": 5.2,
      "originals": 0.27,
      "date": "2025-03-27"
    },
    {
      "rank": 370,
      "title": "KSG17淘汰吃鸡",
      "category": "游戏",
      "heat": 7.94,
      "reads": 80.2,
      "discussions": 0.08,
      "originals": 0.01,
      "date": "2025-03-27"
    },
    {
      "rank": 371,
      "title": "食品日期标注字体将更醒目",
      "category": "社会",
      "heat": 7.78,
      "reads": 214.4,
      "discussions": 0.06,
      "originals": 0.01,
      "date": "2025-03-27"
    },
    {
      "rank": 372,
      "title": "刘诗诗林允儿活动同框",
      "category": "明星",
      "heat": 7.24,
      "reads": 2314.8,
      "discussions": 1.2,
      "originals": 0.13,
      "date": "2025-03-27"
    },
    {
      "rank": 373,
      "title": "曾黎工作室报案",
      "category": "明星",
      "heat": 6.98,
      "reads": 2269.6,
      "discussions": 0.13,
      "originals": 0.02,
      "date": "2025-03-27"
    },
    {
      "rank": 374,
      "title": "芒果TV调整会员同时使用设备数",
      "category": "财经",
      "heat": 6.54,
      "reads": 5426.4,
      "discussions": 1.3,
      "originals": 0.43,
      "date": "2025-03-27"
    },
    {
      "rank": 375,
      "title": "被碾压致死5岁女童家属出具谅解书",
      "category": "社会",
      "heat": 6.49,
      "reads": 4032.9,
      "discussions": 0.41,
      "originals": 0.06,
      "date": "2025-03-27"
    },
    {
      "rank": 376,
      "title": "睡觉时遇到地震咋办",
      "category": "社会",
      "heat": 6.34,
      "reads": 1195.8,
      "discussions": 0.28,
      "originals": 0.05,
      "date": "2025-03-27"
    },
    {
      "rank": 377,
      "title": "赴山海 备播",
      "category": "",
      "heat": 6.15,
      "reads": 871.0,
      "discussions": 3.8,
      "originals": 0.59,
      "date": "2025-03-27"
    },
    {
      "rank": 378,
      "title": "沈阳多家公司被指要求求职者无薪试岗",
      "category": "社会",
      "heat": 6.0,
      "reads": 646.2,
      "discussions": 0.08,
      "originals": 0.01,
      "date": "2025-03-27"
    },
    {
      "rank": 379,
      "title": "警方通报高铁脱鞋放脚打人男被行拘",
      "category": "社会",
      "heat": 5.95,
      "reads": 1959.1,
      "discussions": 0.3,
      "originals": 0.05,
      "date": "2025-03-27"
    },
    {
      "rank": 380,
      "title": "第五人格",
      "category": "游戏",
      "heat": 5.72,
      "reads": 1916000.0,
      "discussions": 1897.3,
      "originals": 154.9,
      "date": "2025-03-27"
    },
    {
      "rank": 381,
      "title": "晒工资条能泄漏什么核心机密呢",
      "category": "社会",
      "heat": 5.6,
      "reads": 1155.7,
      "discussions": 0.1,
      "originals": 0.02,
      "date": "2025-03-27"
    },
    {
      "rank": 382,
      "title": "中方驳斥美方年复一年所谓中国威胁论",
      "category": "社会",
      "heat": 5.36,
      "reads": 253.3,
      "discussions": 0.04,
      "originals": 0.01,
      "date": "2025-03-27"
    },
    {
      "rank": 383,
      "title": "新还珠格格的歌大部分是李晟唱的",
      "category": "明星",
      "heat": 5.3,
      "reads": 973.8,
      "discussions": 0.04,
      "originals": 0.01,
      "date": "2025-03-27"
    },
    {
      "rank": 384,
      "title": "银河左岸音乐节",
      "category": "音乐",
      "heat": 5.29,
      "reads": 25000.0,
      "discussions": 455.0,
      "originals": 0.6,
      "date": "2025-03-27"
    },
    {
      "rank": 385,
      "title": "沙溢 美黑",
      "category": "",
      "heat": 5.18,
      "reads": 2023.8,
      "discussions": 0.62,
      "originals": 0.26,
      "date": "2025-03-27"
    },
    {
      "rank": 386,
      "title": "世界上最顶尖的大学排名",
      "category": "",
      "heat": 5.17,
      "reads": 248.6,
      "discussions": 0.07,
      "originals": 0.01,
      "date": "2025-03-27"
    },
    {
      "rank": 387,
      "title": "昀牵孟绕",
      "category": "明星",
      "heat": 4.88,
      "reads": 134000.0,
      "discussions": 171.7,
      "originals": 7.1,
      "date": "2025-03-27"
    },
    {
      "rank": 388,
      "title": "晒工资被开除山姆试吃员签保密协议",
      "category": "社会",
      "heat": 4.85,
      "reads": 11000.0,
      "discussions": 0.95,
      "originals": 0.21,
      "date": "2025-03-27"
    },
    {
      "rank": 389,
      "title": "地震逃生千万别坐电梯",
      "category": "社会",
      "heat": 4.54,
      "reads": 300.4,
      "discussions": 0.24,
      "originals": 0.02,
      "date": "2025-03-27"
    },
    {
      "rank": 390,
      "title": "乘风2025姐姐乘风值",
      "category": "综艺",
      "heat": 4.42,
      "reads": 1039.2,
      "discussions": 32.2,
      "originals": 6.6,
      "date": "2025-03-27"
    },
    {
      "rank": 391,
      "title": "喜酒吃到一半一群医护冲刺救人",
      "category": "社会",
      "heat": 3.86,
      "reads": 524.0,
      "discussions": 0.05,
      "originals": 0.01,
      "date": "2025-03-27"
    },
    {
      "rank": 392,
      "title": "微短剧用户规模达6.62亿人",
      "category": "社会",
      "heat": 3.29,
      "reads": 200.4,
      "discussions": 0.06,
      "originals": 0.0,
      "date": "2025-03-27"
    },
    {
      "rank": 393,
      "title": "学校称虐猫致死男生在接受心理治疗",
      "category": "社会",
      "heat": 3.23,
      "reads": 256.5,
      "discussions": 0.03,
      "originals": 0.01,
      "date": "2025-03-27"
    },
    {
      "rank": 394,
      "title": "谢淮安谋士人设",
      "category": "",
      "heat": 3.2,
      "reads": 253.5,
      "discussions": 2.4,
      "originals": 0.14,
      "date": "2025-03-27"
    },
    {
      "rank": 395,
      "title": "农民大婶的诗让春天具象化了",
      "category": "社会",
      "heat": 3.2,
      "reads": 338.0,
      "discussions": 0.07,
      "originals": 0.01,
      "date": "2025-03-27"
    },
    {
      "rank": 396,
      "title": "你的班味可能是臭味",
      "category": "社会",
      "heat": 3.2,
      "reads": 263.1,
      "discussions": 0.02,
      "originals": 0.0,
      "date": "2025-03-27"
    },
    {
      "rank": 397,
      "title": "号称3天减10斤减肥产品含利尿剂",
      "category": "社会",
      "heat": 3.19,
      "reads": 2218.4,
      "discussions": 0.16,
      "originals": 0.03,
      "date": "2025-03-27"
    },
    {
      "rank": 398,
      "title": "赵小童穿羽绒服吃鸡西冷面",
      "category": "明星",
      "heat": 3.19,
      "reads": 212.5,
      "discussions": 0.12,
      "originals": 0.0,
      "date": "2025-03-27"
    }
  ]
}